Workbook

Sheet Error Checking
B2: =SUM(B3:B9) -> 0 | D2: Master Error Check Cell
B4: =SUM('13 weeks CF'!14:14) -> 0 | D4: Cash Forecast doesn't match Actual data
B5: =SUM('Summary Dashboard'!14:14) -> 0 | D5: Summary doesn't match the Cash Flow Forecast
B6: =SUM('Rolling CF'!14:14) -> 0 | D6: Cash Forecast 02 doesn't match Actual data
B7: =SUM('Variance Analysis'!20:20) -> 0 | D7: Variance Report doesn't match Cash Forecast
D9: Put all additional error checks above this line

Sheet INSTRUCTIONS
B2: File Update Instructions
B3: Last Updated: XX/XX/XXXX
B5: Week Ending | D5: 45269
B7: Save as new version. | D7: x
B9: Duplicate Cash Forecast Tab | D9: x
B11: Bring Error Check to Error Checking Tab | D11: x
B13: Copy/paste last week's forecast to new forecast | D13: x
B15: Bring in new Bank Data. | D15: x
B17: Add Transaction Numbers & drag down helper formulas. | D17: x
B19: Make sure any checks over $3,000 are tagged to AP. | D19: x
B21: Copy AP Aging Report & bring in new data. | D21: x
B23: Copy AR Aging Report & bring in new data. | D23: x
B25: Drag "Actual" along top of new Cash Forecast. | D25: x
B27: Drag forward all SUMIFS formulas. | D27: x
B29: Copy/paste Ending Cash balance (and fix any variances). | D29: x
... B47: Final Review & distribute report. | D47: x

Sheet Summary Dashboard
B2: Master Error Check Cell | C2: ='Error Checking'!$B$2 -> 0
B4: Actual / Forecast | D4: Actual | E4: Actual | F4: Actual | G4: Actual | H4: Actual | I4: Actual | J4: Forecast | K4: Forecast | L4: Forecast | M4: Forecast | N4: Forecast | O4: Forecast | P4: Forecast | Q4: Forecast | R4: Forecast | S4: Forecast | T4: Forecast | U4: Forecast | V4: Forecast
B5: Week Number | D5: 1 | E5: =D5+1 -> 2 | F5: =E5+1 -> 3 | G5: =F5+1 -> 4 | H5: =G5+1 -> 5 | I5: =H5+1 -> 6 | J5: =I5+1 -> 7 | K5: =J5+1 -> 8 | L5: =K5+1 -> 9 | ... V5: =U5+1 -> 19
B6: Week Beginning | D6: =D7-6 -> 45228 | E6: =E7-6 -> 45235 | F6: =F7-6 -> 45242 | G6: =G7-6 -> 45249 | H6: =H7-6 -> 45256 | I6: =I7-6 -> 45263 | J6: =J7-6 -> 45270 | K6: =K7-6 -> 45277 | ... V6: =V7-6 -> 45354
B7: Week Ending | C7: Forecast Methodology | D7: =E6-1 -> 45234 | E7: =F6-1 -> 45241 | F7: =G6-1 -> 45248 | G7: =H6-1 -> 45255 | H7: =I6-1 -> 45262 | I7: =J6-1 -> 45269 | J7: =K6-1 -> 45276 | K7: =L6-1 -> 45283 | ... U7: =V6-1 -> 45353 | V7: =MAX('Rolling CF'!$7:$7) -> 45360
B9: Cash Balance
B10: Beginning Cash | D10: =INDEX('Rolling CF'!$1:$1048576,MATCH($B10,'Rolling CF'!$C:$C,0),MATCH(D$7,'Rolling CF'!$7:$7,0)) -> 210210 | E10: =D12 -> 174090 | F10: =E12 -> 239110 | G10: =F12 -> 43360 | H10: =G12 -> 325260 | I10: =H12 -> 215160 | J10: =I12 -> 108940 | K10: =J12 -> 160208.33 | L10: =K12 -> 489131.39 | ... V10: =U12 -> -137705.13
B11: Change in Cash | D11: =D76 -> -36120 | E11: =E76 -> 65020 | F11: =F76 -> -195750 | G11: =G76 -> 281900 | H11: =H76 -> -110100 | I11: =I76 -> -106220 | J11: =J76 -> 51268.333 | K11: =K76 -> 328923.06 | ... V11: =V76 -> -59244.097
B12: Ending Cash | D12: =SUM(D10:D11) -> 174090 | E12: =SUM(E10:E11) -> 239110 | F12: =SUM(F10:F11) -> 43360 | G12: =SUM(G10:G11) -> 325260 | H12: =SUM(H10:H11) -> 215160 | I12: =SUM(I10:I11) -> 108940 | J12: =SUM(J10:J11) -> 160208.33 | K12: =SUM(K10:K11) -> 489131.39 | ... V12: =SUM(V10:V11) -> -196949.22
B13: Per Data | D13: =INDEX('Rolling CF'!$1:$1048576,MATCH($B13,'Rolling CF'!$C:$C,0),MATCH(D$7,'Rolling CF'!$7:$7,0)) -> 174090 | E13: =INDEX('Rolling CF'!$1:$1048576,MATCH($B13,'Rolling CF'!$C:$C,0),MATCH(E$7,'Rolling CF'!$7:$7,0)) -> 239110 | F13: =INDEX('Rolling CF'!$1:$1048576,MATCH($B13,'Rolling CF'!$C:$C,0),MATCH(F$7,'Rolling CF'!$7:$7,0)) -> 43360 | G13: =INDEX('Rolling CF'!$1:$1048576,MATCH($B13,'Rolling CF'!$C:$C,0),MATCH(G$7,'Rolling CF'!$7:$7,0)) -> 325260 | H13: =INDEX('Rolling CF'!$1:$1048576,MATCH($B13,'Rolling CF'!$C:$C,0),MATCH(H$7,'Rolling CF'!$7:$7,0)) -> 215160 | I13: =INDEX('Rolling CF'!$1:$1048576,MATCH($B13,'Rolling CF'!$C:$C,0),MATCH(I$7,'Rolling CF'!$7:$7,0)) -> 108940 | J13: =INDEX('Rolling CF'!$1:$1048576,MATCH($B13,'Rolling CF'!$C:$C,0),MATCH(J$7,'Rolling CF'!$7:$7,0)) -> 0 | K13: =INDEX('Rolling CF'!$1:$1048576,MATCH($B13,'Rolling CF'!$C:$C,0),MATCH(K$7,'Rolling CF'!$7:$7,0)) -> 0 | ... V13: =INDEX('Rolling CF'!$1:$1048576,MATCH($B13,'Rolling CF'!$C:$C,0),MATCH(V$7,'Rolling CF'!$7:$7,0)) -> 0
B14: Double-Check | D14: =IF(D$4="Forecast",0,D13-D12) -> 0 | E14: =IF(E$4="Forecast",0,E13-E12) -> 0 | F14: =IF(F$4="Forecast",0,F13-F12) -> 0 | G14: =IF(G$4="Forecast",0,G13-G12) -> 0 | H14: =IF(H$4="Forecast",0,H13-H12) -> 0 | I14: =IF(I$4="Forecast",0,I13-I12) -> 0 | J14: =IF(J$4="Forecast",0,J13-J12) -> 0 | K14: =IF(K$4="Forecast",0,K13-K12) -> 0 | ... V14: =IF(V$4="Forecast",0,V13-V12) -> 0
B15: Last Week's Forecast | D15: =INDEX('Rolling CF'!$1:$1048576,MATCH($B15,'Rolling CF'!$C:$C,0),MATCH(D$7,'Rolling CF'!$7:$7,0)) -> 174090 | E15: =INDEX('Rolling CF'!$1:$1048576,MATCH($B15,'Rolling CF'!$C:$C,0),MATCH(E$7,'Rolling CF'!$7:$7,0)) -> 239110 | F15: =INDEX('Rolling CF'!$1:$1048576,MATCH($B15,'Rolling CF'!$C:$C,0),MATCH(F$7,'Rolling CF'!$7:$7,0)) -> 43360 | G15: =INDEX('Rolling CF'!$1:$1048576,MATCH($B15,'Rolling CF'!$C:$C,0),MATCH(G$7,'Rolling CF'!$7:$7,0)) -> 325260 | H15: =INDEX('Rolling CF'!$1:$1048576,MATCH($B15,'Rolling CF'!$C:$C,0),MATCH(H$7,'Rolling CF'!$7:$7,0)) -> 215160 | I15: =INDEX('Rolling CF'!$1:$1048576,MATCH($B15,'Rolling CF'!$C:$C,0),MATCH(I$7,'Rolling CF'!$7:$7,0)) -> 112041.67 | J15: =INDEX('Rolling CF'!$1:$1048576,MATCH($B15,'Rolling CF'!$C:$C,0),MATCH(J$7,'Rolling CF'!$7:$7,0)) -> 156995.28 | K15: =INDEX('Rolling CF'!$1:$1048576,MATCH($B15,'Rolling CF'!$C:$C,0),MATCH(K$7,'Rolling CF'!$7:$7,0)) -> 399451.16 | ... V15: =INDEX('Rolling CF'!$1:$1048576,MATCH($B15,'Rolling CF'!$C:$C,0),MATCH(V$7,'Rolling CF'!$7:$7,0)) -> 0
B34: Cash Inflows
B35: Invoiced AR + New Revenue | C35: See AR Aging Schedule | D35: =INDEX('Rolling CF'!$1:$1048576,MATCH($B35,'Rolling CF'!$C:$C,0),MATCH(D$7,'Rolling CF'!$7:$7,0)) -> 372100 | E35: =INDEX('Rolling CF'!$1:$1048576,MATCH($B35,'Rolling CF'!$C:$C,0),MATCH(E$7,'Rolling CF'!$7:$7,0)) -> 210150 | F35: =INDEX('Rolling CF'!$1:$1048576,MATCH($B35,'Rolling CF'!$C:$C,0),MATCH(F$7,'Rolling CF'!$7:$7,0)) -> 0 | G35: =INDEX('Rolling CF'!$1:$1048576,MATCH($B35,'Rolling CF'!$C:$C,0),MATCH(G$7,'Rolling CF'!$7:$7,0)) -> 361430 | H35: =INDEX('Rolling CF'!$1:$1048576,MATCH($B35,'Rolling CF'!$C:$C,0),MATCH(H$7,'Rolling CF'!$7:$7,0)) -> 68440 | I35: =INDEX('Rolling CF'!$1:$1048576,MATCH($B35,'Rolling CF'!$C:$C,0),MATCH(I$7,'Rolling CF'!$7:$7,0)) -> 389470 | J35: =INDEX('Rolling CF'!$1:$1048576,MATCH($B35,'Rolling CF'!$C:$C,0),MATCH(J$7,'Rolling CF'!$7:$7,0)) -> 120000 | K35: =INDEX('Rolling CF'!$1:$1048576,MATCH($B35,'Rolling CF'!$C:$C,0),MATCH(K$7,'Rolling CF'!$7:$7,0)) -> 554000 | ... V35: =INDEX('Rolling CF'!$1:$1048576,MATCH($B35,'Rolling CF'!$C:$C,0),MATCH(V$7,'Rolling CF'!$7:$7,0)) -> 0
B36: Other Inflows | C36: Enter Manually | D36: =INDEX('Rolling CF'!$1:$1048576,MATCH($B36,'Rolling CF'!$C:$C,0),MATCH(D$7,'Rolling CF'!$7:$7,0)) -> 0 | E36: =INDEX('Rolling CF'!$1:$1048576,MATCH($B36,'Rolling CF'!$C:$C,0),MATCH(E$7,'Rolling CF'!$7:$7,0)) -> 0 | F36: =INDEX('Rolling CF'!$1:$1048576,MATCH($B36,'Rolling CF'!$C:$C,0),MATCH(F$7,'Rolling CF'!$7:$7,0)) -> 0 | G36: =INDEX('Rolling CF'!$1:$1048576,MATCH($B36,'Rolling CF'!$C:$C,0),MATCH(G$7,'Rolling CF'!$7:$7,0)) -> 0 | H36: =INDEX('Rolling CF'!$1:$1048576,MATCH($B36,'Rolling CF'!$C:$C,0),MATCH(H$7,'Rolling CF'!$7:$7,0)) -> 0 | I36: =INDEX('Rolling CF'!$1:$1048576,MATCH($B36,'Rolling CF'!$C:$C,0),MATCH(I$7,'Rolling CF'!$7:$7,0)) -> 0 | J36: =INDEX('Rolling CF'!$1:$1048576,MATCH($B36,'Rolling CF'!$C:$C,0),MATCH(J$7,'Rolling CF'!$7:$7,0)) -> 0 | K36: =INDEX('Rolling CF'!$1:$1048576,MATCH($B36,'Rolling CF'!$C:$C,0),MATCH(K$7,'Rolling CF'!$7:$7,0)) -> 0 | ... V36: =INDEX('Rolling CF'!$1:$1048576,MATCH($B36,'Rolling CF'!$C:$C,0),MATCH(V$7,'Rolling CF'!$7:$7,0)) -> 0
B38: Total Cash Inflows | D38: =SUM(D35:D37) -> 372100 | E38: =SUM(E35:E37) -> 210150 | F38: =SUM(F35:F37) -> 0 | G38: =SUM(G35:G37) -> 361430 | H38: =SUM(H35:H37) -> 68440 | I38: =SUM(I35:I37) -> 389470 | J38: =SUM(J35:J37) -> 120000 | K38: =SUM(K35:K37) -> 554000 | ... V38: =SUM(V35:V37) -> 0
B40: Operating Cash Outflows
B41: Accounts Payable | C41: See AP Aging Schedule | D41: =INDEX('Rolling CF'!$1:$1048576,MATCH($B41,'Rolling CF'!$C:$C,0),MATCH(D$7,'Rolling CF'!$7:$7,0)) -> -83210 | E41: =INDEX('Rolling CF'!$1:$1048576,MATCH($B41,'Rolling CF'!$C:$C,0),MATCH(E$7,'Rolling CF'!$7:$7,0)) -> -69810 | F41: =INDEX('Rolling CF'!$1:$1048576,MATCH($B41,'Rolling CF'!$C:$C,0),MATCH(F$7,'Rolling CF'!$7:$7,0)) -> -40140 | G41: =INDEX('Rolling CF'!$1:$1048576,MATCH($B41,'Rolling CF'!$C:$C,0),MATCH(G$7,'Rolling CF'!$7:$7,0)) -> -18680 | H41: =INDEX('Rolling CF'!$1:$1048576,MATCH($B41,'Rolling CF'!$C:$C,0),MATCH(H$7,'Rolling CF'!$7:$7,0)) -> -88580 | I41: =INDEX('Rolling CF'!$1:$1048576,MATCH($B41,'Rolling CF'!$C:$C,0),MATCH(I$7,'Rolling CF'!$7:$7,0)) -> -89740 | J41: =INDEX('Rolling CF'!$1:$1048576,MATCH($B41,'Rolling CF'!$C:$C,0),MATCH(J$7,'Rolling CF'!$7:$7,0)) -> 0 | K41: =INDEX('Rolling CF'!$1:$1048576,MATCH($B41,'Rolling CF'!$C:$C,0),MATCH(K$7,'Rolling CF'!$7:$7,0)) -> -164600 | ... V41: =INDEX('Rolling CF'!$1:$1048576,MATCH($B41,'Rolling CF'!$C:$C,0),MATCH(V$7,'Rolling CF'!$7:$7,0)) -> 0
B42: Credit Cards | C42: See AP Aging Schedule | D42: =INDEX('Rolling CF'!$1:$1048576,MATCH($B42,'Rolling CF'!$C:$C,0),MATCH(D$7,'Rolling CF'!$7:$7,0)) -> -194090 | E42: =INDEX('Rolling CF'!$1:$1048576,MATCH($B42,'Rolling CF'!$C:$C,0),MATCH(E$7,'Rolling CF'!$7:$7,0)) -> 0 | F42: =INDEX('Rolling CF'!$1:$1048576,MATCH($B42,'Rolling CF'!$C:$C,0),MATCH(F$7,'Rolling CF'!$7:$7,0)) -> -100000 | G42: =INDEX('Rolling CF'!$1:$1048576,MATCH($B42,'Rolling CF'!$C:$C,0),MATCH(G$7,'Rolling CF'!$7:$7,0)) -> 0 | H42: =INDEX('Rolling CF'!$1:$1048576,MATCH($B42,'Rolling CF'!$C:$C,0),MATCH(H$7,'Rolling CF'!$7:$7,0)) -> -32000 | I42: =INDEX('Rolling CF'!$1:$1048576,MATCH($B42,'Rolling CF'!$C:$C,0),MATCH(I$7,'Rolling CF'!$7:$7,0)) -> -350210 | J42: =INDEX('Rolling CF'!$1:$1048576,MATCH($B42,'Rolling CF'!$C:$C,0),MATCH(J$7,'Rolling CF'!$7:$7,0)) -> 0 | K42: =INDEX('Rolling CF'!$1:$1048576,MATCH($B42,'Rolling CF'!$C:$C,0),MATCH(K$7,'Rolling CF'!$7:$7,0)) -> 0 | ... V42: =INDEX('Rolling CF'!$1:$1048576,MATCH($B42,'Rolling CF'!$C:$C,0),MATCH(V$7,'Rolling CF'!$7:$7,0)) -> 0
B43: Payroll | C43: Trailing 6 Week Average | D43: =INDEX('Rolling CF'!$1:$1048576,MATCH($B43,'Rolling CF'!$C:$C,0),MATCH(D$7,'Rolling CF'!$7:$7,0)) -> -78050 | E43: =INDEX('Rolling CF'!$1:$1048576,MATCH($B43,'Rolling CF'!$C:$C,0),MATCH(E$7,'Rolling CF'!$7:$7,0)) -> -51670 | F43: =INDEX('Rolling CF'!$1:$1048576,MATCH($B43,'Rolling CF'!$C:$C,0),MATCH(F$7,'Rolling CF'!$7:$7,0)) -> -39960 | G43: =INDEX('Rolling CF'!$1:$1048576,MATCH($B43,'Rolling CF'!$C:$C,0),MATCH(G$7,'Rolling CF'!$7:$7,0)) -> -44380 | H43: =INDEX('Rolling CF'!$1:$1048576,MATCH($B43,'Rolling CF'!$C:$C,0),MATCH(H$7,'Rolling CF'!$7:$7,0)) -> -35340 | I43: =INDEX('Rolling CF'!$1:$1048576,MATCH($B43,'Rolling CF'!$C:$C,0),MATCH(I$7,'Rolling CF'!$7:$7,0)) -> -35660 | J43: =INDEX('Rolling CF'!$1:$1048576,MATCH($B43,'Rolling CF'!$C:$C,0),MATCH(J$7,'Rolling CF'!$7:$7,0)) -> -47510 | K43: =INDEX('Rolling CF'!$1:$1048576,MATCH($B43,'Rolling CF'!$C:$C,0),MATCH(K$7,'Rolling CF'!$7:$7,0)) -> -42420 | ... V43: =INDEX('Rolling CF'!$1:$1048576,MATCH($B43,'Rolling CF'!$C:$C,0),MATCH(V$7,'Rolling CF'!$7:$7,0)) -> -41500.77
B44: Contractors | C44: Enter Manually | D44: =INDEX('Rolling CF'!$1:$1048576,MATCH($B44,'Rolling CF'!$C:$C,0),MATCH(D$7,'Rolling CF'!$7:$7,0)) -> 0 | E44: =INDEX('Rolling CF'!$1:$1048576,MATCH($B44,'Rolling CF'!$C:$C,0),MATCH(E$7,'Rolling CF'!$7:$7,0)) -> 0 | F44: =INDEX('Rolling CF'!$1:$1048576,MATCH($B44,'Rolling CF'!$C:$C,0),MATCH(F$7,'Rolling CF'!$7:$7,0)) -> 0 | G44: =INDEX('Rolling CF'!$1:$1048576,MATCH($B44,'Rolling CF'!$C:$C,0),MATCH(G$7,'Rolling CF'!$7:$7,0)) -> 0 | H44: =INDEX('Rolling CF'!$1:$1048576,MATCH($B44,'Rolling CF'!$C:$C,0),MATCH(H$7,'Rolling CF'!$7:$7,0)) -> 0 | I44: =INDEX('Rolling CF'!$1:$1048576,MATCH($B44,'Rolling CF'!$C:$C,0),MATCH(I$7,'Rolling CF'!$7:$7,0)) -> 0 | J44: =INDEX('Rolling CF'!$1:$1048576,MATCH($B44,'Rolling CF'!$C:$C,0),MATCH(J$7,'Rolling CF'!$7:$7,0)) -> 0 | K44: =INDEX('Rolling CF'!$1:$1048576,MATCH($B44,'Rolling CF'!$C:$C,0),MATCH(K$7,'Rolling CF'!$7:$7,0)) -> 0 | ... V44: =INDEX('Rolling CF'!$1:$1048576,MATCH($B44,'Rolling CF'!$C:$C,0),MATCH(V$7,'Rolling CF'!$7:$7,0)) -> 0
B45: Dues & Subscriptions | C45: Trailing 6 Week Average | D45: =INDEX('Rolling CF'!$1:$1048576,MATCH($B45,'Rolling CF'!$C:$C,0),MATCH(D$7,'Rolling CF'!$7:$7,0)) -> -310 | E45: =INDEX('Rolling CF'!$1:$1048576,MATCH($B45,'Rolling CF'!$C:$C,0),MATCH(E$7,'Rolling CF'!$7:$7,0)) -> -310 | F45: =INDEX('Rolling CF'!$1:$1048576,MATCH($B45,'Rolling CF'!$C:$C,0),MATCH(F$7,'Rolling CF'!$7:$7,0)) -> -310 | G45: =INDEX('Rolling CF'!$1:$1048576,MATCH($B45,'Rolling CF'!$C:$C,0),MATCH(G$7,'Rolling CF'!$7:$7,0)) -> -310 | H45: =INDEX('Rolling CF'!$1:$1048576,MATCH($B45,'Rolling CF'!$C:$C,0),MATCH(H$7,'Rolling CF'!$7:$7,0)) -> -310 | I45: =INDEX('Rolling CF'!$1:$1048576,MATCH($B45,'Rolling CF'!$C:$C,0),MATCH(I$7,'Rolling CF'!$7:$7,0)) -> -310 | J45: =INDEX('Rolling CF'!$1:$1048576,MATCH($B45,'Rolling CF'!$C:$C,0),MATCH(J$7,'Rolling CF'!$7:$7,0)) -> -310 | K45: =INDEX('Rolling CF'!$1:$1048576,MATCH($B45,'Rolling CF'!$C:$C,0),MATCH(K$7,'Rolling CF'!$7:$7,0)) -> -310 | ... V45: =INDEX('Rolling CF'!$1:$1048576,MATCH($B45,'Rolling CF'!$C:$C,0),MATCH(V$7,'Rolling CF'!$7:$7,0)) -> -310
B46: Insurance | C46: Enter Manually | D46: =INDEX('Rolling CF'!$1:$1048576,MATCH($B46,'Rolling CF'!$C:$C,0),MATCH(D$7,'Rolling CF'!$7:$7,0)) -> 0 | E46: =INDEX('Rolling CF'!$1:$1048576,MATCH($B46,'Rolling CF'!$C:$C,0),MATCH(E$7,'Rolling CF'!$7:$7,0)) -> 0 | F46: =INDEX('Rolling CF'!$1:$1048576,MATCH($B46,'Rolling CF'!$C:$C,0),MATCH(F$7,'Rolling CF'!$7:$7,0)) -> 0 | G46: =INDEX('Rolling CF'!$1:$1048576,MATCH($B46,'Rolling CF'!$C:$C,0),MATCH(G$7,'Rolling CF'!$7:$7,0)) -> 0 | H46: =INDEX('Rolling CF'!$1:$1048576,MATCH($B46,'Rolling CF'!$C:$C,0),MATCH(H$7,'Rolling CF'!$7:$7,0)) -> 0 | I46: =INDEX('Rolling CF'!$1:$1048576,MATCH($B46,'Rolling CF'!$C:$C,0),MATCH(I$7,'Rolling CF'!$7:$7,0)) -> 0 | J46: =INDEX('Rolling CF'!$1:$1048576,MATCH($B46,'Rolling CF'!$C:$C,0),MATCH(J$7,'Rolling CF'!$7:$7,0)) -> 0 | K46: =INDEX('Rolling CF'!$1:$1048576,MATCH($B46,'Rolling CF'!$C:$C,0),MATCH(K$7,'Rolling CF'!$7:$7,0)) -> 0 | ... V46: =INDEX('Rolling CF'!$1:$1048576,MATCH($B46,'Rolling CF'!$C:$C,0),MATCH(V$7,'Rolling CF'!$7:$7,0)) -> 0
B47: Lease Payments | C47: Trailing 6 Week Average | D47: =INDEX('Rolling CF'!$1:$1048576,MATCH($B47,'Rolling CF'!$C:$C,0),MATCH(D$7,'Rolling CF'!$7:$7,0)) -> -1350 | E47: =INDEX('Rolling CF'!$1:$1048576,MATCH($B47,'Rolling CF'!$C:$C,0),MATCH(E$7,'Rolling CF'!$7:$7,0)) -> 0 | F47: =INDEX('Rolling CF'!$1:$1048576,MATCH($B47,'Rolling CF'!$C:$C,0),MATCH(F$7,'Rolling CF'!$7:$7,0)) -> 0 | G47: =INDEX('Rolling CF'!$1:$1048576,MATCH($B47,'Rolling CF'!$C:$C,0),MATCH(G$7,'Rolling CF'!$7:$7,0)) -> -1350 | H47: =INDEX('Rolling CF'!$1:$1048576,MATCH($B47,'Rolling CF'!$C:$C,0),MATCH(H$7,'Rolling CF'!$7:$7,0)) -> -1350 | I47: =INDEX('Rolling CF'!$1:$1048576,MATCH($B47,'Rolling CF'!$C:$C,0),MATCH(I$7,'Rolling CF'!$7:$7,0)) -> 0 | J47: =INDEX('Rolling CF'!$1:$1048576,MATCH($B47,'Rolling CF'!$C:$C,0),MATCH(J$7,'Rolling CF'!$7:$7,0)) -> -675 | K47: =INDEX('Rolling CF'!$1:$1048576,MATCH($B47,'Rolling CF'!$C:$C,0),MATCH(K$7,'Rolling CF'!$7:$7,0)) -> -562.5 | ... V47: =INDEX('Rolling CF'!$1:$1048576,MATCH($B47,'Rolling CF'!$C:$C,0),MATCH(V$7,'Rolling CF'!$7:$7,0)) -> -645.00429
B48: Marketing | C48: Trailing 6 Week Average | D48: =INDEX('Rolling CF'!$1:$1048576,MATCH($B48,'Rolling CF'!$C:$C,0),MATCH(D$7,'Rolling CF'!$7:$7,0)) -> -1510 | E48: =INDEX('Rolling CF'!$1:$1048576,MATCH($B48,'Rolling CF'!$C:$C,0),MATCH(E$7,'Rolling CF'!$7:$7,0)) -> -1020 | F48: =INDEX('Rolling CF'!$1:$1048576,MATCH($B48,'Rolling CF'!$C:$C,0),MATCH(F$7,'Rolling CF'!$7:$7,0)) -> 0 | G48: =INDEX('Rolling CF'!$1:$1048576,MATCH($B48,'Rolling CF'!$C:$C,0),MATCH(G$7,'Rolling CF'!$7:$7,0)) -> 0 | H48: =INDEX('Rolling CF'!$1:$1048576,MATCH($B48,'Rolling CF'!$C:$C,0),MATCH(H$7,'Rolling CF'!$7:$7,0)) -> -1510 | I48: =INDEX('Rolling CF'!$1:$1048576,MATCH($B48,'Rolling CF'!$C:$C,0),MATCH(I$7,'Rolling CF'!$7:$7,0)) -> 0 | J48: =INDEX('Rolling CF'!$1:$1048576,MATCH($B48,'Rolling CF'!$C:$C,0),MATCH(J$7,'Rolling CF'!$7:$7,0)) -> -673.33333 | K48: =INDEX('Rolling CF'!$1:$1048576,MATCH($B48,'Rolling CF'!$C:$C,0),MATCH(K$7,'Rolling CF'!$7:$7,0)) -> -533.88889 | ... V48: =INDEX('Rolling CF'!$1:$1048576,MATCH($B48,'Rolling CF'!$C:$C,0),MATCH(V$7,'Rolling CF'!$7:$7,0)) -> -530.37388
B49: Phone & Internet | C49: Enter Manually | D49: =INDEX('Rolling CF'!$1:$1048576,MATCH($B49,'Rolling CF'!$C:$C,0),MATCH(D$7,'Rolling CF'!$7:$7,0)) -> 0 | E49: =INDEX('Rolling CF'!$1:$1048576,MATCH($B49,'Rolling CF'!$C:$C,0),MATCH(E$7,'Rolling CF'!$7:$7,0)) -> 0 | F49: =INDEX('Rolling CF'!$1:$1048576,MATCH($B49,'Rolling CF'!$C:$C,0),MATCH(F$7,'Rolling CF'!$7:$7,0)) -> 0 | G49: =INDEX('Rolling CF'!$1:$1048576,MATCH($B49,'Rolling CF'!$C:$C,0),MATCH(G$7,'Rolling CF'!$7:$7,0)) -> 0 | H49: =INDEX('Rolling CF'!$1:$1048576,MATCH($B49,'Rolling CF'!$C:$C,0),MATCH(H$7,'Rolling CF'!$7:$7,0)) -> 0 | I49: =INDEX('Rolling CF'!$1:$1048576,MATCH($B49,'Rolling CF'!$C:$C,0),MATCH(I$7,'Rolling CF'!$7:$7,0)) -> 0 | J49: =INDEX('Rolling CF'!$1:$1048576,MATCH($B49,'Rolling CF'!$C:$C,0),MATCH(J$7,'Rolling CF'!$7:$7,0)) -> 0 | K49: =INDEX('Rolling CF'!$1:$1048576,MATCH($B49,'Rolling CF'!$C:$C,0),MATCH(K$7,'Rolling CF'!$7:$7,0)) -> 0 | ... V49: =INDEX('Rolling CF'!$1:$1048576,MATCH($B49,'Rolling CF'!$C:$C,0),MATCH(V$7,'Rolling CF'!$7:$7,0)) -> 0
B50: Professional Fees | C50: $5k each Month | D50: =INDEX('Rolling CF'!$1:$1048576,MATCH($B50,'Rolling CF'!$C:$C,0),MATCH(D$7,'Rolling CF'!$7:$7,0)) -> -5000 | E50: =INDEX('Rolling CF'!$1:$1048576,MATCH($B50,'Rolling CF'!$C:$C,0),MATCH(E$7,'Rolling CF'!$7:$7,0)) -> 0 | F50: =INDEX('Rolling CF'!$1:$1048576,MATCH($B50,'Rolling CF'!$C:$C,0),MATCH(F$7,'Rolling CF'!$7:$7,0)) -> 0 | G50: =INDEX('Rolling CF'!$1:$1048576,MATCH($B50,'Rolling CF'!$C:$C,0),MATCH(G$7,'Rolling CF'!$7:$7,0)) -> 0 | H50: =INDEX('Rolling CF'!$1:$1048576,MATCH($B50,'Rolling CF'!$C:$C,0),MATCH(H$7,'Rolling CF'!$7:$7,0)) -> 0 | I50: =INDEX('Rolling CF'!$1:$1048576,MATCH($B50,'Rolling CF'!$C:$C,0),MATCH(I$7,'Rolling CF'!$7:$7,0)) -> -5000 | J50: =INDEX('Rolling CF'!$1:$1048576,MATCH($B50,'Rolling CF'!$C:$C,0),MATCH(J$7,'Rolling CF'!$7:$7,0)) -> 0 | K50: =INDEX('Rolling CF'!$1:$1048576,MATCH($B50,'Rolling CF'!$C:$C,0),MATCH(K$7,'Rolling CF'!$7:$7,0)) -> 0 | ... V50: =INDEX('Rolling CF'!$1:$1048576,MATCH($B50,'Rolling CF'!$C:$C,0),MATCH(V$7,'Rolling CF'!$7:$7,0)) -> 0
B51: Rent | C51: Enter Manually | D51: =INDEX('Rolling CF'!$1:$1048576,MATCH($B51,'Rolling CF'!$C:$C,0),MATCH(D$7,'Rolling CF'!$7:$7,0)) -> 0 | E51: =INDEX('Rolling CF'!$1:$1048576,MATCH($B51,'Rolling CF'!$C:$C,0),MATCH(E$7,'Rolling CF'!$7:$7,0)) -> 0 | F51: =INDEX('Rolling CF'!$1:$1048576,MATCH($B51,'Rolling CF'!$C:$C,0),MATCH(F$7,'Rolling CF'!$7:$7,0)) -> 0 | G51: =INDEX('Rolling CF'!$1:$1048576,MATCH($B51,'Rolling CF'!$C:$C,0),MATCH(G$7,'Rolling CF'!$7:$7,0)) -> 0 | H51: =INDEX('Rolling CF'!$1:$1048576,MATCH($B51,'Rolling CF'!$C:$C,0),MATCH(H$7,'Rolling CF'!$7:$7,0)) -> 0 | I51: =INDEX('Rolling CF'!$1:$1048576,MATCH($B51,'Rolling CF'!$C:$C,0),MATCH(I$7,'Rolling CF'!$7:$7,0)) -> 0 | J51: =INDEX('Rolling CF'!$1:$1048576,MATCH($B51,'Rolling CF'!$C:$C,0),MATCH(J$7,'Rolling CF'!$7:$7,0)) -> 0 | K51: =INDEX('Rolling CF'!$1:$1048576,MATCH($B51,'Rolling CF'!$C:$C,0),MATCH(K$7,'Rolling CF'!$7:$7,0)) -> 0 | ... V51: =INDEX('Rolling CF'!$1:$1048576,MATCH($B51,'Rolling CF'!$C:$C,0),MATCH(V$7,'Rolling CF'!$7:$7,0)) -> 0
B52: Repairs & Maintenance | C52: Enter Manually | D52: =INDEX('Rolling CF'!$1:$1048576,MATCH($B52,'Rolling CF'!$C:$C,0),MATCH(D$7,'Rolling CF'!$7:$7,0)) -> 0 | E52: =INDEX('Rolling CF'!$1:$1048576,MATCH($B52,'Rolling CF'!$C:$C,0),MATCH(E$7,'Rolling CF'!$7:$7,0)) -> 0 | F52: =INDEX('Rolling CF'!$1:$1048576,MATCH($B52,'Rolling CF'!$C:$C,0),MATCH(F$7,'Rolling CF'!$7:$7,0)) -> 0 | G52: =INDEX('Rolling CF'!$1:$1048576,MATCH($B52,'Rolling CF'!$C:$C,0),MATCH(G$7,'Rolling CF'!$7:$7,0)) -> 0 | H52: =INDEX('Rolling CF'!$1:$1048576,MATCH($B52,'Rolling CF'!$C:$C,0),MATCH(H$7,'Rolling CF'!$7:$7,0)) -> 0 | I52: =INDEX('Rolling CF'!$1:$1048576,MATCH($B52,'Rolling CF'!$C:$C,0),MATCH(I$7,'Rolling CF'!$7:$7,0)) -> 0 | J52: =INDEX('Rolling CF'!$1:$1048576,MATCH($B52,'Rolling CF'!$C:$C,0),MATCH(J$7,'Rolling CF'!$7:$7,0)) -> 0 | K52: =INDEX('Rolling CF'!$1:$1048576,MATCH($B52,'Rolling CF'!$C:$C,0),MATCH(K$7,'Rolling CF'!$7:$7,0)) -> 0 | ... V52: =INDEX('Rolling CF'!$1:$1048576,MATCH($B52,'Rolling CF'!$C:$C,0),MATCH(V$7,'Rolling CF'!$7:$7,0)) -> 0
... B60: Other Operating Outflows | C60: Trailing 6 Week Average | D60: =INDEX('Rolling CF'!$1:$1048576,MATCH($B60,'Rolling CF'!$C:$C,0),MATCH(D$7,'Rolling CF'!$7:$7,0)) -> -2570 | E60: =INDEX('Rolling CF'!$1:$1048576,MATCH($B60,'Rolling CF'!$C:$C,0),MATCH(E$7,'Rolling CF'!$7:$7,0)) -> 0 | F60: =INDEX('Rolling CF'!$1:$1048576,MATCH($B60,'Rolling CF'!$C:$C,0),MATCH(F$7,'Rolling CF'!$7:$7,0)) -> 0 | G60: =INDEX('Rolling CF'!$1:$1048576,MATCH($B60,'Rolling CF'!$C:$C,0),MATCH(G$7,'Rolling CF'!$7:$7,0)) -> 0 | H60: =INDEX('Rolling CF'!$1:$1048576,MATCH($B60,'Rolling CF'!$C:$C,0),MATCH(H$7,'Rolling CF'!$7:$7,0)) -> -1270 | I60: =INDEX('Rolling CF'!$1:$1048576,MATCH($B60,'Rolling CF'!$C:$C,0),MATCH(I$7,'Rolling CF'!$7:$7,0)) -> -1580 | J60: =INDEX('Rolling CF'!$1:$1048576,MATCH($B60,'Rolling CF'!$C:$C,0),MATCH(J$7,'Rolling CF'!$7:$7,0)) -> -903.33333 | K60: =INDEX('Rolling CF'!$1:$1048576,MATCH($B60,'Rolling CF'!$C:$C,0),MATCH(K$7,'Rolling CF'!$7:$7,0)) -> -625.55556 | ... V60: =INDEX('Rolling CF'!$1:$1048576,MATCH($B60,'Rolling CF'!$C:$C,0),MATCH(V$7,'Rolling CF'!$7:$7,0)) -> -866.79278
B62: Total Operating Cash Outflows | D62: =SUM(D41:D61) -> -374900 | E62: =SUM(E41:E61) -> -124910 | F62: =SUM(F41:F61) -> -180410 | G62: =SUM(G41:G61) -> -66850 | H62: =SUM(H41:H61) -> -166200 | I62: =SUM(I41:I61) -> -483870 | J62: =SUM(J41:J61) -> -51111.667 | K62: =SUM(K41:K61) -> -210073.61 | ... V62: =SUM(V41:V61) -> -44762.955
B64: Non-operating Cash Outflows
B65: Capital Expenditures | C65: Enter Manually | D65: =INDEX('Rolling CF'!$1:$1048576,MATCH($B65,'Rolling CF'!$C:$C,0),MATCH(D$7,'Rolling CF'!$7:$7,0)) -> 0 | E65: =INDEX('Rolling CF'!$1:$1048576,MATCH($B65,'Rolling CF'!$C:$C,0),MATCH(E$7,'Rolling CF'!$7:$7,0)) -> 0 | F65: =INDEX('Rolling CF'!$1:$1048576,MATCH($B65,'Rolling CF'!$C:$C,0),MATCH(F$7,'Rolling CF'!$7:$7,0)) -> 0 | G65: =INDEX('Rolling CF'!$1:$1048576,MATCH($B65,'Rolling CF'!$C:$C,0),MATCH(G$7,'Rolling CF'!$7:$7,0)) -> 0 | H65: =INDEX('Rolling CF'!$1:$1048576,MATCH($B65,'Rolling CF'!$C:$C,0),MATCH(H$7,'Rolling CF'!$7:$7,0)) -> 0 | I65: =INDEX('Rolling CF'!$1:$1048576,MATCH($B65,'Rolling CF'!$C:$C,0),MATCH(I$7,'Rolling CF'!$7:$7,0)) -> 0 | J65: =INDEX('Rolling CF'!$1:$1048576,MATCH($B65,'Rolling CF'!$C:$C,0),MATCH(J$7,'Rolling CF'!$7:$7,0)) -> 0 | K65: =INDEX('Rolling CF'!$1:$1048576,MATCH($B65,'Rolling CF'!$C:$C,0),MATCH(K$7,'Rolling CF'!$7:$7,0)) -> 0 | ... V65: =INDEX('Rolling CF'!$1:$1048576,MATCH($B65,'Rolling CF'!$C:$C,0),MATCH(V$7,'Rolling CF'!$7:$7,0)) -> 0
B66: Debt Proceeds | C66: Enter Manually | D66: =INDEX('Rolling CF'!$1:$1048576,MATCH($B66,'Rolling CF'!$C:$C,0),MATCH(D$7,'Rolling CF'!$7:$7,0)) -> 0 | E66: =INDEX('Rolling CF'!$1:$1048576,MATCH($B66,'Rolling CF'!$C:$C,0),MATCH(E$7,'Rolling CF'!$7:$7,0)) -> 0 | F66: =INDEX('Rolling CF'!$1:$1048576,MATCH($B66,'Rolling CF'!$C:$C,0),MATCH(F$7,'Rolling CF'!$7:$7,0)) -> 0 | G66: =INDEX('Rolling CF'!$1:$1048576,MATCH($B66,'Rolling CF'!$C:$C,0),MATCH(G$7,'Rolling CF'!$7:$7,0)) -> 0 | H66: =INDEX('Rolling CF'!$1:$1048576,MATCH($B66,'Rolling CF'!$C:$C,0),MATCH(H$7,'Rolling CF'!$7:$7,0)) -> 0 | I66: =INDEX('Rolling CF'!$1:$1048576,MATCH($B66,'Rolling CF'!$C:$C,0),MATCH(I$7,'Rolling CF'!$7:$7,0)) -> 0 | J66: =INDEX('Rolling CF'!$1:$1048576,MATCH($B66,'Rolling CF'!$C:$C,0),MATCH(J$7,'Rolling CF'!$7:$7,0)) -> 0 | K66: =INDEX('Rolling CF'!$1:$1048576,MATCH($B66,'Rolling CF'!$C:$C,0),MATCH(K$7,'Rolling CF'!$7:$7,0)) -> 0 | ... V66: =INDEX('Rolling CF'!$1:$1048576,MATCH($B66,'Rolling CF'!$C:$C,0),MATCH(V$7,'Rolling CF'!$7:$7,0)) -> 0
B67: Interest Payments | C67: Enter Manually | D67: =INDEX('Rolling CF'!$1:$1048576,MATCH($B67,'Rolling CF'!$C:$C,0),MATCH(D$7,'Rolling CF'!$7:$7,0)) -> 0 | E67: =INDEX('Rolling CF'!$1:$1048576,MATCH($B67,'Rolling CF'!$C:$C,0),MATCH(E$7,'Rolling CF'!$7:$7,0)) -> 0 | F67: =INDEX('Rolling CF'!$1:$1048576,MATCH($B67,'Rolling CF'!$C:$C,0),MATCH(F$7,'Rolling CF'!$7:$7,0)) -> 0 | G67: =INDEX('Rolling CF'!$1:$1048576,MATCH($B67,'Rolling CF'!$C:$C,0),MATCH(G$7,'Rolling CF'!$7:$7,0)) -> 0 | H67: =INDEX('Rolling CF'!$1:$1048576,MATCH($B67,'Rolling CF'!$C:$C,0),MATCH(H$7,'Rolling CF'!$7:$7,0)) -> 0 | I67: =INDEX('Rolling CF'!$1:$1048576,MATCH($B67,'Rolling CF'!$C:$C,0),MATCH(I$7,'Rolling CF'!$7:$7,0)) -> 0 | J67: =INDEX('Rolling CF'!$1:$1048576,MATCH($B67,'Rolling CF'!$C:$C,0),MATCH(J$7,'Rolling CF'!$7:$7,0)) -> 0 | K67: =INDEX('Rolling CF'!$1:$1048576,MATCH($B67,'Rolling CF'!$C:$C,0),MATCH(K$7,'Rolling CF'!$7:$7,0)) -> 0 | ... V67: =INDEX('Rolling CF'!$1:$1048576,MATCH($B67,'Rolling CF'!$C:$C,0),MATCH(V$7,'Rolling CF'!$7:$7,0)) -> 0
B68: Principal Payments | C68: Enter Manually | D68: =INDEX('Rolling CF'!$1:$1048576,MATCH($B68,'Rolling CF'!$C:$C,0),MATCH(D$7,'Rolling CF'!$7:$7,0)) -> 0 | E68: =INDEX('Rolling CF'!$1:$1048576,MATCH($B68,'Rolling CF'!$C:$C,0),MATCH(E$7,'Rolling CF'!$7:$7,0)) -> 0 | F68: =INDEX('Rolling CF'!$1:$1048576,MATCH($B68,'Rolling CF'!$C:$C,0),MATCH(F$7,'Rolling CF'!$7:$7,0)) -> 0 | G68: =INDEX('Rolling CF'!$1:$1048576,MATCH($B68,'Rolling CF'!$C:$C,0),MATCH(G$7,'Rolling CF'!$7:$7,0)) -> 0 | H68: =INDEX('Rolling CF'!$1:$1048576,MATCH($B68,'Rolling CF'!$C:$C,0),MATCH(H$7,'Rolling CF'!$7:$7,0)) -> 0 | I68: =INDEX('Rolling CF'!$1:$1048576,MATCH($B68,'Rolling CF'!$C:$C,0),MATCH(I$7,'Rolling CF'!$7:$7,0)) -> 0 | J68: =INDEX('Rolling CF'!$1:$1048576,MATCH($B68,'Rolling CF'!$C:$C,0),MATCH(J$7,'Rolling CF'!$7:$7,0)) -> 0 | K68: =INDEX('Rolling CF'!$1:$1048576,MATCH($B68,'Rolling CF'!$C:$C,0),MATCH(K$7,'Rolling CF'!$7:$7,0)) -> 0 | ... V68: =INDEX('Rolling CF'!$1:$1048576,MATCH($B68,'Rolling CF'!$C:$C,0),MATCH(V$7,'Rolling CF'!$7:$7,0)) -> 0
B69: Tax Distributions | C69: Trailing 6 Week Average | D69: =INDEX('Rolling CF'!$1:$1048576,MATCH($B69,'Rolling CF'!$C:$C,0),MATCH(D$7,'Rolling CF'!$7:$7,0)) -> -24740 | E69: =INDEX('Rolling CF'!$1:$1048576,MATCH($B69,'Rolling CF'!$C:$C,0),MATCH(E$7,'Rolling CF'!$7:$7,0)) -> -20220 | F69: =INDEX('Rolling CF'!$1:$1048576,MATCH($B69,'Rolling CF'!$C:$C,0),MATCH(F$7,'Rolling CF'!$7:$7,0)) -> -14200 | G69: =INDEX('Rolling CF'!$1:$1048576,MATCH($B69,'Rolling CF'!$C:$C,0),MATCH(G$7,'Rolling CF'!$7:$7,0)) -> -12680 | H69: =INDEX('Rolling CF'!$1:$1048576,MATCH($B69,'Rolling CF'!$C:$C,0),MATCH(H$7,'Rolling CF'!$7:$7,0)) -> -12340 | I69: =INDEX('Rolling CF'!$1:$1048576,MATCH($B69,'Rolling CF'!$C:$C,0),MATCH(I$7,'Rolling CF'!$7:$7,0)) -> -8560 | J69: =INDEX('Rolling CF'!$1:$1048576,MATCH($B69,'Rolling CF'!$C:$C,0),MATCH(J$7,'Rolling CF'!$7:$7,0)) -> -15456.667 | K69: =INDEX('Rolling CF'!$1:$1048576,MATCH($B69,'Rolling CF'!$C:$C,0),MATCH(K$7,'Rolling CF'!$7:$7,0)) -> -13909.444 | ... V69: =INDEX('Rolling CF'!$1:$1048576,MATCH($B69,'Rolling CF'!$C:$C,0),MATCH(V$7,'Rolling CF'!$7:$7,0)) -> -12988.889
B70: Equity Distributions | C70: Enter Manually | D70: =INDEX('Rolling CF'!$1:$1048576,MATCH($B70,'Rolling CF'!$C:$C,0),MATCH(D$7,'Rolling CF'!$7:$7,0)) -> 0 | E70: =INDEX('Rolling CF'!$1:$1048576,MATCH($B70,'Rolling CF'!$C:$C,0),MATCH(E$7,'Rolling CF'!$7:$7,0)) -> 0 | F70: =INDEX('Rolling CF'!$1:$1048576,MATCH($B70,'Rolling CF'!$C:$C,0),MATCH(F$7,'Rolling CF'!$7:$7,0)) -> 0 | G70: =INDEX('Rolling CF'!$1:$1048576,MATCH($B70,'Rolling CF'!$C:$C,0),MATCH(G$7,'Rolling CF'!$7:$7,0)) -> 0 | H70: =INDEX('Rolling CF'!$1:$1048576,MATCH($B70,'Rolling CF'!$C:$C,0),MATCH(H$7,'Rolling CF'!$7:$7,0)) -> 0 | I70: =INDEX('Rolling CF'!$1:$1048576,MATCH($B70,'Rolling CF'!$C:$C,0),MATCH(I$7,'Rolling CF'!$7:$7,0)) -> 0 | J70: =INDEX('Rolling CF'!$1:$1048576,MATCH($B70,'Rolling CF'!$C:$C,0),MATCH(J$7,'Rolling CF'!$7:$7,0)) -> 0 | K70: =INDEX('Rolling CF'!$1:$1048576,MATCH($B70,'Rolling CF'!$C:$C,0),MATCH(K$7,'Rolling CF'!$7:$7,0)) -> 0 | ... V70: =INDEX('Rolling CF'!$1:$1048576,MATCH($B70,'Rolling CF'!$C:$C,0),MATCH(V$7,'Rolling CF'!$7:$7,0)) -> 0
B71: Equity Contributions | C71: Enter Manually | D71: =INDEX('Rolling CF'!$1:$1048576,MATCH($B71,'Rolling CF'!$C:$C,0),MATCH(D$7,'Rolling CF'!$7:$7,0)) -> 0 | E71: =INDEX('Rolling CF'!$1:$1048576,MATCH($B71,'Rolling CF'!$C:$C,0),MATCH(E$7,'Rolling CF'!$7:$7,0)) -> 0 | F71: =INDEX('Rolling CF'!$1:$1048576,MATCH($B71,'Rolling CF'!$C:$C,0),MATCH(F$7,'Rolling CF'!$7:$7,0)) -> 0 | G71: =INDEX('Rolling CF'!$1:$1048576,MATCH($B71,'Rolling CF'!$C:$C,0),MATCH(G$7,'Rolling CF'!$7:$7,0)) -> 0 | H71: =INDEX('Rolling CF'!$1:$1048576,MATCH($B71,'Rolling CF'!$C:$C,0),MATCH(H$7,'Rolling CF'!$7:$7,0)) -> 0 | I71: =INDEX('Rolling CF'!$1:$1048576,MATCH($B71,'Rolling CF'!$C:$C,0),MATCH(I$7,'Rolling CF'!$7:$7,0)) -> 0 | J71: =INDEX('Rolling CF'!$1:$1048576,MATCH($B71,'Rolling CF'!$C:$C,0),MATCH(J$7,'Rolling CF'!$7:$7,0)) -> 0 | K71: =INDEX('Rolling CF'!$1:$1048576,MATCH($B71,'Rolling CF'!$C:$C,0),MATCH(K$7,'Rolling CF'!$7:$7,0)) -> 0 | ... V71: =INDEX('Rolling CF'!$1:$1048576,MATCH($B71,'Rolling CF'!$C:$C,0),MATCH(V$7,'Rolling CF'!$7:$7,0)) -> 0
B72: Other Non-operating Outflows | C72: Trailing 6 Week Average | D72: =INDEX('Rolling CF'!$1:$1048576,MATCH($B72,'Rolling CF'!$C:$C,0),MATCH(D$7,'Rolling CF'!$7:$7,0)) -> -8580 | E72: =INDEX('Rolling CF'!$1:$1048576,MATCH($B72,'Rolling CF'!$C:$C,0),MATCH(E$7,'Rolling CF'!$7:$7,0)) -> 0 | F72: =INDEX('Rolling CF'!$1:$1048576,MATCH($B72,'Rolling CF'!$C:$C,0),MATCH(F$7,'Rolling CF'!$7:$7,0)) -> -1140 | G72: =INDEX('Rolling CF'!$1:$1048576,MATCH($B72,'Rolling CF'!$C:$C,0),MATCH(G$7,'Rolling CF'!$7:$7,0)) -> 0 | H72: =INDEX('Rolling CF'!$1:$1048576,MATCH($B72,'Rolling CF'!$C:$C,0),MATCH(H$7,'Rolling CF'!$7:$7,0)) -> 0 | I72: =INDEX('Rolling CF'!$1:$1048576,MATCH($B72,'Rolling CF'!$C:$C,0),MATCH(I$7,'Rolling CF'!$7:$7,0)) -> -3260 | J72: =INDEX('Rolling CF'!$1:$1048576,MATCH($B72,'Rolling CF'!$C:$C,0),MATCH(J$7,'Rolling CF'!$7:$7,0)) -> -2163.3333 | K72: =INDEX('Rolling CF'!$1:$1048576,MATCH($B72,'Rolling CF'!$C:$C,0),MATCH(K$7,'Rolling CF'!$7:$7,0)) -> -1093.8889 | ... V72: =INDEX('Rolling CF'!$1:$1048576,MATCH($B72,'Rolling CF'!$C:$C,0),MATCH(V$7,'Rolling CF'!$7:$7,0)) -> -1492.2525
B74: Total Non-operating Cash Outflows | D74: =SUM(D65:D73) -> -33320 | E74: =SUM(E65:E73) -> -20220 | F74: =SUM(F65:F73) -> -15340 | G74: =SUM(G65:G73) -> -12680 | H74: =SUM(H65:H73) -> -12340 | I74: =SUM(I65:I73) -> -11820 | J74: =SUM(J65:J73) -> -17620 | K74: =SUM(K65:K73) -> -15003.333 | ... V74: =SUM(V65:V73) -> -14481.142
B76: Change in Cash | D76: =SUM(D38,D62,D74) -> -36120 | E76: =SUM(E38,E62,E74) -> 65020 | F76: =SUM(F38,F62,F74) -> -195750 | G76: =SUM(G38,G62,G74) -> 281900 | H76: =SUM(H38,H62,H74) -> -110100 | I76: =SUM(I38,I62,I74) -> -106220 | J76: =SUM(J38,J62,J74) -> 51268.333 | K76: =SUM(K38,K62,K74) -> 328923.06 | ... V76: =SUM(V38,V62,V74) -> -59244.097
C78: Week End Date | D78: =D7 -> 45234 | E78: =E7 -> 45241 | F78: =F7 -> 45248 | G78: =G7 -> 45255 | H78: =H7 -> 45262 | I78: =I7 -> 45269 | J78: =J7 -> 45276 | K78: =K7 -> 45283 | ... V78: =V7 -> 45360
C79: This Week's Forecast | D79: =D12 -> 174090 | E79: =E12 -> 239110 | F79: =F12 -> 43360 | G79: =G12 -> 325260 | H79: =H12 -> 215160 | I79: =I12 -> 108940 | J79: =J12 -> 160208.33 | K79: =K12 -> 489131.39 | ... V79: =V12 -> -196949.22
C80: Last Week's Forecast | D80: =D15 -> 174090 | E80: =E15 -> 239110 | F80: =F15 -> 43360 | G80: =G15 -> 325260 | H80: =H15 -> 215160 | I80: =I15 -> 112041.67 | J80: =J15 -> 156995.28 | K80: =K15 -> 399451.16 | ... U80: =U15 -> 291189.57 | V80: =NA() -> #N/A

Sheet Variance Analysis
C2: Master Error Check Cell | D2: ='Error Checking'!$B$2 -> 0
C4: Actual / Forecast | E4: Actual | F4: Actual | G4: Actual | H4: Actual | I4: Actual | J4: Actual | K4: Actual | L4: Forecast | M4: Forecast | N4: Forecast | O4: Forecast | P4: Forecast | Q4: Forecast | R4: Forecast | S4: Forecast | T4: Forecast | U4: Forecast | V4: Forecast | W4: Forecast
C5: Week Number | E5: 1 | F5: =E5+1 -> 2 | G5: =F5+1 -> 3 | H5: =G5+1 -> 4 | I5: =H5+1 -> 5 | J5: =I5+1 -> 6 | K5: =J5+1 -> 7 | L5: =K5+1 -> 8 | M5: =L5+1 -> 9 | ... W5: =V5+1 -> 19
C6: Week Beginning | E6: =E7-6 -> 45221 | F6: =F7-6 -> 45228 | G6: =G7-6 -> 45235 | H6: =H7-6 -> 45242 | I6: =I7-6 -> 45249 | J6: =J7-6 -> 45256 | K6: =K7-6 -> 45263 | L6: =L7-6 -> 45270 | ... W6: =W7-6 -> 45347
B7: Variance Tagging | C7: Week Ending | E7: =F6-1 -> 45227 | F7: =G6-1 -> 45234 | G7: =H6-1 -> 45241 | H7: =I6-1 -> 45248 | I7: =J6-1 -> 45255 | J7: =K6-1 -> 45262 | K7: =L6-1 -> 45269 | L7: =M6-1 -> 45276 | ... V7: =W6-1 -> 45346 | W7: =MAX('13 weeks CF'!7:7) -> 45353
C9: Bridge
B10: Ending Cash | C10: Last Week's Ending Cash | E10: =INDEX('13 weeks CF'!$12:$12,MATCH(E$7,'13 weeks CF'!$7:$7,0)) -> 210210 | F10: =INDEX('13 weeks CF'!$12:$12,MATCH(F$7,'13 weeks CF'!$7:$7,0)) -> 174090 | G10: =INDEX('13 weeks CF'!$12:$12,MATCH(G$7,'13 weeks CF'!$7:$7,0)) -> 239110 | H10: =INDEX('13 weeks CF'!$12:$12,MATCH(H$7,'13 weeks CF'!$7:$7,0)) -> 43360 | I10: =INDEX('13 weeks CF'!$12:$12,MATCH(I$7,'13 weeks CF'!$7:$7,0)) -> 325260 | J10: =INDEX('13 weeks CF'!$12:$12,MATCH(J$7,'13 weeks CF'!$7:$7,0)) -> 215160 | K10: =INDEX('13 weeks CF'!$12:$12,MATCH(K$7,'13 weeks CF'!$7:$7,0)) -> 112041.67 | L10: =INDEX('13 weeks CF'!$12:$12,MATCH(L$7,'13 weeks CF'!$7:$7,0)) -> 156995.28 | ... W10: =INDEX('13 weeks CF'!$12:$12,MATCH(W$7,'13 weeks CF'!$7:$7,0)) -> 291189.57
C11: Difference in Invoiced AR + New Revenue | E11: =SUM($E24:E24) -> 0 | F11: =SUM($E24:F24) -> 0 | G11: =SUM($E24:G24) -> 0 | H11: =SUM($E24:H24) -> 0 | I11: =SUM($E24:I24) -> 0 | J11: =SUM($E24:J24) -> 0 | K11: =SUM($E24:K24) -> 59470 | L11: =SUM($E24:L24) -> 59470 | ... W11: =SUM($E24:W24) -> -142130
C12: Difference in Accounts Payable | E12: =SUM($E28:E28) -> 0 | F12: =SUM($E28:F28) -> 0 | G12: =SUM($E28:G28) -> 0 | H12: =SUM($E28:H28) -> 0 | I12: =SUM($E28:I28) -> 0 | J12: =SUM($E28:J28) -> 0 | K12: =SUM($E28:K28) -> -88940 | L12: =SUM($E28:L28) -> -87140 | ... W12: =SUM($E28:W28) -> -271640
C13: Difference in Credit Cards | E13: =SUM($E32:E32) -> 0 | F13: =SUM($E32:F32) -> 0 | G13: =SUM($E32:G32) -> 0 | H13: =SUM($E32:H32) -> 0 | I13: =SUM($E32:I32) -> 0 | J13: =SUM($E32:J32) -> 0 | K13: =SUM($E32:K32) -> -210 | L13: =SUM($E32:L32) -> -210 | ... W13: =SUM($E32:W32) -> -128310
C14: Difference in Other Ops | E14: =SUM($E36:E36) -> 0 | F14: =SUM($E36:F36) -> 0 | G14: =SUM($E36:G36) -> 0 | H14: =SUM($E36:H36) -> 0 | I14: =SUM($E36:I36) -> 0 | J14: =SUM($E36:J36) -> 0 | K14: =SUM($E36:K36) -> 19210 | L14: =SUM($E36:L36) -> 22496.667 | ... W14: =SUM($E36:W36) -> 82258.893
C15: Difference in Non Ops | E15: =SUM($E40:E40) -> 0 | F15: =SUM($E40:F40) -> 0 | G15: =SUM($E40:G40) -> 0 | H15: =SUM($E40:H40) -> 0 | I15: =SUM($E40:I40) -> 0 | J15: =SUM($E40:J40) -> 0 | K15: =SUM($E40:K40) -> 7368.3333 | L15: =SUM($E40:L40) -> 8596.3889 | ... W15: =SUM($E40:W40) -> 30926.409
C17: Net Difference | E17: =SUM(E11:E16) -> 0 | F17: =SUM(F11:F16) -> 0 | G17: =SUM(G11:G16) -> 0 | H17: =SUM(H11:H16) -> 0 | I17: =SUM(I11:I16) -> 0 | J17: =SUM(J11:J16) -> 0 | K17: =SUM(K11:K16) -> -3101.6667 | L17: =SUM(L11:L16) -> 3213.0556 | ... W17: =SUM(W11:W16) -> -428894.7
C18: This Week's Ending Cash | E18: =SUM(E10,E17) -> 210210 | F18: =SUM(F10,F17) -> 174090 | G18: =SUM(G10,G17) -> 239110 | H18: =SUM(H10,H17) -> 43360 | I18: =SUM(I10,I17) -> 325260 | J18: =SUM(J10,J17) -> 215160 | K18: =SUM(K10,K17) -> 108940 | L18: =SUM(L10,L17) -> 160208.33 | ... W18: =SUM(W10,W17) -> -137705.13
C19: This Week's Ending Cash, per Forecast | E19: =INDEX('Rolling CF'!$12:$12,MATCH(E$7,'Rolling CF'!$7:$7,0)) -> 210210 | F19: =INDEX('Rolling CF'!$12:$12,MATCH(F$7,'Rolling CF'!$7:$7,0)) -> 174090 | G19: =INDEX('Rolling CF'!$12:$12,MATCH(G$7,'Rolling CF'!$7:$7,0)) -> 239110 | H19: =INDEX('Rolling CF'!$12:$12,MATCH(H$7,'Rolling CF'!$7:$7,0)) -> 43360 | I19: =INDEX('Rolling CF'!$12:$12,MATCH(I$7,'Rolling CF'!$7:$7,0)) -> 325260 | J19: =INDEX('Rolling CF'!$12:$12,MATCH(J$7,'Rolling CF'!$7:$7,0)) -> 215160 | K19: =INDEX('Rolling CF'!$12:$12,MATCH(K$7,'Rolling CF'!$7:$7,0)) -> 108940 | L19: =INDEX('Rolling CF'!$12:$12,MATCH(L$7,'Rolling CF'!$7:$7,0)) -> 160208.33 | ... W19: =INDEX('Rolling CF'!$12:$12,MATCH(W$7,'Rolling CF'!$7:$7,0)) -> -137705.13
C20: Difference | E20: =ROUND(E18-E19,2) -> 0 | F20: =ROUND(F18-F19,2) -> 0 | G20: =ROUND(G18-G19,2) -> 0 | H20: =ROUND(H18-H19,2) -> 0 | I20: =ROUND(I18-I19,2) -> 0 | J20: =ROUND(J18-J19,2) -> 0 | K20: =ROUND(K18-K19,2) -> 0 | L20: =ROUND(L18-L19,2) -> 0 | ... W20: =ROUND(W18-W19,2) -> 0
B22: Invoiced AR + New Revenue | C22: ="Last Week's "&B22 -> Last Week's Invoiced AR + New Revenue | E22: {=SUMPRODUCT('13 weeks CF'!$E$10:$X$59*('13 weeks CF'!$E$7:$X$7=E$7)*('13 weeks CF'!$B$10:$B$59=$B22))} -> 0 | F22: {=SUMPRODUCT('13 weeks CF'!$E$10:$X$59*('13 weeks CF'!$E$7:$X$7=F$7)*('13 weeks CF'!$B$10:$B$59=$B22))} -> 372100 | G22: {=SUMPRODUCT('13 weeks CF'!$E$10:$X$59*('13 weeks CF'!$E$7:$X$7=G$7)*('13 weeks CF'!$B$10:$B$59=$B22))} -> 210150 | H22: {=SUMPRODUCT('13 weeks CF'!$E$10:$X$59*('13 weeks CF'!$E$7:$X$7=H$7)*('13 weeks CF'!$B$10:$B$59=$B22))} -> 0 | I22: {=SUMPRODUCT('13 weeks CF'!$E$10:$X$59*('13 weeks CF'!$E$7:$X$7=I$7)*('13 weeks CF'!$B$10:$B$59=$B22))} -> 361430 | J22: {=SUMPRODUCT('13 weeks CF'!$E$10:$X$59*('13 weeks CF'!$E$7:$X$7=J$7)*('13 weeks CF'!$B$10:$B$59=$B22))} -> 68440 | K22: {=SUMPRODUCT('13 weeks CF'!$E$10:$X$59*('13 weeks CF'!$E$7:$X$7=K$7)*('13 weeks CF'!$B$10:$B$59=$B22))} -> 330000 | L22: {=SUMPRODUCT('13 weeks CF'!$E$10:$X$59*('13 weeks CF'!$E$7:$X$7=L$7)*('13 weeks CF'!$B$10:$B$59=$B22))} -> 120000 | ... W22: {=SUMPRODUCT('13 weeks CF'!$E$10:$X$59*('13 weeks CF'!$E$7:$X$7=W$7)*('13 weeks CF'!$B$10:$B$59=$B22))} -> 0
B23: Invoiced AR + New Revenue | C23: ="This Week's "&B23 -> This Week's Invoiced AR + New Revenue | E23: {=SUMPRODUCT('Rolling CF'!$E$10:$Y$59*('Rolling CF'!$E$7:$Y$7=E$7)*('Rolling CF'!$B$10:$B$59=$B23))} -> 0 | F23: {=SUMPRODUCT('Rolling CF'!$E$10:$Y$59*('Rolling CF'!$E$7:$Y$7=F$7)*('Rolling CF'!$B$10:$B$59=$B23))} -> 372100 | G23: {=SUMPRODUCT('Rolling CF'!$E$10:$Y$59*('Rolling CF'!$E$7:$Y$7=G$7)*('Rolling CF'!$B$10:$B$59=$B23))} -> 210150 | H23: {=SUMPRODUCT('Rolling CF'!$E$10:$Y$59*('Rolling CF'!$E$7:$Y$7=H$7)*('Rolling CF'!$B$10:$B$59=$B23))} -> 0 | I23: {=SUMPRODUCT('Rolling CF'!$E$10:$Y$59*('Rolling CF'!$E$7:$Y$7=I$7)*('Rolling CF'!$B$10:$B$59=$B23))} -> 361430 | J23: {=SUMPRODUCT('Rolling CF'!$E$10:$Y$59*('Rolling CF'!$E$7:$Y$7=J$7)*('Rolling CF'!$B$10:$B$59=$B23))} -> 68440 | K23: {=SUMPRODUCT('Rolling CF'!$E$10:$Y$59*('Rolling CF'!$E$7:$Y$7=K$7)*('Rolling CF'!$B$10:$B$59=$B23))} -> 389470 | L23: {=SUMPRODUCT('Rolling CF'!$E$10:$Y$59*('Rolling CF'!$E$7:$Y$7=L$7)*('Rolling CF'!$B$10:$B$59=$B23))} -> 120000 | ... W23: {=SUMPRODUCT('Rolling CF'!$E$10:$Y$59*('Rolling CF'!$E$7:$Y$7=W$7)*('Rolling CF'!$B$10:$B$59=$B23))} -> 0
B24: Invoiced AR + New Revenue | C24: ="Difference in "&B24 -> Difference in Invoiced AR + New Revenue | E24: =E23-E22 -> 0 | F24: =F23-F22 -> 0 | G24: =G23-G22 -> 0 | H24: =H23-H22 -> 0 | I24: =I23-I22 -> 0 | J24: =J23-J22 -> 0 | K24: =K23-K22 -> 59470 | L24: =L23-L22 -> 0 | ... W24: =W23-W22 -> 0
B26: Accounts Payable | C26: ="Last Week's "&B26 -> Last Week's Accounts Payable | E26: {=SUMPRODUCT('13 weeks CF'!$E$10:$X$59*('13 weeks CF'!$E$7:$X$7=E$7)*('13 weeks CF'!$B$10:$B$59=$B26))} -> -33620 | F26: {=SUMPRODUCT('13 weeks CF'!$E$10:$X$59*('13 weeks CF'!$E$7:$X$7=F$7)*('13 weeks CF'!$B$10:$B$59=$B26))} -> -83210 | G26: {=SUMPRODUCT('13 weeks CF'!$E$10:$X$59*('13 weeks CF'!$E$7:$X$7=G$7)*('13 weeks CF'!$B$10:$B$59=$B26))} -> -69810 | H26: {=SUMPRODUCT('13 weeks CF'!$E$10:$X$59*('13 weeks CF'!$E$7:$X$7=H$7)*('13 weeks CF'!$B$10:$B$59=$B26))} -> -40140 | I26: {=SUMPRODUCT('13 weeks CF'!$E$10:$X$59*('13 weeks CF'!$E$7:$X$7=I$7)*('13 weeks CF'!$B$10:$B$59=$B26))} -> -18680 | J26: {=SUMPRODUCT('13 weeks CF'!$E$10:$X$59*('13 weeks CF'!$E$7:$X$7=J$7)*('13 weeks CF'!$B$10:$B$59=$B26))} -> -88580 | K26: {=SUMPRODUCT('13 weeks CF'!$E$10:$X$59*('13 weeks CF'!$E$7:$X$7=K$7)*('13 weeks CF'!$B$10:$B$59=$B26))} -> -800 | L26: {=SUMPRODUCT('13 weeks CF'!$E$10:$X$59*('13 weeks CF'!$E$7:$X$7=L$7)*('13 weeks CF'!$B$10:$B$59=$B26))} -> -1800 | ... W26: {=SUMPRODUCT('13 weeks CF'!$E$10:$X$59*('13 weeks CF'!$E$7:$X$7=W$7)*('13 weeks CF'!$B$10:$B$59=$B26))} -> 0
B27: Accounts Payable | C27: ="This Week's "&B27 -> This Week's Accounts Payable | E27: {=SUMPRODUCT('Rolling CF'!$E$10:$Y$59*('Rolling CF'!$E$7:$Y$7=E$7)*('Rolling CF'!$B$10:$B$59=$B27))} -> -33620 | F27: {=SUMPRODUCT('Rolling CF'!$E$10:$Y$59*('Rolling CF'!$E$7:$Y$7=F$7)*('Rolling CF'!$B$10:$B$59=$B27))} -> -83210 | G27: {=SUMPRODUCT('Rolling CF'!$E$10:$Y$59*('Rolling CF'!$E$7:$Y$7=G$7)*('Rolling CF'!$B$10:$B$59=$B27))} -> -69810 | H27: {=SUMPRODUCT('Rolling CF'!$E$10:$Y$59*('Rolling CF'!$E$7:$Y$7=H$7)*('Rolling CF'!$B$10:$B$59=$B27))} -> -40140 | I27: {=SUMPRODUCT('Rolling CF'!$E$10:$Y$59*('Rolling CF'!$E$7:$Y$7=I$7)*('Rolling CF'!$B$10:$B$59=$B27))} -> -18680 | J27: {=SUMPRODUCT('Rolling CF'!$E$10:$Y$59*('Rolling CF'!$E$7:$Y$7=J$7)*('Rolling CF'!$B$10:$B$59=$B27))} -> -88580 | K27: {=SUMPRODUCT('Rolling CF'!$E$10:$Y$59*('Rolling CF'!$E$7:$Y$7=K$7)*('Rolling CF'!$B$10:$B$59=$B27))} -> -89740 | L27: {=SUMPRODUCT('Rolling CF'!$E$10:$Y$59*('Rolling CF'!$E$7:$Y$7=L$7)*('Rolling CF'!$B$10:$B$59=$B27))} -> 0 | ... W27: {=SUMPRODUCT('Rolling CF'!$E$10:$Y$59*('Rolling CF'!$E$7:$Y$7=W$7)*('Rolling CF'!$B$10:$B$59=$B27))} -> 0
B28: Accounts Payable | C28: ="Difference in "&B28 -> Difference in Accounts Payable | E28: =E27-E26 -> 0 | F28: =F27-F26 -> 0 | G28: =G27-G26 -> 0 | H28: =H27-H26 -> 0 | I28: =I27-I26 -> 0 | J28: =J27-J26 -> 0 | K28: =K27-K26 -> -88940 | L28: =L27-L26 -> 1800 | ... W28: =W27-W26 -> 0
B30: Credit Cards | C30: ="Last Week's "&B30 -> Last Week's Credit Cards | E30: {=SUMPRODUCT('13 weeks CF'!$E$10:$X$59*('13 weeks CF'!$E$7:$X$7=E$7)*('13 weeks CF'!$B$10:$B$59=$B30))} -> 0 | F30: {=SUMPRODUCT('13 weeks CF'!$E$10:$X$59*('13 weeks CF'!$E$7:$X$7=F$7)*('13 weeks CF'!$B$10:$B$59=$B30))} -> -194090 | G30: {=SUMPRODUCT('13 weeks CF'!$E$10:$X$59*('13 weeks CF'!$E$7:$X$7=G$7)*('13 weeks CF'!$B$10:$B$59=$B30))} -> 0 | H30: {=SUMPRODUCT('13 weeks CF'!$E$10:$X$59*('13 weeks CF'!$E$7:$X$7=H$7)*('13 weeks CF'!$B$10:$B$59=$B30))} -> -100000 | I30: {=SUMPRODUCT('13 weeks CF'!$E$10:$X$59*('13 weeks CF'!$E$7:$X$7=I$7)*('13 weeks CF'!$B$10:$B$59=$B30))} -> 0 | J30: {=SUMPRODUCT('13 weeks CF'!$E$10:$X$59*('13 weeks CF'!$E$7:$X$7=J$7)*('13 weeks CF'!$B$10:$B$59=$B30))} -> -32000 | K30: {=SUMPRODUCT('13 weeks CF'!$E$10:$X$59*('13 weeks CF'!$E$7:$X$7=K$7)*('13 weeks CF'!$B$10:$B$59=$B30))} -> -350000 | L30: {=SUMPRODUCT('13 weeks CF'!$E$10:$X$59*('13 weeks CF'!$E$7:$X$7=L$7)*('13 weeks CF'!$B$10:$B$59=$B30))} -> 0 | ... W30: {=SUMPRODUCT('13 weeks CF'!$E$10:$X$59*('13 weeks CF'!$E$7:$X$7=W$7)*('13 weeks CF'!$B$10:$B$59=$B30))} -> -210000
B31: Credit Cards | C31: ="This Week's "&B31 -> This Week's Credit Cards | E31: {=SUMPRODUCT('Rolling CF'!$E$10:$Y$59*('Rolling CF'!$E$7:$Y$7=E$7)*('Rolling CF'!$B$10:$B$59=$B31))} -> 0 | F31: {=SUMPRODUCT('Rolling CF'!$E$10:$Y$59*('Rolling CF'!$E$7:$Y$7=F$7)*('Rolling CF'!$B$10:$B$59=$B31))} -> -194090 | G31: {=SUMPRODUCT('Rolling CF'!$E$10:$Y$59*('Rolling CF'!$E$7:$Y$7=G$7)*('Rolling CF'!$B$10:$B$59=$B31))} -> 0 | H31: {=SUMPRODUCT('Rolling CF'!$E$10:$Y$59*('Rolling CF'!$E$7:$Y$7=H$7)*('Rolling CF'!$B$10:$B$59=$B31))} -> -100000 | I31: {=SUMPRODUCT('Rolling CF'!$E$10:$Y$59*('Rolling CF'!$E$7:$Y$7=I$7)*('Rolling CF'!$B$10:$B$59=$B31))} -> 0 | J31: {=SUMPRODUCT('Rolling CF'!$E$10:$Y$59*('Rolling CF'!$E$7:$Y$7=J$7)*('Rolling CF'!$B$10:$B$59=$B31))} -> -32000 | K31: {=SUMPRODUCT('Rolling CF'!$E$10:$Y$59*('Rolling CF'!$E$7:$Y$7=K$7)*('Rolling CF'!$B$10:$B$59=$B31))} -> -350210 | L31: {=SUMPRODUCT('Rolling CF'!$E$10:$Y$59*('Rolling CF'!$E$7:$Y$7=L$7)*('Rolling CF'!$B$10:$B$59=$B31))} -> 0 | ... W31: {=SUMPRODUCT('Rolling CF'!$E$10:$Y$59*('Rolling CF'!$E$7:$Y$7=W$7)*('Rolling CF'!$B$10:$B$59=$B31))} -> -216000
B32: Credit Cards | C32: ="Difference in "&B32 -> Difference in Credit Cards | E32: =E31-E30 -> 0 | F32: =F31-F30 -> 0 | G32: =G31-G30 -> 0 | H32: =H31-H30 -> 0 | I32: =I31-I30 -> 0 | J32: =J31-J30 -> 0 | K32: =K31-K30 -> -210 | L32: =L31-L30 -> 0 | ... W32: =W31-W30 -> -6000
B34: Other Ops | C34: ="Last Week's "&B34 -> Last Week's Other Ops | E34: {=SUMPRODUCT('13 weeks CF'!$E$10:$X$59*('13 weeks CF'!$E$7:$X$7=E$7)*('13 weeks CF'!$B$10:$B$59=$B34))} -> -80520 | F34: {=SUMPRODUCT('13 weeks CF'!$E$10:$X$59*('13 weeks CF'!$E$7:$X$7=F$7)*('13 weeks CF'!$B$10:$B$59=$B34))} -> -97600 | G34: {=SUMPRODUCT('13 weeks CF'!$E$10:$X$59*('13 weeks CF'!$E$7:$X$7=G$7)*('13 weeks CF'!$B$10:$B$59=$B34))} -> -55100 | H34: {=SUMPRODUCT('13 weeks CF'!$E$10:$X$59*('13 weeks CF'!$E$7:$X$7=H$7)*('13 weeks CF'!$B$10:$B$59=$B34))} -> -40270 | I34: {=SUMPRODUCT('13 weeks CF'!$E$10:$X$59*('13 weeks CF'!$E$7:$X$7=I$7)*('13 weeks CF'!$B$10:$B$59=$B34))} -> -48170 | J34: {=SUMPRODUCT('13 weeks CF'!$E$10:$X$59*('13 weeks CF'!$E$7:$X$7=J$7)*('13 weeks CF'!$B$10:$B$59=$B34))} -> -45620 | K34: {=SUMPRODUCT('13 weeks CF'!$E$10:$X$59*('13 weeks CF'!$E$7:$X$7=K$7)*('13 weeks CF'!$B$10:$B$59=$B34))} -> -63130 | L34: {=SUMPRODUCT('13 weeks CF'!$E$10:$X$59*('13 weeks CF'!$E$7:$X$7=L$7)*('13 weeks CF'!$B$10:$B$59=$B34))} -> -54398.333 | ... W34: {=SUMPRODUCT('13 weeks CF'!$E$10:$X$59*('13 weeks CF'!$E$7:$X$7=W$7)*('13 weeks CF'!$B$10:$B$59=$B34))} -> -62464.987
B35: Other Ops | C35: ="This Week's "&B35 -> This Week's Other Ops | E35: {=SUMPRODUCT('Rolling CF'!$E$10:$Y$59*('Rolling CF'!$E$7:$Y$7=E$7)*('Rolling CF'!$B$10:$B$59=$B35))} -> -80520 | F35: {=SUMPRODUCT('Rolling CF'!$E$10:$Y$59*('Rolling CF'!$E$7:$Y$7=F$7)*('Rolling CF'!$B$10:$B$59=$B35))} -> -97600 | G35: {=SUMPRODUCT('Rolling CF'!$E$10:$Y$59*('Rolling CF'!$E$7:$Y$7=G$7)*('Rolling CF'!$B$10:$B$59=$B35))} -> -55100 | H35: {=SUMPRODUCT('Rolling CF'!$E$10:$Y$59*('Rolling CF'!$E$7:$Y$7=H$7)*('Rolling CF'!$B$10:$B$59=$B35))} -> -40270 | I35: {=SUMPRODUCT('Rolling CF'!$E$10:$Y$59*('Rolling CF'!$E$7:$Y$7=I$7)*('Rolling CF'!$B$10:$B$59=$B35))} -> -48170 | J35: {=SUMPRODUCT('Rolling CF'!$E$10:$Y$59*('Rolling CF'!$E$7:$Y$7=J$7)*('Rolling CF'!$B$10:$B$59=$B35))} -> -45620 | K35: {=SUMPRODUCT('Rolling CF'!$E$10:$Y$59*('Rolling CF'!$E$7:$Y$7=K$7)*('Rolling CF'!$B$10:$B$59=$B35))} -> -43920 | L35: {=SUMPRODUCT('Rolling CF'!$E$10:$Y$59*('Rolling CF'!$E$7:$Y$7=L$7)*('Rolling CF'!$B$10:$B$59=$B35))} -> -51111.667 | ... W35: {=SUMPRODUCT('Rolling CF'!$E$10:$Y$59*('Rolling CF'!$E$7:$Y$7=W$7)*('Rolling CF'!$B$10:$B$59=$B35))} -> -56729.815
B36: Other Ops | C36: ="Difference in "&B36 -> Difference in Other Ops | E36: =E35-E34 -> 0 | F36: =F35-F34 -> 0 | G36: =G35-G34 -> 0 | H36: =H35-H34 -> 0 | I36: =I35-I34 -> 0 | J36: =J35-J34 -> 0 | K36: =K35-K34 -> 19210 | L36: =L35-L34 -> 3286.6667 | ... W36: =W35-W34 -> 5735.1718
B38: Non Ops | C38: ="Last Week's "&B38 -> Last Week's Non Ops | E38: {=SUMPRODUCT('13 weeks CF'!$E$10:$X$59*('13 weeks CF'!$E$7:$X$7=E$7)*('13 weeks CF'!$B$10:$B$59=$B38))} -> -21230 | F38: {=SUMPRODUCT('13 weeks CF'!$E$10:$X$59*('13 weeks CF'!$E$7:$X$7=F$7)*('13 weeks CF'!$B$10:$B$59=$B38))} -> -33320 | G38: {=SUMPRODUCT('13 weeks CF'!$E$10:$X$59*('13 weeks CF'!$E$7:$X$7=G$7)*('13 weeks CF'!$B$10:$B$59=$B38))} -> -20220 | H38: {=SUMPRODUCT('13 weeks CF'!$E$10:$X$59*('13 weeks CF'!$E$7:$X$7=H$7)*('13 weeks CF'!$B$10:$B$59=$B38))} -> -15340 | I38: {=SUMPRODUCT('13 weeks CF'!$E$10:$X$59*('13 weeks CF'!$E$7:$X$7=I$7)*('13 weeks CF'!$B$10:$B$59=$B38))} -> -12680 | J38: {=SUMPRODUCT('13 weeks CF'!$E$10:$X$59*('13 weeks CF'!$E$7:$X$7=J$7)*('13 weeks CF'!$B$10:$B$59=$B38))} -> -12340 | K38: {=SUMPRODUCT('13 weeks CF'!$E$10:$X$59*('13 weeks CF'!$E$7:$X$7=K$7)*('13 weeks CF'!$B$10:$B$59=$B38))} -> -19188.333 | L38: {=SUMPRODUCT('13 weeks CF'!$E$10:$X$59*('13 weeks CF'!$E$7:$X$7=L$7)*('13 weeks CF'!$B$10:$B$59=$B38))} -> -18848.056 | ... W38: {=SUMPRODUCT('13 weeks CF'!$E$10:$X$59*('13 weeks CF'!$E$7:$X$7=W$7)*('13 weeks CF'!$B$10:$B$59=$B38))} -> -16618.479
B39: Non Ops | C39: ="This Week's "&B39 -> This Week's Non Ops | E39: {=SUMPRODUCT('Rolling CF'!$E$10:$Y$59*('Rolling CF'!$E$7:$Y$7=E$7)*('Rolling CF'!$B$10:$B$59=$B39))} -> -21230 | F39: {=SUMPRODUCT('Rolling CF'!$E$10:$Y$59*('Rolling CF'!$E$7:$Y$7=F$7)*('Rolling CF'!$B$10:$B$59=$B39))} -> -33320 | G39: {=SUMPRODUCT('Rolling CF'!$E$10:$Y$59*('Rolling CF'!$E$7:$Y$7=G$7)*('Rolling CF'!$B$10:$B$59=$B39))} -> -20220 | H39: {=SUMPRODUCT('Rolling CF'!$E$10:$Y$59*('Rolling CF'!$E$7:$Y$7=H$7)*('Rolling CF'!$B$10:$B$59=$B39))} -> -15340 | I39: {=SUMPRODUCT('Rolling CF'!$E$10:$Y$59*('Rolling CF'!$E$7:$Y$7=I$7)*('Rolling CF'!$B$10:$B$59=$B39))} -> -12680 | J39: {=SUMPRODUCT('Rolling CF'!$E$10:$Y$59*('Rolling CF'!$E$7:$Y$7=J$7)*('Rolling CF'!$B$10:$B$59=$B39))} -> -12340 | K39: {=SUMPRODUCT('Rolling CF'!$E$10:$Y$59*('Rolling CF'!$E$7:$Y$7=K$7)*('Rolling CF'!$B$10:$B$59=$B39))} -> -11820 | L39: {=SUMPRODUCT('Rolling CF'!$E$10:$Y$59*('Rolling CF'!$E$7:$Y$7=L$7)*('Rolling CF'!$B$10:$B$59=$B39))} -> -17620 | ... W39: {=SUMPRODUCT('Rolling CF'!$E$10:$Y$59*('Rolling CF'!$E$7:$Y$7=W$7)*('Rolling CF'!$B$10:$B$59=$B39))} -> -14475.545
B40: Non Ops | C40: ="Difference in "&B40 -> Difference in Non Ops | E40: =E39-E38 -> 0 | F40: =F39-F38 -> 0 | G40: =G39-G38 -> 0 | H40: =H39-H38 -> 0 | I40: =I39-I38 -> 0 | J40: =J39-J38 -> 0 | K40: =K39-K38 -> 7368.3333 | L40: =L39-L38 -> 1228.0556 | ... W40: =W39-W38 -> 2142.934
C42: Commentary
C43: What Changed: | I43: Why it Changed: | Q43: What to do Next:
C44: Pulsetech can't pay | I44: Liquidity crisis | Q44: Reach out to AP team
C45: Whirlix can't pay | I45: Liquidity crisis | Q45: Reach out to AP team
C46: Astratech had larger AP balance than expected | I46: [to discuss] | Q46: [to discuss]

Sheet Rolling CF
E1: =SUMPRODUCT([result range]*([date range]=[date])*([category range]=[category]))
C2: Master Error Check Cell | D2: ='Error Checking'!$B$2 -> 0
C4: Actual / Forecast | E4: Actual | F4: Actual | G4: Actual | H4: Actual | I4: Actual | J4: Actual | K4: Actual | L4: Forecast | M4: Forecast | N4: Forecast | O4: Forecast | P4: Forecast | Q4: Forecast | R4: Forecast | S4: Forecast | T4: Forecast | U4: Forecast | V4: Forecast | W4: Forecast | X4: Forecast
C5: Week Number | E5: 1 | F5: =E5+1 -> 2 | G5: =F5+1 -> 3 | H5: =G5+1 -> 4 | I5: =H5+1 -> 5 | J5: =I5+1 -> 6 | K5: =J5+1 -> 7 | L5: =K5+1 -> 8 | M5: =L5+1 -> 9 | ... X5: =W5+1 -> 20
C6: Week Beginning | E6: 45221 | F6: =E7+1 -> 45228 | G6: =F7+1 -> 45235 | H6: =G7+1 -> 45242 | I6: =H7+1 -> 45249 | J6: =I7+1 -> 45256 | K6: =J7+1 -> 45263 | L6: =K7+1 -> 45270 | M6: =L7+1 -> 45277 | ... X6: =W7+1 -> 45354
B7: Variance Tagging | C7: Week Ending | D7: Forecast Methodology | E7: =E6+6 -> 45227 | F7: =F6+6 -> 45234 | G7: =G6+6 -> 45241 | H7: =H6+6 -> 45248 | I7: =I6+6 -> 45255 | J7: =J6+6 -> 45262 | K7: =K6+6 -> 45269 | L7: =L6+6 -> 45276 | ... X7: =X6+6 -> 45360 | Y7: Placeholder
C9: Cash Balance
C10: Beginning Cash | E10: 345580 | F10: =E12 -> 210210 | G10: =F12 -> 174090 | H10: =G12 -> 239110 | I10: =H12 -> 43360 | J10: =I12 -> 325260 | K10: =J12 -> 215160 | L10: =K12 -> 108940 | M10: =L12 -> 160208.33 | ... X10: =W12 -> -137705.13
C11: Change in Cash | E11: =E59 -> -135370 | F11: =F59 -> -36120 | G11: =G59 -> 65020 | H11: =H59 -> -195750 | I11: =I59 -> 281900 | J11: =J59 -> -110100 | K11: =K59 -> -106220 | L11: =L59 -> 51268.333 | ... X11: =X59 -> -59244.097
B12: Ending Cash | C12: Ending Cash | E12: =SUM(E10:E11) -> 210210 | F12: =SUM(F10:F11) -> 174090 | G12: =SUM(G10:G11) -> 239110 | H12: =SUM(H10:H11) -> 43360 | I12: =SUM(I10:I11) -> 325260 | J12: =SUM(J10:J11) -> 215160 | K12: =SUM(K10:K11) -> 108940 | L12: =SUM(L10:L11) -> 160208.33 | ... X12: =SUM(X10:X11) -> -196949.22
C13: Per Data | E13: 210210 | F13: 174090 | G13: 239110 | H13: 43360 | I13: 325260 | J13: 215160 | K13: 108940
C14: Double-Check | E14: =IF(E$4="Forecast",0,E13-E12) -> 0 | F14: =IF(F$4="Forecast",0,F13-F12) -> 0 | G14: =IF(G$4="Forecast",0,G13-G12) -> 0 | H14: =IF(H$4="Forecast",0,H13-H12) -> 0 | I14: =IF(I$4="Forecast",0,I13-I12) -> 0 | J14: =IF(J$4="Forecast",0,J13-J12) -> 0 | K14: =IF(K$4="Forecast",0,K13-K12) -> 0 | L14: =IF(L$4="Forecast",0,L13-L12) -> 0 | ... X14: =IF(X$4="Forecast",0,X13-X12) -> 0
C15: Last Week's Forecast | E15: 210210 | F15: 174090 | G15: 239110 | H15: 43360 | I15: 325260 | J15: 215160 | K15: 112041.67 | L15: 156995.28 | M15: 399451.16 | N15: 415303.02 | O15: 382731.85 | P15: 316373.83 | Q15: 519442.8 | R15: 532142.99 | S15: 472334.27 | T15: 279031.46 | U15: 412252.87 | V15: 580273.04 | W15: 291189.57
C17: Cash Inflows
B18: Invoiced AR + New Revenue | C18: Invoiced AR + New Revenue | D18: See AR Aging Schedule | E18: =SUMIFS(Actuals!$I:$I,Actuals!$A:$A,E$7,Actuals!$C:$C,$C18) -> 0 | F18: =SUMIFS(Actuals!$I:$I,Actuals!$A:$A,F$7,Actuals!$C:$C,$C18) -> 372100 | G18: =SUMIFS(Actuals!$I:$I,Actuals!$A:$A,G$7,Actuals!$C:$C,$C18) -> 210150 | H18: =SUMIFS(Actuals!$I:$I,Actuals!$A:$A,H$7,Actuals!$C:$C,$C18) -> 0 | I18: =SUMIFS(Actuals!$I:$I,Actuals!$A:$A,I$7,Actuals!$C:$C,$C18) -> 361430 | J18: =SUMIFS(Actuals!$I:$I,Actuals!$A:$A,J$7,Actuals!$C:$C,$C18) -> 68440 | K18: =SUMIFS(Actuals!$I:$I,Actuals!$A:$A,K$7,Actuals!$C:$C,$C18) -> 389470 | L18: =SUMIFS('AR Aging 02'!$B:$B,'AR Aging 02'!$A:$A,L$7) -> 120000 | M18: =SUMIFS('AR Aging 02'!$B:$B,'AR Aging 02'!$A:$A,M$7) -> 554000 | N18: =SUMIFS('AR Aging 02'!$B:$B,'AR Aging 02'!$A:$A,N$7) -> 80000 | O18: =SUMIFS('AR Aging 02'!$B:$B,'AR Aging 02'!$A:$A,O$7) -> 198400 | P18: =SUMIFS('AR Aging 02'!$B:$B,'AR Aging 02'!$A:$A,P$7) -> 0 | Q18: =SUMIFS('AR Aging 02'!$B:$B,'AR Aging 02'!$A:$A,Q$7) -> 271800 | R18: =SUMIFS('AR Aging 02'!$B:$B,'AR Aging 02'!$A:$A,R$7) -> 80000 | S18: =SUMIFS('AR Aging 02'!$B:$B,'AR Aging 02'!$A:$A,S$7) -> 0 | ... X18: =SUMIFS('AR Aging 02'!$B:$B,'AR Aging 02'!$A:$A,X$7) -> 0
B19: Invoiced AR + New Revenue | C19: Other Inflows | D19: Enter Manually | E19: =SUMIFS(Actuals!$I:$I,Actuals!$A:$A,E$7,Actuals!$C:$C,$C19) -> 0 | F19: =SUMIFS(Actuals!$I:$I,Actuals!$A:$A,F$7,Actuals!$C:$C,$C19) -> 0 | G19: =SUMIFS(Actuals!$I:$I,Actuals!$A:$A,G$7,Actuals!$C:$C,$C19) -> 0 | H19: =SUMIFS(Actuals!$I:$I,Actuals!$A:$A,H$7,Actuals!$C:$C,$C19) -> 0 | I19: =SUMIFS(Actuals!$I:$I,Actuals!$A:$A,I$7,Actuals!$C:$C,$C19) -> 0 | J19: =SUMIFS(Actuals!$I:$I,Actuals!$A:$A,J$7,Actuals!$C:$C,$C19) -> 0 | K19: =SUMIFS(Actuals!$I:$I,Actuals!$A:$A,K$7,Actuals!$C:$C,$C19) -> 0
C21: Total Cash Inflows | E21: =SUM(E18:E20) -> 0 | F21: =SUM(F18:F20) -> 372100 | G21: =SUM(G18:G20) -> 210150 | H21: =SUM(H18:H20) -> 0 | I21: =SUM(I18:I20) -> 361430 | J21: =SUM(J18:J20) -> 68440 | K21: =SUM(K18:K20) -> 389470 | L21: =SUM(L18:L20) -> 120000 | ... X21: =SUM(X18:X20) -> 0
C23: Operating Cash Outflows
B24: Accounts Payable | C24: Accounts Payable | D24: See AP Aging Schedule | E24: =SUMIFS(Actuals!$I:$I,Actuals!$A:$A,E$7,Actuals!$C:$C,$C24) -> -33620 | F24: =SUMIFS(Actuals!$I:$I,Actuals!$A:$A,F$7,Actuals!$C:$C,$C24) -> -83210 | G24: =SUMIFS(Actuals!$I:$I,Actuals!$A:$A,G$7,Actuals!$C:$C,$C24) -> -69810 | H24: =SUMIFS(Actuals!$I:$I,Actuals!$A:$A,H$7,Actuals!$C:$C,$C24) -> -40140 | I24: =SUMIFS(Actuals!$I:$I,Actuals!$A:$A,I$7,Actuals!$C:$C,$C24) -> -18680 | J24: =SUMIFS(Actuals!$I:$I,Actuals!$A:$A,J$7,Actuals!$C:$C,$C24) -> -88580 | K24: =SUMIFS(Actuals!$I:$I,Actuals!$A:$A,K$7,Actuals!$C:$C,$C24) -> -89740 | L24: =-SUMIFS('AP Aging 02'!$B:$B,'AP Aging 02'!$A:$A,L$7,'AP Aging 02'!$D:$D,"<>Yes") -> 0 | M24: =-SUMIFS('AP Aging 02'!$B:$B,'AP Aging 02'!$A:$A,M$7,'AP Aging 02'!$D:$D,"<>Yes") -> -164600 | N24: =-SUMIFS('AP Aging 02'!$B:$B,'AP Aging 02'!$A:$A,N$7,'AP Aging 02'!$D:$D,"<>Yes") -> 0 | O24: =-SUMIFS('AP Aging 02'!$B:$B,'AP Aging 02'!$A:$A,O$7,'AP Aging 02'!$D:$D,"<>Yes") -> 0 | P24: =-SUMIFS('AP Aging 02'!$B:$B,'AP Aging 02'!$A:$A,P$7,'AP Aging 02'!$D:$D,"<>Yes") -> 0 | Q24: =-SUMIFS('AP Aging 02'!$B:$B,'AP Aging 02'!$A:$A,Q$7,'AP Aging 02'!$D:$D,"<>Yes") -> -50000 | R24: =-SUMIFS('AP Aging 02'!$B:$B,'AP Aging 02'!$A:$A,R$7,'AP Aging 02'!$D:$D,"<>Yes") -> 0 | S24: =-SUMIFS('AP Aging 02'!$B:$B,'AP Aging 02'!$A:$A,S$7,'AP Aging 02'!$D:$D,"<>Yes") -> 0 | ... X24: =-SUMIFS('AP Aging 02'!$B:$B,'AP Aging 02'!$A:$A,X$7,'AP Aging 02'!$D:$D,"<>Yes") -> 0
B25: Credit Cards | C25: Credit Cards | D25: See AP Aging Schedule | E25: =SUMIFS(Actuals!$I:$I,Actuals!$A:$A,E$7,Actuals!$C:$C,$C25) -> 0 | F25: =SUMIFS(Actuals!$I:$I,Actuals!$A:$A,F$7,Actuals!$C:$C,$C25) -> -194090 | G25: =SUMIFS(Actuals!$I:$I,Actuals!$A:$A,G$7,Actuals!$C:$C,$C25) -> 0 | H25: =SUMIFS(Actuals!$I:$I,Actuals!$A:$A,H$7,Actuals!$C:$C,$C25) -> -100000 | I25: =SUMIFS(Actuals!$I:$I,Actuals!$A:$A,I$7,Actuals!$C:$C,$C25) -> 0 | J25: =SUMIFS(Actuals!$I:$I,Actuals!$A:$A,J$7,Actuals!$C:$C,$C25) -> -32000 | K25: =SUMIFS(Actuals!$I:$I,Actuals!$A:$A,K$7,Actuals!$C:$C,$C25) -> -350210 | L25: =-SUMIFS('AP Aging 02'!$B:$B,'AP Aging 02'!$A:$A,L$7,'AP Aging 02'!$D:$D,"Yes") -> 0 | M25: =-SUMIFS('AP Aging 02'!$B:$B,'AP Aging 02'!$A:$A,M$7,'AP Aging 02'!$D:$D,"Yes") -> 0 | N25: =-SUMIFS('AP Aging 02'!$B:$B,'AP Aging 02'!$A:$A,N$7,'AP Aging 02'!$D:$D,"Yes") -> 0 | O25: =-SUMIFS('AP Aging 02'!$B:$B,'AP Aging 02'!$A:$A,O$7,'AP Aging 02'!$D:$D,"Yes") -> -153000 | P25: =-SUMIFS('AP Aging 02'!$B:$B,'AP Aging 02'!$A:$A,P$7,'AP Aging 02'!$D:$D,"Yes") -> 0 | Q25: =-SUMIFS('AP Aging 02'!$B:$B,'AP Aging 02'!$A:$A,Q$7,'AP Aging 02'!$D:$D,"Yes") -> 0 | R25: =-SUMIFS('AP Aging 02'!$B:$B,'AP Aging 02'!$A:$A,R$7,'AP Aging 02'!$D:$D,"Yes") -> 0 | S25: =-SUMIFS('AP Aging 02'!$B:$B,'AP Aging 02'!$A:$A,S$7,'AP Aging 02'!$D:$D,"Yes") -> -203600 | ... X25: =-SUMIFS('AP Aging 02'!$B:$B,'AP Aging 02'!$A:$A,X$7,'AP Aging 02'!$D:$D,"Yes") -> 0
B26: Other Ops | C26: Payroll | D26: Trailing 6 Week Average | E26: =SUMIFS(Actuals!$I:$I,Actuals!$A:$A,E$7,Actuals!$C:$C,$C26) -> -77830 | F26: =SUMIFS(Actuals!$I:$I,Actuals!$A:$A,F$7,Actuals!$C:$C,$C26) -> -78050 | G26: =SUMIFS(Actuals!$I:$I,Actuals!$A:$A,G$7,Actuals!$C:$C,$C26) -> -51670 | H26: =SUMIFS(Actuals!$I:$I,Actuals!$A:$A,H$7,Actuals!$C:$C,$C26) -> -39960 | I26: =SUMIFS(Actuals!$I:$I,Actuals!$A:$A,I$7,Actuals!$C:$C,$C26) -> -44380 | J26: =SUMIFS(Actuals!$I:$I,Actuals!$A:$A,J$7,Actuals!$C:$C,$C26) -> -35340 | K26: =SUMIFS(Actuals!$I:$I,Actuals!$A:$A,K$7,Actuals!$C:$C,$C26) -> -35660 | L26: =AVERAGE(F26:K26) -> -47510 | M26: =AVERAGE(G26:L26) -> -42420 | N26: =AVERAGE(H26:M26) -> -40878.333 | O26: =AVERAGE(I26:N26) -> -41031.389 | P26: =AVERAGE(J26:O26) -> -40473.287 | Q26: =AVERAGE(K26:P26) -> -41328.835 | R26: =AVERAGE(L26:Q26) -> -42273.641 | S26: =AVERAGE(M26:R26) -> -41400.914 | ... X26: =AVERAGE(R26:W26) -> -41500.77
B27: Other Ops | C27: Contractors | D27: Enter Manually | E27: =SUMIFS(Actuals!$I:$I,Actuals!$A:$A,E$7,Actuals!$C:$C,$C27) -> 0 | F27: =SUMIFS(Actuals!$I:$I,Actuals!$A:$A,F$7,Actuals!$C:$C,$C27) -> 0 | G27: =SUMIFS(Actuals!$I:$I,Actuals!$A:$A,G$7,Actuals!$C:$C,$C27) -> 0 | H27: =SUMIFS(Actuals!$I:$I,Actuals!$A:$A,H$7,Actuals!$C:$C,$C27) -> 0 | I27: =SUMIFS(Actuals!$I:$I,Actuals!$A:$A,I$7,Actuals!$C:$C,$C27) -> 0 | J27: =SUMIFS(Actuals!$I:$I,Actuals!$A:$A,J$7,Actuals!$C:$C,$C27) -> 0 | K27: =SUMIFS(Actuals!$I:$I,Actuals!$A:$A,K$7,Actuals!$C:$C,$C27) -> 0
B28: Other Ops | C28: Dues & Subscriptions | D28: Trailing 6 Week Average | E28: =SUMIFS(Actuals!$I:$I,Actuals!$A:$A,E$7,Actuals!$C:$C,$C28) -> -310 | F28: =SUMIFS(Actuals!$I:$I,Actuals!$A:$A,F$7,Actuals!$C:$C,$C28) -> -310 | G28: =SUMIFS(Actuals!$I:$I,Actuals!$A:$A,G$7,Actuals!$C:$C,$C28) -> -310 | H28: =SUMIFS(Actuals!$I:$I,Actuals!$A:$A,H$7,Actuals!$C:$C,$C28) -> -310 | I28: =SUMIFS(Actuals!$I:$I,Actuals!$A:$A,I$7,Actuals!$C:$C,$C28) -> -310 | J28: =SUMIFS(Actuals!$I:$I,Actuals!$A:$A,J$7,Actuals!$C:$C,$C28) -> -310 | K28: =SUMIFS(Actuals!$I:$I,Actuals!$A:$A,K$7,Actuals!$C:$C,$C28) -> -310 | L28: =AVERAGE(F28:K28) -> -310 | M28: =AVERAGE(G28:L28) -> -310 | N28: =AVERAGE(H28:M28) -> -310 | O28: =AVERAGE(I28:N28) -> -310 | P28: =AVERAGE(J28:O28) -> -310 | Q28: =AVERAGE(K28:P28) -> -310 | R28: =AVERAGE(L28:Q28) -> -310 | S28: =AVERAGE(M28:R28) -> -310 | ... X28: =AVERAGE(R28:W28) -> -310
B29: Other Ops | C29: Insurance | D29: Enter Manually | E29: =SUMIFS(Actuals!$I:$I,Actuals!$A:$A,E$7,Actuals!$C:$C,$C29) -> 0 | F29: =SUMIFS(Actuals!$I:$I,Actuals!$A:$A,F$7,Actuals!$C:$C,$C29) -> 0 | G29: =SUMIFS(Actuals!$I:$I,Actuals!$A:$A,G$7,Actuals!$C:$C,$C29) -> 0 | H29: =SUMIFS(Actuals!$I:$I,Actuals!$A:$A,H$7,Actuals!$C:$C,$C29) -> 0 | I29: =SUMIFS(Actuals!$I:$I,Actuals!$A:$A,I$7,Actuals!$C:$C,$C29) -> 0 | J29: =SUMIFS(Actuals!$I:$I,Actuals!$A:$A,J$7,Actuals!$C:$C,$C29) -> 0 | K29: =SUMIFS(Actuals!$I:$I,Actuals!$A:$A,K$7,Actuals!$C:$C,$C29) -> 0
B30: Other Ops | C30: Lease Payments | D30: Trailing 6 Week Average | E30: =SUMIFS(Actuals!$I:$I,Actuals!$A:$A,E$7,Actuals!$C:$C,$C30) -> 0 | F30: =SUMIFS(Actuals!$I:$I,Actuals!$A:$A,F$7,Actuals!$C:$C,$C30) -> -1350 | G30: =SUMIFS(Actuals!$I:$I,Actuals!$A:$A,G$7,Actuals!$C:$C,$C30) -> 0 | H30: =SUMIFS(Actuals!$I:$I,Actuals!$A:$A,H$7,Actuals!$C:$C,$C30) -> 0 | I30: =SUMIFS(Actuals!$I:$I,Actuals!$A:$A,I$7,Actuals!$C:$C,$C30) -> -1350 | J30: =SUMIFS(Actuals!$I:$I,Actuals!$A:$A,J$7,Actuals!$C:$C,$C30) -> -1350 | K30: =SUMIFS(Actuals!$I:$I,Actuals!$A:$A,K$7,Actuals!$C:$C,$C30) -> 0 | L30: =AVERAGE(F30:K30) -> -675 | M30: =AVERAGE(G30:L30) -> -562.5 | N30: =AVERAGE(H30:M30) -> -656.25 | O30: =AVERAGE(I30:N30) -> -765.625 | P30: =AVERAGE(J30:O30) -> -668.22917 | Q30: =AVERAGE(K30:P30) -> -554.60069 | R30: =AVERAGE(L30:Q30) -> -647.03414 | S30: =AVERAGE(M30:R30) -> -642.37317 | ... X30: =AVERAGE(R30:W30) -> -645.00429
B31: Other Ops | C31: Marketing | D31: Trailing 6 Week Average | E31: =SUMIFS(Actuals!$I:$I,Actuals!$A:$A,E$7,Actuals!$C:$C,$C31) -> 0 | F31: =SUMIFS(Actuals!$I:$I,Actuals!$A:$A,F$7,Actuals!$C:$C,$C31) -> -1510 | G31: =SUMIFS(Actuals!$I:$I,Actuals!$A:$A,G$7,Actuals!$C:$C,$C31) -> -1020 | H31: =SUMIFS(Actuals!$I:$I,Actuals!$A:$A,H$7,Actuals!$C:$C,$C31) -> 0 | I31: =SUMIFS(Actuals!$I:$I,Actuals!$A:$A,I$7,Actuals!$C:$C,$C31) -> 0 | J31: =SUMIFS(Actuals!$I:$I,Actuals!$A:$A,J$7,Actuals!$C:$C,$C31) -> -1510 | K31: =SUMIFS(Actuals!$I:$I,Actuals!$A:$A,K$7,Actuals!$C:$C,$C31) -> 0 | L31: =AVERAGE(F31:K31) -> -673.33333 | M31: =AVERAGE(G31:L31) -> -533.88889 | N31: =AVERAGE(H31:M31) -> -452.87037 | O31: =AVERAGE(I31:N31) -> -528.34877 | P31: =AVERAGE(J31:O31) -> -616.40689 | Q31: =AVERAGE(K31:P31) -> -467.47471 | R31: =AVERAGE(L31:Q31) -> -545.38716 | S31: =AVERAGE(M31:R31) -> -524.0628 | ... X31: =AVERAGE(R31:W31) -> -530.37388
B32: Other Ops | C32: Phone & Internet | D32: Enter Manually | E32: =SUMIFS(Actuals!$I:$I,Actuals!$A:$A,E$7,Actuals!$C:$C,$C32) -> 0 | F32: =SUMIFS(Actuals!$I:$I,Actuals!$A:$A,F$7,Actuals!$C:$C,$C32) -> 0 | G32: =SUMIFS(Actuals!$I:$I,Actuals!$A:$A,G$7,Actuals!$C:$C,$C32) -> 0 | H32: =SUMIFS(Actuals!$I:$I,Actuals!$A:$A,H$7,Actuals!$C:$C,$C32) -> 0 | I32: =SUMIFS(Actuals!$I:$I,Actuals!$A:$A,I$7,Actuals!$C:$C,$C32) -> 0 | J32: =SUMIFS(Actuals!$I:$I,Actuals!$A:$A,J$7,Actuals!$C:$C,$C32) -> 0 | K32: =SUMIFS(Actuals!$I:$I,Actuals!$A:$A,K$7,Actuals!$C:$C,$C32) -> 0
B33: Other Ops | C33: Professional Fees | D33: $5k each Month | E33: =SUMIFS(Actuals!$I:$I,Actuals!$A:$A,E$7,Actuals!$C:$C,$C33) -> 0 | F33: =SUMIFS(Actuals!$I:$I,Actuals!$A:$A,F$7,Actuals!$C:$C,$C33) -> -5000 | G33: =SUMIFS(Actuals!$I:$I,Actuals!$A:$A,G$7,Actuals!$C:$C,$C33) -> 0 | H33: =SUMIFS(Actuals!$I:$I,Actuals!$A:$A,H$7,Actuals!$C:$C,$C33) -> 0 | I33: =SUMIFS(Actuals!$I:$I,Actuals!$A:$A,I$7,Actuals!$C:$C,$C33) -> 0 | J33: =SUMIFS(Actuals!$I:$I,Actuals!$A:$A,J$7,Actuals!$C:$C,$C33) -> 0 | K33: =SUMIFS(Actuals!$I:$I,Actuals!$A:$A,K$7,Actuals!$C:$C,$C33) -> -5000 | O33: -5000 | S33: -5000 | W33: -5000
B34: Other Ops | C34: Rent | D34: Enter Manually | E34: =SUMIFS(Actuals!$I:$I,Actuals!$A:$A,E$7,Actuals!$C:$C,$C34) -> 0 | F34: =SUMIFS(Actuals!$I:$I,Actuals!$A:$A,F$7,Actuals!$C:$C,$C34) -> 0 | G34: =SUMIFS(Actuals!$I:$I,Actuals!$A:$A,G$7,Actuals!$C:$C,$C34) -> 0 | H34: =SUMIFS(Actuals!$I:$I,Actuals!$A:$A,H$7,Actuals!$C:$C,$C34) -> 0 | I34: =SUMIFS(Actuals!$I:$I,Actuals!$A:$A,I$7,Actuals!$C:$C,$C34) -> 0 | J34: =SUMIFS(Actuals!$I:$I,Actuals!$A:$A,J$7,Actuals!$C:$C,$C34) -> 0 | K34: =SUMIFS(Actuals!$I:$I,Actuals!$A:$A,K$7,Actuals!$C:$C,$C34) -> 0
B35: Other Ops | C35: Repairs & Maintenance | D35: Enter Manually | E35: =SUMIFS(Actuals!$I:$I,Actuals!$A:$A,E$7,Actuals!$C:$C,$C35) -> 0 | F35: =SUMIFS(Actuals!$I:$I,Actuals!$A:$A,F$7,Actuals!$C:$C,$C35) -> 0 | G35: =SUMIFS(Actuals!$I:$I,Actuals!$A:$A,G$7,Actuals!$C:$C,$C35) -> 0 | H35: =SUMIFS(Actuals!$I:$I,Actuals!$A:$A,H$7,Actuals!$C:$C,$C35) -> 0 | I35: =SUMIFS(Actuals!$I:$I,Actuals!$A:$A,I$7,Actuals!$C:$C,$C35) -> 0 | J35: =SUMIFS(Actuals!$I:$I,Actuals!$A:$A,J$7,Actuals!$C:$C,$C35) -> 0 | K35: =SUMIFS(Actuals!$I:$I,Actuals!$A:$A,K$7,Actuals!$C:$C,$C35) -> 0
B36: Other Ops | C36: Supplies | D36: Enter Manually | E36: =SUMIFS(Actuals!$I:$I,Actuals!$A:$A,E$7,Actuals!$C:$C,$C36) -> 0 | F36: =SUMIFS(Actuals!$I:$I,Actuals!$A:$A,F$7,Actuals!$C:$C,$C36) -> 0 | G36: =SUMIFS(Actuals!$I:$I,Actuals!$A:$A,G$7,Actuals!$C:$C,$C36) -> 0 | H36: =SUMIFS(Actuals!$I:$I,Actuals!$A:$A,H$7,Actuals!$C:$C,$C36) -> 0 | I36: =SUMIFS(Actuals!$I:$I,Actuals!$A:$A,I$7,Actuals!$C:$C,$C36) -> 0 | J36: =SUMIFS(Actuals!$I:$I,Actuals!$A:$A,J$7,Actuals!$C:$C,$C36) -> 0 | K36: =SUMIFS(Actuals!$I:$I,Actuals!$A:$A,K$7,Actuals!$C:$C,$C36) -> 0
B37: Other Ops | C37: Licenses | D37: Enter Manually | E37: =SUMIFS(Actuals!$I:$I,Actuals!$A:$A,E$7,Actuals!$C:$C,$C37) -> 0 | F37: =SUMIFS(Actuals!$I:$I,Actuals!$A:$A,F$7,Actuals!$C:$C,$C37) -> 0 | G37: =SUMIFS(Actuals!$I:$I,Actuals!$A:$A,G$7,Actuals!$C:$C,$C37) -> 0 | H37: =SUMIFS(Actuals!$I:$I,Actuals!$A:$A,H$7,Actuals!$C:$C,$C37) -> 0 | I37: =SUMIFS(Actuals!$I:$I,Actuals!$A:$A,I$7,Actuals!$C:$C,$C37) -> 0 | J37: =SUMIFS(Actuals!$I:$I,Actuals!$A:$A,J$7,Actuals!$C:$C,$C37) -> 0 | K37: =SUMIFS(Actuals!$I:$I,Actuals!$A:$A,K$7,Actuals!$C:$C,$C37) -> 0
B38: Other Ops | C38: Technology | D38: Trailing 6 Week Average | E38: =SUMIFS(Actuals!$I:$I,Actuals!$A:$A,E$7,Actuals!$C:$C,$C38) -> -1110 | F38: =SUMIFS(Actuals!$I:$I,Actuals!$A:$A,F$7,Actuals!$C:$C,$C38) -> -1150 | G38: =SUMIFS(Actuals!$I:$I,Actuals!$A:$A,G$7,Actuals!$C:$C,$C38) -> -2100 | H38: =SUMIFS(Actuals!$I:$I,Actuals!$A:$A,H$7,Actuals!$C:$C,$C38) -> 0 | I38: =SUMIFS(Actuals!$I:$I,Actuals!$A:$A,I$7,Actuals!$C:$C,$C38) -> -2130 | J38: =SUMIFS(Actuals!$I:$I,Actuals!$A:$A,J$7,Actuals!$C:$C,$C38) -> 0 | K38: =SUMIFS(Actuals!$I:$I,Actuals!$A:$A,K$7,Actuals!$C:$C,$C38) -> -860 | L38: =AVERAGE(F38:K38) -> -1040 | M38: =AVERAGE(G38:L38) -> -1021.6667 | N38: =AVERAGE(H38:M38) -> -841.94444 | O38: =AVERAGE(I38:N38) -> -982.26852 | P38: =AVERAGE(J38:O38) -> -790.97994 | Q38: =AVERAGE(K38:P38) -> -922.80993 | R38: =AVERAGE(L38:Q38) -> -933.27825 | S38: =AVERAGE(M38:R38) -> -915.49129 | ... X38: =AVERAGE(R38:W38) -> -910.01463
B39: Other Ops | C39: Training | D39: Enter Manually | E39: =SUMIFS(Actuals!$I:$I,Actuals!$A:$A,E$7,Actuals!$C:$C,$C39) -> 0 | F39: =SUMIFS(Actuals!$I:$I,Actuals!$A:$A,F$7,Actuals!$C:$C,$C39) -> 0 | G39: =SUMIFS(Actuals!$I:$I,Actuals!$A:$A,G$7,Actuals!$C:$C,$C39) -> 0 | H39: =SUMIFS(Actuals!$I:$I,Actuals!$A:$A,H$7,Actuals!$C:$C,$C39) -> 0 | I39: =SUMIFS(Actuals!$I:$I,Actuals!$A:$A,I$7,Actuals!$C:$C,$C39) -> 0 | J39: =SUMIFS(Actuals!$I:$I,Actuals!$A:$A,J$7,Actuals!$C:$C,$C39) -> 0 | K39: =SUMIFS(Actuals!$I:$I,Actuals!$A:$A,K$7,Actuals!$C:$C,$C39) -> 0
B40: Other Ops | C40: Travel & Entertainment | D40: Enter Manually | E40: =SUMIFS(Actuals!$I:$I,Actuals!$A:$A,E$7,Actuals!$C:$C,$C40) -> 0 | F40: =SUMIFS(Actuals!$I:$I,Actuals!$A:$A,F$7,Actuals!$C:$C,$C40) -> 0 | G40: =SUMIFS(Actuals!$I:$I,Actuals!$A:$A,G$7,Actuals!$C:$C,$C40) -> 0 | H40: =SUMIFS(Actuals!$I:$I,Actuals!$A:$A,H$7,Actuals!$C:$C,$C40) -> 0 | I40: =SUMIFS(Actuals!$I:$I,Actuals!$A:$A,I$7,Actuals!$C:$C,$C40) -> 0 | J40: =SUMIFS(Actuals!$I:$I,Actuals!$A:$A,J$7,Actuals!$C:$C,$C40) -> 0 | K40: =SUMIFS(Actuals!$I:$I,Actuals!$A:$A,K$7,Actuals!$C:$C,$C40) -> 0
B41: Other Ops | C41: Utilities | D41: Enter Manually | E41: =SUMIFS(Actuals!$I:$I,Actuals!$A:$A,E$7,Actuals!$C:$C,$C41) -> 0 | F41: =SUMIFS(Actuals!$I:$I,Actuals!$A:$A,F$7,Actuals!$C:$C,$C41) -> 0 | G41: =SUMIFS(Actuals!$I:$I,Actuals!$A:$A,G$7,Actuals!$C:$C,$C41) -> 0 | H41: =SUMIFS(Actuals!$I:$I,Actuals!$A:$A,H$7,Actuals!$C:$C,$C41) -> 0 | I41: =SUMIFS(Actuals!$I:$I,Actuals!$A:$A,I$7,Actuals!$C:$C,$C41) -> 0 | J41: =SUMIFS(Actuals!$I:$I,Actuals!$A:$A,J$7,Actuals!$C:$C,$C41) -> 0 | K41: =SUMIFS(Actuals!$I:$I,Actuals!$A:$A,K$7,Actuals!$C:$C,$C41) -> 0
B42: Other Ops | C42: Vehicles | D42: $7k each Month | E42: =SUMIFS(Actuals!$I:$I,Actuals!$A:$A,E$7,Actuals!$C:$C,$C42) -> 0 | F42: =SUMIFS(Actuals!$I:$I,Actuals!$A:$A,F$7,Actuals!$C:$C,$C42) -> -7660 | G42: =SUMIFS(Actuals!$I:$I,Actuals!$A:$A,G$7,Actuals!$C:$C,$C42) -> 0 | H42: =SUMIFS(Actuals!$I:$I,Actuals!$A:$A,H$7,Actuals!$C:$C,$C42) -> 0 | I42: =SUMIFS(Actuals!$I:$I,Actuals!$A:$A,I$7,Actuals!$C:$C,$C42) -> 0 | J42: =SUMIFS(Actuals!$I:$I,Actuals!$A:$A,J$7,Actuals!$C:$C,$C42) -> -5840 | K42: =SUMIFS(Actuals!$I:$I,Actuals!$A:$A,K$7,Actuals!$C:$C,$C42) -> -510 | O42: -7000 | S42: -7000 | W42: -7000
B43: Other Ops | C43: Other Operating Outflows | D43: Trailing 6 Week Average | E43: =SUMIFS(Actuals!$I:$I,Actuals!$A:$A,E$7,Actuals!$C:$C,$C43) -> -1270 | F43: =SUMIFS(Actuals!$I:$I,Actuals!$A:$A,F$7,Actuals!$C:$C,$C43) -> -2570 | G43: =SUMIFS(Actuals!$I:$I,Actuals!$A:$A,G$7,Actuals!$C:$C,$C43) -> 0 | H43: =SUMIFS(Actuals!$I:$I,Actuals!$A:$A,H$7,Actuals!$C:$C,$C43) -> 0 | I43: =SUMIFS(Actuals!$I:$I,Actuals!$A:$A,I$7,Actuals!$C:$C,$C43) -> 0 | J43: =SUMIFS(Actuals!$I:$I,Actuals!$A:$A,J$7,Actuals!$C:$C,$C43) -> -1270 | K43: =SUMIFS(Actuals!$I:$I,Actuals!$A:$A,K$7,Actuals!$C:$C,$C43) -> -1580 | L43: =AVERAGE(F43:K43) -> -903.33333 | M43: =AVERAGE(G43:L43) -> -625.55556 | N43: =AVERAGE(H43:M43) -> -729.81481 | O43: =AVERAGE(I43:N43) -> -851.45062 | P43: =AVERAGE(J43:O43) -> -993.35905 | Q43: =AVERAGE(K43:P43) -> -947.25223 | R43: =AVERAGE(L43:Q43) -> -841.79427 | S43: =AVERAGE(M43:R43) -> -831.53776 | ... X43: =AVERAGE(R43:W43) -> -866.79278
C45: Total Operating Cash Outflows | E45: =SUM(E24:E44) -> -114140 | F45: =SUM(F24:F44) -> -374900 | G45: =SUM(G24:G44) -> -124910 | H45: =SUM(H24:H44) -> -180410 | I45: =SUM(I24:I44) -> -66850 | J45: =SUM(J24:J44) -> -166200 | K45: =SUM(K24:K44) -> -483870 | L45: =SUM(L24:L44) -> -51111.667 | ... X45: =SUM(X24:X44) -> -44762.955
C47: Non-operating Cash Outflows
B48: Non Ops | C48: Capital Expenditures | D48: Enter Manually | E48: =SUMIFS(Actuals!$I:$I,Actuals!$A:$A,E$7,Actuals!$C:$C,$C48) -> 0 | F48: =SUMIFS(Actuals!$I:$I,Actuals!$A:$A,F$7,Actuals!$C:$C,$C48) -> 0 | G48: =SUMIFS(Actuals!$I:$I,Actuals!$A:$A,G$7,Actuals!$C:$C,$C48) -> 0 | H48: =SUMIFS(Actuals!$I:$I,Actuals!$A:$A,H$7,Actuals!$C:$C,$C48) -> 0 | I48: =SUMIFS(Actuals!$I:$I,Actuals!$A:$A,I$7,Actuals!$C:$C,$C48) -> 0 | J48: =SUMIFS(Actuals!$I:$I,Actuals!$A:$A,J$7,Actuals!$C:$C,$C48) -> 0 | K48: =SUMIFS(Actuals!$I:$I,Actuals!$A:$A,K$7,Actuals!$C:$C,$C48) -> 0
B49: Non Ops | C49: Debt Proceeds | D49: Enter Manually | E49: =SUMIFS(Actuals!$I:$I,Actuals!$A:$A,E$7,Actuals!$C:$C,$C49) -> 0 | F49: =SUMIFS(Actuals!$I:$I,Actuals!$A:$A,F$7,Actuals!$C:$C,$C49) -> 0 | G49: =SUMIFS(Actuals!$I:$I,Actuals!$A:$A,G$7,Actuals!$C:$C,$C49) -> 0 | H49: =SUMIFS(Actuals!$I:$I,Actuals!$A:$A,H$7,Actuals!$C:$C,$C49) -> 0 | I49: =SUMIFS(Actuals!$I:$I,Actuals!$A:$A,I$7,Actuals!$C:$C,$C49) -> 0 | J49: =SUMIFS(Actuals!$I:$I,Actuals!$A:$A,J$7,Actuals!$C:$C,$C49) -> 0 | K49: =SUMIFS(Actuals!$I:$I,Actuals!$A:$A,K$7,Actuals!$C:$C,$C49) -> 0
B50: Non Ops | C50: Interest Payments | D50: Enter Manually | E50: =SUMIFS(Actuals!$I:$I,Actuals!$A:$A,E$7,Actuals!$C:$C,$C50) -> 0 | F50: =SUMIFS(Actuals!$I:$I,Actuals!$A:$A,F$7,Actuals!$C:$C,$C50) -> 0 | G50: =SUMIFS(Actuals!$I:$I,Actuals!$A:$A,G$7,Actuals!$C:$C,$C50) -> 0 | H50: =SUMIFS(Actuals!$I:$I,Actuals!$A:$A,H$7,Actuals!$C:$C,$C50) -> 0 | I50: =SUMIFS(Actuals!$I:$I,Actuals!$A:$A,I$7,Actuals!$C:$C,$C50) -> 0 | J50: =SUMIFS(Actuals!$I:$I,Actuals!$A:$A,J$7,Actuals!$C:$C,$C50) -> 0 | K50: =SUMIFS(Actuals!$I:$I,Actuals!$A:$A,K$7,Actuals!$C:$C,$C50) -> 0
B51: Non Ops | C51: Principal Payments | D51: Enter Manually | E51: =SUMIFS(Actuals!$I:$I,Actuals!$A:$A,E$7,Actuals!$C:$C,$C51) -> 0 | F51: =SUMIFS(Actuals!$I:$I,Actuals!$A:$A,F$7,Actuals!$C:$C,$C51) -> 0 | G51: =SUMIFS(Actuals!$I:$I,Actuals!$A:$A,G$7,Actuals!$C:$C,$C51) -> 0 | H51: =SUMIFS(Actuals!$I:$I,Actuals!$A:$A,H$7,Actuals!$C:$C,$C51) -> 0 | I51: =SUMIFS(Actuals!$I:$I,Actuals!$A:$A,I$7,Actuals!$C:$C,$C51) -> 0 | J51: =SUMIFS(Actuals!$I:$I,Actuals!$A:$A,J$7,Actuals!$C:$C,$C51) -> 0 | K51: =SUMIFS(Actuals!$I:$I,Actuals!$A:$A,K$7,Actuals!$C:$C,$C51) -> 0
B52: Non Ops | C52: Tax Distributions | D52: Trailing 6 Week Average | E52: =SUMIFS(Actuals!$I:$I,Actuals!$A:$A,E$7,Actuals!$C:$C,$C52) -> -21230 | F52: =SUMIFS(Actuals!$I:$I,Actuals!$A:$A,F$7,Actuals!$C:$C,$C52) -> -24740 | G52: =SUMIFS(Actuals!$I:$I,Actuals!$A:$A,G$7,Actuals!$C:$C,$C52) -> -20220 | H52: =SUMIFS(Actuals!$I:$I,Actuals!$A:$A,H$7,Actuals!$C:$C,$C52) -> -14200 | I52: =SUMIFS(Actuals!$I:$I,Actuals!$A:$A,I$7,Actuals!$C:$C,$C52) -> -12680 | J52: =SUMIFS(Actuals!$I:$I,Actuals!$A:$A,J$7,Actuals!$C:$C,$C52) -> -12340 | K52: =SUMIFS(Actuals!$I:$I,Actuals!$A:$A,K$7,Actuals!$C:$C,$C52) -> -8560 | L52: =AVERAGE(F52:K52) -> -15456.667 | M52: =AVERAGE(G52:L52) -> -13909.444 | N52: =AVERAGE(H52:M52) -> -12857.685 | O52: =AVERAGE(I52:N52) -> -12633.966 | P52: =AVERAGE(J52:O52) -> -12626.294 | Q52: =AVERAGE(K52:P52) -> -12674.009 | R52: =AVERAGE(L52:Q52) -> -13359.678 | S52: =AVERAGE(M52:R52) -> -13010.179 | ... X52: =AVERAGE(R52:W52) -> -12988.889
B53: Non Ops | C53: Equity Distributions | D53: Enter Manually | E53: =SUMIFS(Actuals!$I:$I,Actuals!$A:$A,E$7,Actuals!$C:$C,$C53) -> 0 | F53: =SUMIFS(Actuals!$I:$I,Actuals!$A:$A,F$7,Actuals!$C:$C,$C53) -> 0 | G53: =SUMIFS(Actuals!$I:$I,Actuals!$A:$A,G$7,Actuals!$C:$C,$C53) -> 0 | H53: =SUMIFS(Actuals!$I:$I,Actuals!$A:$A,H$7,Actuals!$C:$C,$C53) -> 0 | I53: =SUMIFS(Actuals!$I:$I,Actuals!$A:$A,I$7,Actuals!$C:$C,$C53) -> 0 | J53: =SUMIFS(Actuals!$I:$I,Actuals!$A:$A,J$7,Actuals!$C:$C,$C53) -> 0 | K53: =SUMIFS(Actuals!$I:$I,Actuals!$A:$A,K$7,Actuals!$C:$C,$C53) -> 0
B54: Non Ops | C54: Equity Contributions | D54: Enter Manually | E54: =SUMIFS(Actuals!$I:$I,Actuals!$A:$A,E$7,Actuals!$C:$C,$C54) -> 0 | F54: =SUMIFS(Actuals!$I:$I,Actuals!$A:$A,F$7,Actuals!$C:$C,$C54) -> 0 | G54: =SUMIFS(Actuals!$I:$I,Actuals!$A:$A,G$7,Actuals!$C:$C,$C54) -> 0 | H54: =SUMIFS(Actuals!$I:$I,Actuals!$A:$A,H$7,Actuals!$C:$C,$C54) -> 0 | I54: =SUMIFS(Actuals!$I:$I,Actuals!$A:$A,I$7,Actuals!$C:$C,$C54) -> 0 | J54: =SUMIFS(Actuals!$I:$I,Actuals!$A:$A,J$7,Actuals!$C:$C,$C54) -> 0 | K54: =SUMIFS(Actuals!$I:$I,Actuals!$A:$A,K$7,Actuals!$C:$C,$C54) -> 0
B55: Non Ops | C55: Other Non-operating Outflows | D55: Trailing 6 Week Average | E55: =SUMIFS(Actuals!$I:$I,Actuals!$A:$A,E$7,Actuals!$C:$C,$C55) -> 0 | F55: =SUMIFS(Actuals!$I:$I,Actuals!$A:$A,F$7,Actuals!$C:$C,$C55) -> -8580 | G55: =SUMIFS(Actuals!$I:$I,Actuals!$A:$A,G$7,Actuals!$C:$C,$C55) -> 0 | H55: =SUMIFS(Actuals!$I:$I,Actuals!$A:$A,H$7,Actuals!$C:$C,$C55) -> -1140 | I55: =SUMIFS(Actuals!$I:$I,Actuals!$A:$A,I$7,Actuals!$C:$C,$C55) -> 0 | J55: =SUMIFS(Actuals!$I:$I,Actuals!$A:$A,J$7,Actuals!$C:$C,$C55) -> 0 | K55: =SUMIFS(Actuals!$I:$I,Actuals!$A:$A,K$7,Actuals!$C:$C,$C55) -> -3260 | L55: =AVERAGE(F55:K55) -> -2163.3333 | M55: =AVERAGE(G55:L55) -> -1093.8889 | N55: =AVERAGE(H55:M55) -> -1276.2037 | O55: =AVERAGE(I55:N55) -> -1298.9043 | P55: =AVERAGE(J55:O55) -> -1515.3884 | Q55: =AVERAGE(K55:P55) -> -1767.9531 | R55: =AVERAGE(L55:Q55) -> -1519.2786 | S55: =AVERAGE(M55:R55) -> -1411.9362 | ... X55: =AVERAGE(R55:W55) -> -1492.2525
C57: Total Non-operating Cash Outflows | E57: =SUM(E48:E56) -> -21230 | F57: =SUM(F48:F56) -> -33320 | G57: =SUM(G48:G56) -> -20220 | H57: =SUM(H48:H56) -> -15340 | I57: =SUM(I48:I56) -> -12680 | J57: =SUM(J48:J56) -> -12340 | K57: =SUM(K48:K56) -> -11820 | L57: =SUM(L48:L56) -> -17620 | ... X57: =SUM(X48:X56) -> -14481.142
C59: Change in Cash | E59: =SUM(E21,E45,E57) -> -135370 | F59: =SUM(F21,F45,F57) -> -36120 | G59: =SUM(G21,G45,G57) -> 65020 | H59: =SUM(H21,H45,H57) -> -195750 | I59: =SUM(I21,I45,I57) -> 281900 | J59: =SUM(J21,J45,J57) -> -110100 | K59: =SUM(K21,K45,K57) -> -106220 | L59: =SUM(L21,L45,L57) -> 51268.333 | ... X59: =SUM(X21,X45,X57) -> -59244.097

Sheet 13 weeks CF
E1: =SUMPRODUCT([result range]*([date range]=[date])*([category range]=[category]))
C2: Master Error Check Cell | D2: ='Error Checking'!$B$2 -> 0
C4: Actual / Forecast | E4: Actual | F4: Actual | G4: Actual | H4: Actual | I4: Actual | J4: Actual | K4: Forecast | L4: Forecast | M4: Forecast | N4: Forecast | O4: Forecast | P4: Forecast | Q4: Forecast | R4: Forecast | S4: Forecast | T4: Forecast | U4: Forecast | V4: Forecast | W4: Forecast
C5: Week Number | E5: 1 | F5: =E5+1 -> 2 | G5: =F5+1 -> 3 | H5: =G5+1 -> 4 | I5: =H5+1 -> 5 | J5: =I5+1 -> 6 | K5: =J5+1 -> 7 | L5: =K5+1 -> 8 | M5: =L5+1 -> 9 | ... W5: =V5+1 -> 19
C6: Week Beginning | E6: 45221 | F6: =E7+1 -> 45228 | G6: =F7+1 -> 45235 | H6: =G7+1 -> 45242 | I6: =H7+1 -> 45249 | J6: =I7+1 -> 45256 | K6: =J7+1 -> 45263 | L6: =K7+1 -> 45270 | M6: =L7+1 -> 45277 | ... W6: =V7+1 -> 45347
B7: Variance Tagging | C7: Week Ending | D7: Forecast Methodology | E7: =E6+6 -> 45227 | F7: =F6+6 -> 45234 | G7: =G6+6 -> 45241 | H7: =H6+6 -> 45248 | I7: =I6+6 -> 45255 | J7: =J6+6 -> 45262 | K7: =K6+6 -> 45269 | L7: =L6+6 -> 45276 | ... W7: =W6+6 -> 45353 | X7: Placeholder
C9: Cash Balance
C10: Beginning Cash | E10: 345580 | F10: =E12 -> 210210 | G10: =F12 -> 174090 | H10: =G12 -> 239110 | I10: =H12 -> 43360 | J10: =I12 -> 325260 | K10: =J12 -> 215160 | L10: =K12 -> 112041.67 | M10: =L12 -> 156995.28 | ... W10: =V12 -> 580273.04
C11: Change in Cash | E11: =E59 -> -135370 | F11: =F59 -> -36120 | G11: =G59 -> 65020 | H11: =H59 -> -195750 | I11: =I59 -> 281900 | J11: =J59 -> -110100 | K11: =K59 -> -103118.33 | L11: =L59 -> 44953.611 | ... W11: =W59 -> -289083.47
B12: Ending Cash | C12: Ending Cash | E12: =SUM(E10:E11) -> 210210 | F12: =SUM(F10:F11) -> 174090 | G12: =SUM(G10:G11) -> 239110 | H12: =SUM(H10:H11) -> 43360 | I12: =SUM(I10:I11) -> 325260 | J12: =SUM(J10:J11) -> 215160 | K12: =SUM(K10:K11) -> 112041.67 | L12: =SUM(L10:L11) -> 156995.28 | ... W12: =SUM(W10:W11) -> 291189.57
C13: Per Data | E13: 210210 | F13: 174090 | G13: 239110 | H13: 43360 | I13: 325260 | J13: 215160
C14: Double-Check | E14: =IF(E$4="Forecast",0,E13-E12) -> 0 | F14: =IF(F$4="Forecast",0,F13-F12) -> 0 | G14: =IF(G$4="Forecast",0,G13-G12) -> 0 | H14: =IF(H$4="Forecast",0,H13-H12) -> 0 | I14: =IF(I$4="Forecast",0,I13-I12) -> 0 | J14: =IF(J$4="Forecast",0,J13-J12) -> 0 | K14: =IF(K$4="Forecast",0,K13-K12) -> 0 | L14: =IF(L$4="Forecast",0,L13-L12) -> 0 | ... W14: =IF(W$4="Forecast",0,W13-W12) -> 0
C15: Last Week's Forecast
C17: Cash Inflows
B18: Invoiced AR + New Revenue | C18: Invoiced AR + New Revenue | D18: See AR Aging Schedule | E18: =SUMIFS(Actuals!$I:$I,Actuals!$A:$A,E$7,Actuals!$C:$C,$C18) -> 0 | F18: =SUMIFS(Actuals!$I:$I,Actuals!$A:$A,F$7,Actuals!$C:$C,$C18) -> 372100 | G18: =SUMIFS(Actuals!$I:$I,Actuals!$A:$A,G$7,Actuals!$C:$C,$C18) -> 210150 | H18: =SUMIFS(Actuals!$I:$I,Actuals!$A:$A,H$7,Actuals!$C:$C,$C18) -> 0 | I18: =SUMIFS(Actuals!$I:$I,Actuals!$A:$A,I$7,Actuals!$C:$C,$C18) -> 361430 | J18: =SUMIFS(Actuals!$I:$I,Actuals!$A:$A,J$7,Actuals!$C:$C,$C18) -> 68440 | K18: =SUMIFS('AR Aging 01'!$B:$B,'AR Aging 01'!$A:$A,K$7) -> 330000 | L18: =SUMIFS('AR Aging 01'!$B:$B,'AR Aging 01'!$A:$A,L$7) -> 120000 | M18: =SUMIFS('AR Aging 01'!$B:$B,'AR Aging 01'!$A:$A,M$7) -> 454000 | N18: =SUMIFS('AR Aging 01'!$B:$B,'AR Aging 01'!$A:$A,N$7) -> 80000 | O18: =SUMIFS('AR Aging 01'!$B:$B,'AR Aging 01'!$A:$A,O$7) -> 100000 | P18: =SUMIFS('AR Aging 01'!$B:$B,'AR Aging 01'!$A:$A,P$7) -> 0 | Q18: =SUMIFS('AR Aging 01'!$B:$B,'AR Aging 01'!$A:$A,Q$7) -> 271800 | R18: =SUMIFS('AR Aging 01'!$B:$B,'AR Aging 01'!$A:$A,R$7) -> 80000 | ... W18: =SUMIFS('AR Aging 01'!$B:$B,'AR Aging 01'!$A:$A,W$7) -> 0
B19: Invoiced AR + New Revenue | C19: Other Inflows | D19: Enter Manually | E19: =SUMIFS(Actuals!$I:$I,Actuals!$A:$A,E$7,Actuals!$C:$C,$C19) -> 0 | F19: =SUMIFS(Actuals!$I:$I,Actuals!$A:$A,F$7,Actuals!$C:$C,$C19) -> 0 | G19: =SUMIFS(Actuals!$I:$I,Actuals!$A:$A,G$7,Actuals!$C:$C,$C19) -> 0 | H19: =SUMIFS(Actuals!$I:$I,Actuals!$A:$A,H$7,Actuals!$C:$C,$C19) -> 0 | I19: =SUMIFS(Actuals!$I:$I,Actuals!$A:$A,I$7,Actuals!$C:$C,$C19) -> 0 | J19: =SUMIFS(Actuals!$I:$I,Actuals!$A:$A,J$7,Actuals!$C:$C,$C19) -> 0
C21: Total Cash Inflows | E21: =SUM(E18:E20) -> 0 | F21: =SUM(F18:F20) -> 372100 | G21: =SUM(G18:G20) -> 210150 | H21: =SUM(H18:H20) -> 0 | I21: =SUM(I18:I20) -> 361430 | J21: =SUM(J18:J20) -> 68440 | K21: =SUM(K18:K20) -> 330000 | L21: =SUM(L18:L20) -> 120000 | ... W21: =SUM(W18:W20) -> 0
C23: Operating Cash Outflows
B24: Accounts Payable | C24: Accounts Payable | D24: See AP Aging Schedule | E24: =SUMIFS(Actuals!$I:$I,Actuals!$A:$A,E$7,Actuals!$C:$C,$C24) -> -33620 | F24: =SUMIFS(Actuals!$I:$I,Actuals!$A:$A,F$7,Actuals!$C:$C,$C24) -> -83210 | G24: =SUMIFS(Actuals!$I:$I,Actuals!$A:$A,G$7,Actuals!$C:$C,$C24) -> -69810 | H24: =SUMIFS(Actuals!$I:$I,Actuals!$A:$A,H$7,Actuals!$C:$C,$C24) -> -40140 | I24: =SUMIFS(Actuals!$I:$I,Actuals!$A:$A,I$7,Actuals!$C:$C,$C24) -> -18680 | J24: =SUMIFS(Actuals!$I:$I,Actuals!$A:$A,J$7,Actuals!$C:$C,$C24) -> -88580 | K24: =-SUMIFS('AP Aging 01'!$B:$B,'AP Aging 01'!$A:$A,K$7,'AP Aging 01'!$D:$D,"<>Yes") -> -800 | L24: =-SUMIFS('AP Aging 01'!$B:$B,'AP Aging 01'!$A:$A,L$7,'AP Aging 01'!$D:$D,"<>Yes") -> -1800 | M24: =-SUMIFS('AP Aging 01'!$B:$B,'AP Aging 01'!$A:$A,M$7,'AP Aging 01'!$D:$D,"<>Yes") -> -145800 | N24: =-SUMIFS('AP Aging 01'!$B:$B,'AP Aging 01'!$A:$A,N$7,'AP Aging 01'!$D:$D,"<>Yes") -> 0 | O24: =-SUMIFS('AP Aging 01'!$B:$B,'AP Aging 01'!$A:$A,O$7,'AP Aging 01'!$D:$D,"<>Yes") -> 0 | P24: =-SUMIFS('AP Aging 01'!$B:$B,'AP Aging 01'!$A:$A,P$7,'AP Aging 01'!$D:$D,"<>Yes") -> 0 | Q24: =-SUMIFS('AP Aging 01'!$B:$B,'AP Aging 01'!$A:$A,Q$7,'AP Aging 01'!$D:$D,"<>Yes") -> 0 | R24: =-SUMIFS('AP Aging 01'!$B:$B,'AP Aging 01'!$A:$A,R$7,'AP Aging 01'!$D:$D,"<>Yes") -> 0 | ... W24: =-SUMIFS('AP Aging 01'!$B:$B,'AP Aging 01'!$A:$A,W$7,'AP Aging 01'!$D:$D,"<>Yes") -> 0
B25: Credit Cards | C25: Credit Cards | D25: See AP Aging Schedule | E25: =SUMIFS(Actuals!$I:$I,Actuals!$A:$A,E$7,Actuals!$C:$C,$C25) -> 0 | F25: =SUMIFS(Actuals!$I:$I,Actuals!$A:$A,F$7,Actuals!$C:$C,$C25) -> -194090 | G25: =SUMIFS(Actuals!$I:$I,Actuals!$A:$A,G$7,Actuals!$C:$C,$C25) -> 0 | H25: =SUMIFS(Actuals!$I:$I,Actuals!$A:$A,H$7,Actuals!$C:$C,$C25) -> -100000 | I25: =SUMIFS(Actuals!$I:$I,Actuals!$A:$A,I$7,Actuals!$C:$C,$C25) -> 0 | J25: =SUMIFS(Actuals!$I:$I,Actuals!$A:$A,J$7,Actuals!$C:$C,$C25) -> -32000 | K25: =-SUMIFS('AP Aging 01'!$B:$B,'AP Aging 01'!$A:$A,K$7,'AP Aging 01'!$D:$D,"Yes") -> -350000 | L25: =-SUMIFS('AP Aging 01'!$B:$B,'AP Aging 01'!$A:$A,L$7,'AP Aging 01'!$D:$D,"Yes") -> 0 | M25: =-SUMIFS('AP Aging 01'!$B:$B,'AP Aging 01'!$A:$A,M$7,'AP Aging 01'!$D:$D,"Yes") -> 0 | N25: =-SUMIFS('AP Aging 01'!$B:$B,'AP Aging 01'!$A:$A,N$7,'AP Aging 01'!$D:$D,"Yes") -> 0 | O25: =-SUMIFS('AP Aging 01'!$B:$B,'AP Aging 01'!$A:$A,O$7,'AP Aging 01'!$D:$D,"Yes") -> -55000 | P25: =-SUMIFS('AP Aging 01'!$B:$B,'AP Aging 01'!$A:$A,P$7,'AP Aging 01'!$D:$D,"Yes") -> 0 | Q25: =-SUMIFS('AP Aging 01'!$B:$B,'AP Aging 01'!$A:$A,Q$7,'AP Aging 01'!$D:$D,"Yes") -> 0 | R25: =-SUMIFS('AP Aging 01'!$B:$B,'AP Aging 01'!$A:$A,R$7,'AP Aging 01'!$D:$D,"Yes") -> 0 | ... W25: =-SUMIFS('AP Aging 01'!$B:$B,'AP Aging 01'!$A:$A,W$7,'AP Aging 01'!$D:$D,"Yes") -> -210000
B26: Other Ops | C26: Payroll | D26: Trailing 6 Week Average | E26: =SUMIFS(Actuals!$I:$I,Actuals!$A:$A,E$7,Actuals!$C:$C,$C26) -> -77830 | F26: =SUMIFS(Actuals!$I:$I,Actuals!$A:$A,F$7,Actuals!$C:$C,$C26) -> -78050 | G26: =SUMIFS(Actuals!$I:$I,Actuals!$A:$A,G$7,Actuals!$C:$C,$C26) -> -51670 | H26: =SUMIFS(Actuals!$I:$I,Actuals!$A:$A,H$7,Actuals!$C:$C,$C26) -> -39960 | I26: =SUMIFS(Actuals!$I:$I,Actuals!$A:$A,I$7,Actuals!$C:$C,$C26) -> -44380 | J26: =SUMIFS(Actuals!$I:$I,Actuals!$A:$A,J$7,Actuals!$C:$C,$C26) -> -35340 | K26: =AVERAGE(E26:J26) -> -54538.333 | L26: =AVERAGE(F26:K26) -> -50656.389 | M26: =AVERAGE(G26:L26) -> -46090.787 | N26: =AVERAGE(H26:M26) -> -45160.918 | O26: =AVERAGE(I26:N26) -> -46027.738 | P26: =AVERAGE(J26:O26) -> -46302.361 | Q26: =AVERAGE(K26:P26) -> -48129.421 | R26: =AVERAGE(L26:Q26) -> -47061.269 | ... W26: =AVERAGE(Q26:V26) -> -46966.597
B27: Other Ops | C27: Contractors | D27: Enter Manually | E27: =SUMIFS(Actuals!$I:$I,Actuals!$A:$A,E$7,Actuals!$C:$C,$C27) -> 0 | F27: =SUMIFS(Actuals!$I:$I,Actuals!$A:$A,F$7,Actuals!$C:$C,$C27) -> 0 | G27: =SUMIFS(Actuals!$I:$I,Actuals!$A:$A,G$7,Actuals!$C:$C,$C27) -> 0 | H27: =SUMIFS(Actuals!$I:$I,Actuals!$A:$A,H$7,Actuals!$C:$C,$C27) -> 0 | I27: =SUMIFS(Actuals!$I:$I,Actuals!$A:$A,I$7,Actuals!$C:$C,$C27) -> 0 | J27: =SUMIFS(Actuals!$I:$I,Actuals!$A:$A,J$7,Actuals!$C:$C,$C27) -> 0
B28: Other Ops | C28: Dues & Subscriptions | D28: Trailing 6 Week Average | E28: =SUMIFS(Actuals!$I:$I,Actuals!$A:$A,E$7,Actuals!$C:$C,$C28) -> -310 | F28: =SUMIFS(Actuals!$I:$I,Actuals!$A:$A,F$7,Actuals!$C:$C,$C28) -> -310 | G28: =SUMIFS(Actuals!$I:$I,Actuals!$A:$A,G$7,Actuals!$C:$C,$C28) -> -310 | H28: =SUMIFS(Actuals!$I:$I,Actuals!$A:$A,H$7,Actuals!$C:$C,$C28) -> -310 | I28: =SUMIFS(Actuals!$I:$I,Actuals!$A:$A,I$7,Actuals!$C:$C,$C28) -> -310 | J28: =SUMIFS(Actuals!$I:$I,Actuals!$A:$A,J$7,Actuals!$C:$C,$C28) -> -310 | K28: =AVERAGE(E28:J28) -> -310 | L28: =AVERAGE(F28:K28) -> -310 | M28: =AVERAGE(G28:L28) -> -310 | N28: =AVERAGE(H28:M28) -> -310 | O28: =AVERAGE(I28:N28) -> -310 | P28: =AVERAGE(J28:O28) -> -310 | Q28: =AVERAGE(K28:P28) -> -310 | R28: =AVERAGE(L28:Q28) -> -310 | ... W28: =AVERAGE(Q28:V28) -> -310
B29: Other Ops | C29: Insurance | D29: Enter Manually | E29: =SUMIFS(Actuals!$I:$I,Actuals!$A:$A,E$7,Actuals!$C:$C,$C29) -> 0 | F29: =SUMIFS(Actuals!$I:$I,Actuals!$A:$A,F$7,Actuals!$C:$C,$C29) -> 0 | G29: =SUMIFS(Actuals!$I:$I,Actuals!$A:$A,G$7,Actuals!$C:$C,$C29) -> 0 | H29: =SUMIFS(Actuals!$I:$I,Actuals!$A:$A,H$7,Actuals!$C:$C,$C29) -> 0 | I29: =SUMIFS(Actuals!$I:$I,Actuals!$A:$A,I$7,Actuals!$C:$C,$C29) -> 0 | J29: =SUMIFS(Actuals!$I:$I,Actuals!$A:$A,J$7,Actuals!$C:$C,$C29) -> 0
B30: Other Ops | C30: Lease Payments | D30: Trailing 6 Week Average | E30: =SUMIFS(Actuals!$I:$I,Actuals!$A:$A,E$7,Actuals!$C:$C,$C30) -> 0 | F30: =SUMIFS(Actuals!$I:$I,Actuals!$A:$A,F$7,Actuals!$C:$C,$C30) -> -1350 | G30: =SUMIFS(Actuals!$I:$I,Actuals!$A:$A,G$7,Actuals!$C:$C,$C30) -> 0 | H30: =SUMIFS(Actuals!$I:$I,Actuals!$A:$A,H$7,Actuals!$C:$C,$C30) -> 0 | I30: =SUMIFS(Actuals!$I:$I,Actuals!$A:$A,I$7,Actuals!$C:$C,$C30) -> -1350 | J30: =SUMIFS(Actuals!$I:$I,Actuals!$A:$A,J$7,Actuals!$C:$C,$C30) -> -1350 | K30: =AVERAGE(E30:J30) -> -675 | L30: =AVERAGE(F30:K30) -> -787.5 | M30: =AVERAGE(G30:L30) -> -693.75 | N30: =AVERAGE(H30:M30) -> -809.375 | O30: =AVERAGE(I30:N30) -> -944.27083 | P30: =AVERAGE(J30:O30) -> -876.64931 | Q30: =AVERAGE(K30:P30) -> -797.75752 | R30: =AVERAGE(L30:Q30) -> -818.21711 | ... W30: =AVERAGE(Q30:V30) -> -828.39988
B31: Other Ops | C31: Marketing | D31: Trailing 6 Week Average | E31: =SUMIFS(Actuals!$I:$I,Actuals!$A:$A,E$7,Actuals!$C:$C,$C31) -> 0 | F31: =SUMIFS(Actuals!$I:$I,Actuals!$A:$A,F$7,Actuals!$C:$C,$C31) -> -1510 | G31: =SUMIFS(Actuals!$I:$I,Actuals!$A:$A,G$7,Actuals!$C:$C,$C31) -> -1020 | H31: =SUMIFS(Actuals!$I:$I,Actuals!$A:$A,H$7,Actuals!$C:$C,$C31) -> 0 | I31: =SUMIFS(Actuals!$I:$I,Actuals!$A:$A,I$7,Actuals!$C:$C,$C31) -> 0 | J31: =SUMIFS(Actuals!$I:$I,Actuals!$A:$A,J$7,Actuals!$C:$C,$C31) -> -1510 | K31: =AVERAGE(E31:J31) -> -673.33333 | L31: =AVERAGE(F31:K31) -> -785.55556 | M31: =AVERAGE(G31:L31) -> -664.81481 | N31: =AVERAGE(H31:M31) -> -605.61728 | O31: =AVERAGE(I31:N31) -> -706.5535 | P31: =AVERAGE(J31:O31) -> -824.31241 | Q31: =AVERAGE(K31:P31) -> -710.03115 | R31: =AVERAGE(L31:Q31) -> -716.14745 | ... W31: =AVERAGE(Q31:V31) -> -717.21397
B32: Other Ops | C32: Phone & Internet | D32: Enter Manually | E32: =SUMIFS(Actuals!$I:$I,Actuals!$A:$A,E$7,Actuals!$C:$C,$C32) -> 0 | F32: =SUMIFS(Actuals!$I:$I,Actuals!$A:$A,F$7,Actuals!$C:$C,$C32) -> 0 | G32: =SUMIFS(Actuals!$I:$I,Actuals!$A:$A,G$7,Actuals!$C:$C,$C32) -> 0 | H32: =SUMIFS(Actuals!$I:$I,Actuals!$A:$A,H$7,Actuals!$C:$C,$C32) -> 0 | I32: =SUMIFS(Actuals!$I:$I,Actuals!$A:$A,I$7,Actuals!$C:$C,$C32) -> 0 | J32: =SUMIFS(Actuals!$I:$I,Actuals!$A:$A,J$7,Actuals!$C:$C,$C32) -> 0
B33: Other Ops | C33: Professional Fees | D33: $5k each Month | E33: =SUMIFS(Actuals!$I:$I,Actuals!$A:$A,E$7,Actuals!$C:$C,$C33) -> 0 | F33: =SUMIFS(Actuals!$I:$I,Actuals!$A:$A,F$7,Actuals!$C:$C,$C33) -> -5000 | G33: =SUMIFS(Actuals!$I:$I,Actuals!$A:$A,G$7,Actuals!$C:$C,$C33) -> 0 | H33: =SUMIFS(Actuals!$I:$I,Actuals!$A:$A,H$7,Actuals!$C:$C,$C33) -> 0 | I33: =SUMIFS(Actuals!$I:$I,Actuals!$A:$A,I$7,Actuals!$C:$C,$C33) -> 0 | J33: =SUMIFS(Actuals!$I:$I,Actuals!$A:$A,J$7,Actuals!$C:$C,$C33) -> 0 | K33: -5000 | O33: -5000 | S33: -5000 | W33: -5000
B34: Other Ops | C34: Rent | D34: Enter Manually | E34: =SUMIFS(Actuals!$I:$I,Actuals!$A:$A,E$7,Actuals!$C:$C,$C34) -> 0 | F34: =SUMIFS(Actuals!$I:$I,Actuals!$A:$A,F$7,Actuals!$C:$C,$C34) -> 0 | G34: =SUMIFS(Actuals!$I:$I,Actuals!$A:$A,G$7,Actuals!$C:$C,$C34) -> 0 | H34: =SUMIFS(Actuals!$I:$I,Actuals!$A:$A,H$7,Actuals!$C:$C,$C34) -> 0 | I34: =SUMIFS(Actuals!$I:$I,Actuals!$A:$A,I$7,Actuals!$C:$C,$C34) -> 0 | J34: =SUMIFS(Actuals!$I:$I,Actuals!$A:$A,J$7,Actuals!$C:$C,$C34) -> 0
B35: Other Ops | C35: Repairs & Maintenance | D35: Enter Manually | E35: =SUMIFS(Actuals!$I:$I,Actuals!$A:$A,E$7,Actuals!$C:$C,$C35) -> 0 | F35: =SUMIFS(Actuals!$I:$I,Actuals!$A:$A,F$7,Actuals!$C:$C,$C35) -> 0 | G35: =SUMIFS(Actuals!$I:$I,Actuals!$A:$A,G$7,Actuals!$C:$C,$C35) -> 0 | H35: =SUMIFS(Actuals!$I:$I,Actuals!$A:$A,H$7,Actuals!$C:$C,$C35) -> 0 | I35: =SUMIFS(Actuals!$I:$I,Actuals!$A:$A,I$7,Actuals!$C:$C,$C35) -> 0 | J35: =SUMIFS(Actuals!$I:$I,Actuals!$A:$A,J$7,Actuals!$C:$C,$C35) -> 0
B36: Other Ops | C36: Supplies | D36: Enter Manually | E36: =SUMIFS(Actuals!$I:$I,Actuals!$A:$A,E$7,Actuals!$C:$C,$C36) -> 0 | F36: =SUMIFS(Actuals!$I:$I,Actuals!$A:$A,F$7,Actuals!$C:$C,$C36) -> 0 | G36: =SUMIFS(Actuals!$I:$I,Actuals!$A:$A,G$7,Actuals!$C:$C,$C36) -> 0 | H36: =SUMIFS(Actuals!$I:$I,Actuals!$A:$A,H$7,Actuals!$C:$C,$C36) -> 0 | I36: =SUMIFS(Actuals!$I:$I,Actuals!$A:$A,I$7,Actuals!$C:$C,$C36) -> 0 | J36: =SUMIFS(Actuals!$I:$I,Actuals!$A:$A,J$7,Actuals!$C:$C,$C36) -> 0
B37: Other Ops | C37: Licenses | D37: Enter Manually | E37: =SUMIFS(Actuals!$I:$I,Actuals!$A:$A,E$7,Actuals!$C:$C,$C37) -> 0 | F37: =SUMIFS(Actuals!$I:$I,Actuals!$A:$A,F$7,Actuals!$C:$C,$C37) -> 0 | G37: =SUMIFS(Actuals!$I:$I,Actuals!$A:$A,G$7,Actuals!$C:$C,$C37) -> 0 | H37: =SUMIFS(Actuals!$I:$I,Actuals!$A:$A,H$7,Actuals!$C:$C,$C37) -> 0 | I37: =SUMIFS(Actuals!$I:$I,Actuals!$A:$A,I$7,Actuals!$C:$C,$C37) -> 0 | J37: =SUMIFS(Actuals!$I:$I,Actuals!$A:$A,J$7,Actuals!$C:$C,$C37) -> 0
B38: Other Ops | C38: Technology | D38: Trailing 6 Week Average | E38: =SUMIFS(Actuals!$I:$I,Actuals!$A:$A,E$7,Actuals!$C:$C,$C38) -> -1110 | F38: =SUMIFS(Actuals!$I:$I,Actuals!$A:$A,F$7,Actuals!$C:$C,$C38) -> -1150 | G38: =SUMIFS(Actuals!$I:$I,Actuals!$A:$A,G$7,Actuals!$C:$C,$C38) -> -2100 | H38: =SUMIFS(Actuals!$I:$I,Actuals!$A:$A,H$7,Actuals!$C:$C,$C38) -> 0 | I38: =SUMIFS(Actuals!$I:$I,Actuals!$A:$A,I$7,Actuals!$C:$C,$C38) -> -2130 | J38: =SUMIFS(Actuals!$I:$I,Actuals!$A:$A,J$7,Actuals!$C:$C,$C38) -> 0 | K38: =AVERAGE(E38:J38) -> -1081.6667 | L38: =AVERAGE(F38:K38) -> -1076.9444 | M38: =AVERAGE(G38:L38) -> -1064.7685 | N38: =AVERAGE(H38:M38) -> -892.22994 | O38: =AVERAGE(I38:N38) -> -1040.9349 | P38: =AVERAGE(J38:O38) -> -859.42408 | Q38: =AVERAGE(K38:P38) -> -1002.6614 | R38: =AVERAGE(L38:Q38) -> -989.49389 | ... W38: =AVERAGE(Q38:V38) -> -976.3099
B39: Other Ops | C39: Training | D39: Enter Manually | E39: =SUMIFS(Actuals!$I:$I,Actuals!$A:$A,E$7,Actuals!$C:$C,$C39) -> 0 | F39: =SUMIFS(Actuals!$I:$I,Actuals!$A:$A,F$7,Actuals!$C:$C,$C39) -> 0 | G39: =SUMIFS(Actuals!$I:$I,Actuals!$A:$A,G$7,Actuals!$C:$C,$C39) -> 0 | H39: =SUMIFS(Actuals!$I:$I,Actuals!$A:$A,H$7,Actuals!$C:$C,$C39) -> 0 | I39: =SUMIFS(Actuals!$I:$I,Actuals!$A:$A,I$7,Actuals!$C:$C,$C39) -> 0 | J39: =SUMIFS(Actuals!$I:$I,Actuals!$A:$A,J$7,Actuals!$C:$C,$C39) -> 0
B40: Other Ops | C40: Travel & Entertainment | D40: Enter Manually | E40: =SUMIFS(Actuals!$I:$I,Actuals!$A:$A,E$7,Actuals!$C:$C,$C40) -> 0 | F40: =SUMIFS(Actuals!$I:$I,Actuals!$A:$A,F$7,Actuals!$C:$C,$C40) -> 0 | G40: =SUMIFS(Actuals!$I:$I,Actuals!$A:$A,G$7,Actuals!$C:$C,$C40) -> 0 | H40: =SUMIFS(Actuals!$I:$I,Actuals!$A:$A,H$7,Actuals!$C:$C,$C40) -> 0 | I40: =SUMIFS(Actuals!$I:$I,Actuals!$A:$A,I$7,Actuals!$C:$C,$C40) -> 0 | J40: =SUMIFS(Actuals!$I:$I,Actuals!$A:$A,J$7,Actuals!$C:$C,$C40) -> 0
B41: Other Ops | C41: Utilities | D41: Enter Manually | E41: =SUMIFS(Actuals!$I:$I,Actuals!$A:$A,E$7,Actuals!$C:$C,$C41) -> 0 | F41: =SUMIFS(Actuals!$I:$I,Actuals!$A:$A,F$7,Actuals!$C:$C,$C41) -> 0 | G41: =SUMIFS(Actuals!$I:$I,Actuals!$A:$A,G$7,Actuals!$C:$C,$C41) -> 0 | H41: =SUMIFS(Actuals!$I:$I,Actuals!$A:$A,H$7,Actuals!$C:$C,$C41) -> 0 | I41: =SUMIFS(Actuals!$I:$I,Actuals!$A:$A,I$7,Actuals!$C:$C,$C41) -> 0 | J41: =SUMIFS(Actuals!$I:$I,Actuals!$A:$A,J$7,Actuals!$C:$C,$C41) -> 0
B42: Other Ops | C42: Vehicles | D42: $7k each Month | E42: =SUMIFS(Actuals!$I:$I,Actuals!$A:$A,E$7,Actuals!$C:$C,$C42) -> 0 | F42: =SUMIFS(Actuals!$I:$I,Actuals!$A:$A,F$7,Actuals!$C:$C,$C42) -> -7660 | G42: =SUMIFS(Actuals!$I:$I,Actuals!$A:$A,G$7,Actuals!$C:$C,$C42) -> 0 | H42: =SUMIFS(Actuals!$I:$I,Actuals!$A:$A,H$7,Actuals!$C:$C,$C42) -> 0 | I42: =SUMIFS(Actuals!$I:$I,Actuals!$A:$A,I$7,Actuals!$C:$C,$C42) -> 0 | J42: =SUMIFS(Actuals!$I:$I,Actuals!$A:$A,J$7,Actuals!$C:$C,$C42) -> -5840 | O42: -7000 | S42: -7000 | W42: -7000
B43: Other Ops | C43: Other Operating Outflows | D43: Trailing 6 Week Average | E43: =SUMIFS(Actuals!$I:$I,Actuals!$A:$A,E$7,Actuals!$C:$C,$C43) -> -1270 | F43: =SUMIFS(Actuals!$I:$I,Actuals!$A:$A,F$7,Actuals!$C:$C,$C43) -> -2570 | G43: =SUMIFS(Actuals!$I:$I,Actuals!$A:$A,G$7,Actuals!$C:$C,$C43) -> 0 | H43: =SUMIFS(Actuals!$I:$I,Actuals!$A:$A,H$7,Actuals!$C:$C,$C43) -> 0 | I43: =SUMIFS(Actuals!$I:$I,Actuals!$A:$A,I$7,Actuals!$C:$C,$C43) -> 0 | J43: =SUMIFS(Actuals!$I:$I,Actuals!$A:$A,J$7,Actuals!$C:$C,$C43) -> -1270 | K43: =AVERAGE(E43:J43) -> -851.66667 | L43: =AVERAGE(F43:K43) -> -781.94444 | M43: =AVERAGE(G43:L43) -> -483.93519 | N43: =AVERAGE(H43:M43) -> -564.59105 | O43: =AVERAGE(I43:N43) -> -658.68956 | P43: =AVERAGE(J43:O43) -> -768.47115 | Q43: =AVERAGE(K43:P43) -> -684.88301 | R43: =AVERAGE(L43:Q43) -> -657.08573 | ... W43: =AVERAGE(Q43:V43) -> -666.46564
C45: Total Operating Cash Outflows | E45: =SUM(E24:E44) -> -114140 | F45: =SUM(F24:F44) -> -374900 | G45: =SUM(G24:G44) -> -124910 | H45: =SUM(H24:H44) -> -180410 | I45: =SUM(I24:I44) -> -66850 | J45: =SUM(J24:J44) -> -166200 | K45: =SUM(K24:K44) -> -413930 | L45: =SUM(L24:L44) -> -56198.333 | ... W45: =SUM(W24:W44) -> -272464.99
C47: Non-operating Cash Outflows
B48: Non Ops | C48: Capital Expenditures | D48: Enter Manually | E48: =SUMIFS(Actuals!$I:$I,Actuals!$A:$A,E$7,Actuals!$C:$C,$C48) -> 0 | F48: =SUMIFS(Actuals!$I:$I,Actuals!$A:$A,F$7,Actuals!$C:$C,$C48) -> 0 | G48: =SUMIFS(Actuals!$I:$I,Actuals!$A:$A,G$7,Actuals!$C:$C,$C48) -> 0 | H48: =SUMIFS(Actuals!$I:$I,Actuals!$A:$A,H$7,Actuals!$C:$C,$C48) -> 0 | I48: =SUMIFS(Actuals!$I:$I,Actuals!$A:$A,I$7,Actuals!$C:$C,$C48) -> 0 | J48: =SUMIFS(Actuals!$I:$I,Actuals!$A:$A,J$7,Actuals!$C:$C,$C48) -> 0
B49: Non Ops | C49: Debt Proceeds | D49: Enter Manually | E49: =SUMIFS(Actuals!$I:$I,Actuals!$A:$A,E$7,Actuals!$C:$C,$C49) -> 0 | F49: =SUMIFS(Actuals!$I:$I,Actuals!$A:$A,F$7,Actuals!$C:$C,$C49) -> 0 | G49: =SUMIFS(Actuals!$I:$I,Actuals!$A:$A,G$7,Actuals!$C:$C,$C49) -> 0 | H49: =SUMIFS(Actuals!$I:$I,Actuals!$A:$A,H$7,Actuals!$C:$C,$C49) -> 0 | I49: =SUMIFS(Actuals!$I:$I,Actuals!$A:$A,I$7,Actuals!$C:$C,$C49) -> 0 | J49: =SUMIFS(Actuals!$I:$I,Actuals!$A:$A,J$7,Actuals!$C:$C,$C49) -> 0
B50: Non Ops | C50: Interest Payments | D50: Enter Manually | E50: =SUMIFS(Actuals!$I:$I,Actuals!$A:$A,E$7,Actuals!$C:$C,$C50) -> 0 | F50: =SUMIFS(Actuals!$I:$I,Actuals!$A:$A,F$7,Actuals!$C:$C,$C50) -> 0 | G50: =SUMIFS(Actuals!$I:$I,Actuals!$A:$A,G$7,Actuals!$C:$C,$C50) -> 0 | H50: =SUMIFS(Actuals!$I:$I,Actuals!$A:$A,H$7,Actuals!$C:$C,$C50) -> 0 | I50: =SUMIFS(Actuals!$I:$I,Actuals!$A:$A,I$7,Actuals!$C:$C,$C50) -> 0 | J50: =SUMIFS(Actuals!$I:$I,Actuals!$A:$A,J$7,Actuals!$C:$C,$C50) -> 0
B51: Non Ops | C51: Principal Payments | D51: Enter Manually | E51: =SUMIFS(Actuals!$I:$I,Actuals!$A:$A,E$7,Actuals!$C:$C,$C51) -> 0 | F51: =SUMIFS(Actuals!$I:$I,Actuals!$A:$A,F$7,Actuals!$C:$C,$C51) -> 0 | G51: =SUMIFS(Actuals!$I:$I,Actuals!$A:$A,G$7,Actuals!$C:$C,$C51) -> 0 | H51: =SUMIFS(Actuals!$I:$I,Actuals!$A:$A,H$7,Actuals!$C:$C,$C51) -> 0 | I51: =SUMIFS(Actuals!$I:$I,Actuals!$A:$A,I$7,Actuals!$C:$C,$C51) -> 0 | J51: =SUMIFS(Actuals!$I:$I,Actuals!$A:$A,J$7,Actuals!$C:$C,$C51) -> 0
B52: Non Ops | C52: Tax Distributions | D52: Trailing 6 Week Average | E52: =SUMIFS(Actuals!$I:$I,Actuals!$A:$A,E$7,Actuals!$C:$C,$C52) -> -21230 | F52: =SUMIFS(Actuals!$I:$I,Actuals!$A:$A,F$7,Actuals!$C:$C,$C52) -> -24740 | G52: =SUMIFS(Actuals!$I:$I,Actuals!$A:$A,G$7,Actuals!$C:$C,$C52) -> -20220 | H52: =SUMIFS(Actuals!$I:$I,Actuals!$A:$A,H$7,Actuals!$C:$C,$C52) -> -14200 | I52: =SUMIFS(Actuals!$I:$I,Actuals!$A:$A,I$7,Actuals!$C:$C,$C52) -> -12680 | J52: =SUMIFS(Actuals!$I:$I,Actuals!$A:$A,J$7,Actuals!$C:$C,$C52) -> -12340 | K52: =AVERAGE(E52:J52) -> -17568.333 | L52: =AVERAGE(F52:K52) -> -16958.056 | M52: =AVERAGE(G52:L52) -> -15661.065 | N52: =AVERAGE(H52:M52) -> -14901.242 | O52: =AVERAGE(I52:N52) -> -15018.116 | P52: =AVERAGE(J52:O52) -> -15407.802 | Q52: =AVERAGE(K52:P52) -> -15919.102 | R52: =AVERAGE(L52:Q52) -> -15644.23 | ... W52: =AVERAGE(Q52:V52) -> -15563.802
B53: Non Ops | C53: Equity Distributions | D53: Enter Manually | E53: =SUMIFS(Actuals!$I:$I,Actuals!$A:$A,E$7,Actuals!$C:$C,$C53) -> 0 | F53: =SUMIFS(Actuals!$I:$I,Actuals!$A:$A,F$7,Actuals!$C:$C,$C53) -> 0 | G53: =SUMIFS(Actuals!$I:$I,Actuals!$A:$A,G$7,Actuals!$C:$C,$C53) -> 0 | H53: =SUMIFS(Actuals!$I:$I,Actuals!$A:$A,H$7,Actuals!$C:$C,$C53) -> 0 | I53: =SUMIFS(Actuals!$I:$I,Actuals!$A:$A,I$7,Actuals!$C:$C,$C53) -> 0 | J53: =SUMIFS(Actuals!$I:$I,Actuals!$A:$A,J$7,Actuals!$C:$C,$C53) -> 0
B54: Non Ops | C54: Equity Contributions | D54: Enter Manually | E54: =SUMIFS(Actuals!$I:$I,Actuals!$A:$A,E$7,Actuals!$C:$C,$C54) -> 0 | F54: =SUMIFS(Actuals!$I:$I,Actuals!$A:$A,F$7,Actuals!$C:$C,$C54) -> 0 | G54: =SUMIFS(Actuals!$I:$I,Actuals!$A:$A,G$7,Actuals!$C:$C,$C54) -> 0 | H54: =SUMIFS(Actuals!$I:$I,Actuals!$A:$A,H$7,Actuals!$C:$C,$C54) -> 0 | I54: =SUMIFS(Actuals!$I:$I,Actuals!$A:$A,I$7,Actuals!$C:$C,$C54) -> 0 | J54: =SUMIFS(Actuals!$I:$I,Actuals!$A:$A,J$7,Actuals!$C:$C,$C54) -> 0
B55: Non Ops | C55: Other Non-operating Outflows | D55: Trailing 6 Week Average | E55: =SUMIFS(Actuals!$I:$I,Actuals!$A:$A,E$7,Actuals!$C:$C,$C55) -> 0 | F55: =SUMIFS(Actuals!$I:$I,Actuals!$A:$A,F$7,Actuals!$C:$C,$C55) -> -8580 | G55: =SUMIFS(Actuals!$I:$I,Actuals!$A:$A,G$7,Actuals!$C:$C,$C55) -> 0 | H55: =SUMIFS(Actuals!$I:$I,Actuals!$A:$A,H$7,Actuals!$C:$C,$C55) -> -1140 | I55: =SUMIFS(Actuals!$I:$I,Actuals!$A:$A,I$7,Actuals!$C:$C,$C55) -> 0 | J55: =SUMIFS(Actuals!$I:$I,Actuals!$A:$A,J$7,Actuals!$C:$C,$C55) -> 0 | K55: =AVERAGE(E55:J55) -> -1620 | L55: =AVERAGE(F55:K55) -> -1890 | M55: =AVERAGE(G55:L55) -> -775 | N55: =AVERAGE(H55:M55) -> -904.16667 | O55: =AVERAGE(I55:N55) -> -864.86111 | P55: =AVERAGE(J55:O55) -> -1009.0046 | Q55: =AVERAGE(K55:P55) -> -1177.1721 | R55: =AVERAGE(L55:Q55) -> -1103.3674 | ... W55: =AVERAGE(Q55:V55) -> -1054.6767
C57: Total Non-operating Cash Outflows | E57: =SUM(E48:E56) -> -21230 | F57: =SUM(F48:F56) -> -33320 | G57: =SUM(G48:G56) -> -20220 | H57: =SUM(H48:H56) -> -15340 | I57: =SUM(I48:I56) -> -12680 | J57: =SUM(J48:J56) -> -12340 | K57: =SUM(K48:K56) -> -19188.333 | L57: =SUM(L48:L56) -> -18848.056 | ... W57: =SUM(W48:W56) -> -16618.479
C59: Change in Cash | E59: =SUM(E21,E45,E57) -> -135370 | F59: =SUM(F21,F45,F57) -> -36120 | G59: =SUM(G21,G45,G57) -> 65020 | H59: =SUM(H21,H45,H57) -> -195750 | I59: =SUM(I21,I45,I57) -> 281900 | J59: =SUM(J21,J45,J57) -> -110100 | K59: =SUM(K21,K45,K57) -> -103118.33 | L59: =SUM(L21,L45,L57) -> 44953.611 | ... W59: =SUM(W21,W45,W57) -> -289083.47

Sheet AR Aging 02
B1: ↓ Flows thru Model | D1: ↓ Raw Data from AR Aging Report
A2: Week Ending | B2: Amount | C2: Date | D2: Customer | E2: Current | F2: 1 - 30 | G2: 31 - 60 | H2: 61 - 90 | I2: > 90 | J2: TOTAL
A3: =C3+7-WEEKDAY(C3+7-7) -> 45283 | B3: 65900 | C3: 45280 | D3: AQUATECH | E3: 65900 | F3: 0 | G3: 0 | H3: 0 | I3: 0 | J3: =SUM(E3:I3) -> 65900
A4: =C4+7-WEEKDAY(C4+7-7) -> 45311 | B4: 75000 | C4: 45311 | D4: AQUATECH | E4: 0 | F4: 0 | G4: 0 | H4: 0 | I4: 0 | J4: =SUM(E4:I4) -> 0
A5: =C5+7-WEEKDAY(C5+7-7) -> 45346 | B5: 100000 | C5: 45342 | D5: AQUATECH | E5: 0 | F5: 0 | G5: 0 | H5: 0 | I5: 0 | J5: =SUM(E5:I5) -> 0
A6: =C6+7-WEEKDAY(C6+7-7) -> 45297 | B6: 98400 | C6: 45291 | D6: BLAZECORP | E6: 0 | F6: 13100 | G6: 25000 | H6: 16700 | I6: 0 | J6: =SUM(E6:I6) -> 54800
A7: =C7+7-WEEKDAY(C7+7-7) -> 0 | D7: CORELIX | E7: 0 | F7: 0 | G7: 0 | H7: 0 | I7: 7000 | J7: =SUM(E7:I7) -> 7000
A8: =C8+7-WEEKDAY(C8+7-7) -> 45297 | B8: 100000 | C8: 45291 | D8: DIAMONTECH | E8: 48900 | F8: 101900 | G8: 1400 | H8: 0 | I8: 0 | J8: =SUM(E8:I8) -> 152200
A9: =C9+7-WEEKDAY(C9+7-7) -> 45332 | B9: 48000 | C9: 45330 | D9: DIAMONTECH | E9: 0 | F9: 0 | G9: 0 | H9: 0 | I9: 0 | J9: =SUM(E9:I9) -> 0
A10: =C10+7-WEEKDAY(C10+7-7) -> 45290 | B10: 80000 | C10: 45285 | D10: ECHOIX | E10: 0 | F10: 83200 | G10: 68200 | H10: 18000 | I10: 21200 | J10: =SUM(E10:I10) -> 190600
A11: =C11+7-WEEKDAY(C11+7-7) -> 45318 | B11: 80000 | C11: 45316 | D11: ECHOIX | E11: 0 | F11: 0 | G11: 0 | H11: 0 | I11: 0 | J11: =SUM(E11:I11) -> 0
A12: =C12+7-WEEKDAY(C12+7-7) -> 45283 | B12: 150000 | C12: 45280 | D12: FLARETECH | E12: 150000 | F12: 0 | G12: 0 | H12: 0 | I12: 0 | J12: =SUM(E12:I12) -> 150000
A13: =C13+7-WEEKDAY(C13+7-7) -> 0 | D13: GRAVITONIX | E13: 0 | F13: 0 | G13: 0 | H13: 0 | I13: 500 | J13: =SUM(E13:I13) -> 500
A14: =C14+7-WEEKDAY(C14+7-7) -> 0 | D14: HELIXCORP | E14: 0 | F14: 0 | G14: 0 | H14: 0 | I14: 500 | J14: =SUM(E14:I14) -> 500
A15: =C15+7-WEEKDAY(C15+7-7) -> 0 | D15: ILLUMIX | E15: 0 | F15: 0 | G15: 0 | H15: 0 | I15: 7500 | J15: =SUM(E15:I15) -> 7500
A16: =C16+7-WEEKDAY(C16+7-7) -> 45283 | B16: 43800 | C16: 45280 | D16: JADETECH | E16: 0 | F16: 43800 | G16: 0 | H16: 0 | I16: 0 | J16: =SUM(E16:I16) -> 43800
A17: =C17+7-WEEKDAY(C17+7-7) -> 0 | D17: KRYSTALIX | E17: 0 | F17: 0 | G17: 0 | H17: 0 | I17: 900 | J17: =SUM(E17:I17) -> 900
A18: =C18+7-WEEKDAY(C18+7-7) -> 0 | D18: LUXORTECH | E18: 0 | F18: 0 | G18: 0 | H18: 15100 | I18: 0 | J18: =SUM(E18:I18) -> 15100
A19: =C19+7-WEEKDAY(C19+7-7) -> 0 | D19: MAGMACORP | E19: 0 | F19: 0 | G19: 0 | H19: 0 | I19: 1000 | J19: =SUM(E19:I19) -> 1000
A20: =C20+7-WEEKDAY(C20+7-7) -> 0 | D20: NEOTRONIX | E20: 0 | F20: 0 | G20: 0 | H20: 0 | I20: 700 | J20: =SUM(E20:I20) -> 700
A21: =C21+7-WEEKDAY(C21+7-7) -> 0 | D21: OMEGATECH | E21: 0 | F21: 0 | G21: 0 | H21: 0 | I21: 1000 | J21: =SUM(E21:I21) -> 1000
A22: =C22+7-WEEKDAY(C22+7-7) -> 45332 | B22: =250000*0 -> 0 | C22: 45330 | D22: PULSETECH | E22: 0 | F22: 0 | G22: 0 | H22: 0 | I22: 0 | J22: =SUM(E22:I22) -> 0
A23: =C23+7-WEEKDAY(C23+7-7) -> 0 | D23: QUARTZTECH | E23: 0 | F23: 0 | G23: 0 | H23: 0 | I23: 900 | J23: =SUM(E23:I23) -> 900
A24: =C24+7-WEEKDAY(C24+7-7) -> 0 | D24: REFLUXIX | E24: 0 | F24: 0 | G24: 0 | H24: 0 | I24: 500 | J24: =SUM(E24:I24) -> 500
A25: =C25+7-WEEKDAY(C25+7-7) -> 45276 | B25: 120000 | C25: 45275 | D25: SOLARIX | E25: 83900 | F25: 132800 | G25: 8400 | H25: 1500 | I25: 90500 | J25: =SUM(E25:I25) -> 317100
A26: =C26+7-WEEKDAY(C26+7-7) -> 45311 | B26: 80000 | C26: 45306 | D26: SOLARIX | E26: 0 | F26: 0 | G26: 0 | H26: 0 | I26: 0 | J26: =SUM(E26:I26) -> 0
A27: =C27+7-WEEKDAY(C27+7-7) -> 0 | D27: TURBOTRON | E27: 0 | F27: 0 | G27: 0 | H27: 0 | I27: 23200 | J27: =SUM(E27:I27) -> 23200
A28: =C28+7-WEEKDAY(C28+7-7) -> 0 | D28: UNITYCORP | E28: 0 | F28: 0 | G28: 0 | H28: 0 | I28: 14000 | J28: =SUM(E28:I28) -> 14000
A29: =C29+7-WEEKDAY(C29+7-7) -> 0 | D29: VIBECH | E29: 0 | F29: 0 | G29: 0 | H29: 0 | I29: 0 | J29: =SUM(E29:I29) -> 0
A30: =C30+7-WEEKDAY(C30+7-7) -> 45332 | B30: =150000*0 -> 0 | C30: 45330 | D30: WHIRLIX | E30: 0 | F30: 0 | G30: 0 | H30: 0 | I30: 150000 | J30: =SUM(E30:I30) -> 150000
A31: =C31+7-WEEKDAY(C31+7-7) -> 45283 | B31: 30700 | C31: 45280 | D31: XORTECH | E31: 30700 | F31: 0 | G31: 0 | H31: 0 | I31: 0 | J31: =SUM(E31:I31) -> 30700
A32: =C32+7-WEEKDAY(C32+7-7) -> 45283 | B32: 100000 | C32: 45280 | D32: YONIX | E32: 106700 | F32: 900 | G32: 1000 | H32: 2000 | I32: 2600 | J32: =SUM(E32:I32) -> 113200
A33: =C33+7-WEEKDAY(C33+7-7) -> 45283 | B33: 38500 | C33: 45280 | D33: ZIONTECH | E33: 27000 | F33: 0 | G33: 11500 | H33: 0 | I33: 0 | J33: =SUM(E33:I33) -> 38500
A34: =C34+7-WEEKDAY(C34+7-7) -> 0 | D34: ASCENTIX | E34: 0 | F34: 0 | G34: 0 | H34: 0 | I34: 29600 | J34: =SUM(E34:I34) -> 29600
A35: =C35+7-WEEKDAY(C35+7-7) -> 0 | D35: BRILLIATECH | E35: 0 | F35: 0 | G35: 0 | H35: 0 | I35: 0 | J35: =SUM(E35:I35) -> 0
A36: =C36+7-WEEKDAY(C36+7-7) -> 45311 | B36: 50000 | C36: 45311 | D36: CRYSTALTECH | E36: 0 | F36: 0 | G36: 0 | H36: 0 | I36: 0 | J36: =SUM(E36:I36) -> 0
A37: =C37+7-WEEKDAY(C37+7-7) -> 45346 | B37: 150000 | C37: 45342 | D37: CRYSTALTECH | E37: 0 | F37: 0 | G37: 0 | H37: 0 | I37: 0 | J37: =SUM(E37:I37) -> 0
A38: =C38+7-WEEKDAY(C38+7-7) -> 45311 | B38: 66800 | C38: 45306 | D38: THJADETECH | E38: 0 | F38: 300 | G38: 0 | H38: 2400 | I38: 64000 | J38: =SUM(E38:I38) -> 66700
A39: =C39+7-WEEKDAY(C39+7-7) -> 45346 | B39: 75000 | C39: 45342 | D39: ENERGIX | E39: 0 | F39: 0 | G39: 0 | H39: 0 | I39: 0 | J39: =SUM(E39:I39) -> 0
A40: =C40+7-WEEKDAY(C40+7-7) -> 0 | D40: FLUXATECH | E40: 0 | F40: 0 | G40: 0 | H40: 6500 | I40: 16100 | J40: =SUM(E40:I40) -> 22600
A41: =C41+7-WEEKDAY(C41+7-7) -> 0 | D41: GLOTECH | E41: 0 | F41: 0 | G41: 400 | H41: 3600 | I41: 27600 | J41: =SUM(E41:I41) -> 31600
A42: =C42+7-WEEKDAY(C42+7-7) -> 0 | D42: HALOCORP | E42: 0 | F42: 0 | G42: 0 | H42: 0 | I42: 70900 | J42: =SUM(E42:I42) -> 70900
A43: =C43+7-WEEKDAY(C43+7-7) -> 0 | D43: INTELIX | E43: 0 | F43: 700 | G43: 900 | H43: 2300 | I43: 6000 | J43: =SUM(E43:I43) -> 9900
A44: =C44+7-WEEKDAY(C44+7-7) -> 0 | D44: JUPITERIX | E44: 0 | F44: 0 | G44: 0 | H44: 0 | I44: 30400 | J44: =SUM(E44:I44) -> 30400
A45: =C45+7-WEEKDAY(C45+7-7) -> 0 | D45: KOSMIX | E45: 0 | F45: 0 | G45: 0 | H45: 0 | I45: 9600 | J45: =SUM(E45:I45) -> 9600
A46: =C46+7-WEEKDAY(C46+7-7) -> 45283 | B46: 125100 | C46: 45280 | D46: ZJADETECH | E46: 0 | F46: 113200 | G46: 0 | H46: 2700 | I46: 9100 | J46: =SUM(E46:I46) -> 125000

Sheet AR Aging 01
B1: ↓ Flows thru Model | D1: ↓ Raw Data from AR Aging Report
A2: Week Ending | B2: Amount | C2: Date | D2: Customer | E2: Current | F2: 1 - 30 | G2: 31 - 60 | H2: 61 - 90 | I2: > 90 | J2: TOTAL
A3: =C3+7-WEEKDAY(C3+7-7) -> 45283 | B3: 65900 | C3: 45280 | D3: AQUATECH | E3: 65900 | F3: 0 | G3: 0 | H3: 0 | I3: 0 | J3: =SUM(E3:I3) -> 65900
A4: =C4+7-WEEKDAY(C4+7-7) -> 45311 | B4: 75000 | C4: 45311 | D4: AQUATECH | E4: 0 | F4: 0 | G4: 0 | H4: 0 | I4: 0 | J4: =SUM(E4:I4) -> 0
A5: =C5+7-WEEKDAY(C5+7-7) -> 45346 | B5: 100000 | C5: 45342 | D5: AQUATECH | E5: 0 | F5: 0 | G5: 0 | H5: 0 | I5: 0 | J5: =SUM(E5:I5) -> 0
A6: =C6+7-WEEKDAY(C6+7-7) -> 45269 | B6: 225000 | C6: 45269 | D6: BLAZECORP | E6: 0 | F6: 240300 | G6: 25000 | H6: 16700 | I6: 0 | J6: =SUM(E6:I6) -> 282000
A7: =C7+7-WEEKDAY(C7+7-7) -> 0 | D7: CORELIX | E7: 0 | F7: 0 | G7: 0 | H7: 0 | I7: 7000 | J7: =SUM(E7:I7) -> 7000
A8: =C8+7-WEEKDAY(C8+7-7) -> 45297 | B8: 100000 | C8: 45291 | D8: DIAMONTECH | E8: 48900 | F8: 101900 | G8: 1400 | H8: 0 | I8: 0 | J8: =SUM(E8:I8) -> 152200
A9: =C9+7-WEEKDAY(C9+7-7) -> 45325 | B9: 48000 | C9: 45321 | D9: DIAMONTECH | E9: 0 | F9: 0 | G9: 0 | H9: 0 | I9: 0 | J9: =SUM(E9:I9) -> 0
A10: =C10+7-WEEKDAY(C10+7-7) -> 45290 | B10: 80000 | C10: 45285 | D10: ECHOIX | E10: 0 | F10: 83200 | G10: 68200 | H10: 18000 | I10: 21200 | J10: =SUM(E10:I10) -> 190600
A11: =C11+7-WEEKDAY(C11+7-7) -> 45318 | B11: 80000 | C11: 45316 | D11: ECHOIX | E11: 0 | F11: 0 | G11: 0 | H11: 0 | I11: 0 | J11: =SUM(E11:I11) -> 0
A12: =C12+7-WEEKDAY(C12+7-7) -> 45283 | B12: 150000 | C12: 45280 | D12: FLARETECH | E12: 150000 | F12: 0 | G12: 0 | H12: 0 | I12: 0 | J12: =SUM(E12:I12) -> 150000
A13: =C13+7-WEEKDAY(C13+7-7) -> 0 | D13: GRAVITONIX | E13: 0 | F13: 0 | G13: 0 | H13: 0 | I13: 500 | J13: =SUM(E13:I13) -> 500
A14: =C14+7-WEEKDAY(C14+7-7) -> 0 | D14: HELIXCORP | E14: 0 | F14: 0 | G14: 0 | H14: 0 | I14: 500 | J14: =SUM(E14:I14) -> 500
A15: =C15+7-WEEKDAY(C15+7-7) -> 0 | D15: ILLUMIX | E15: 0 | F15: 0 | G15: 0 | H15: 0 | I15: 7500 | J15: =SUM(E15:I15) -> 7500
A16: =C16+7-WEEKDAY(C16+7-7) -> 45283 | B16: 43800 | C16: 45280 | D16: JADETECH | E16: 0 | F16: 43800 | G16: 0 | H16: 12700 | I16: 0 | J16: =SUM(E16:I16) -> 56500
A17: =C17+7-WEEKDAY(C17+7-7) -> 0 | D17: KRYSTALIX | E17: 0 | F17: 0 | G17: 0 | H17: 0 | I17: 900 | J17: =SUM(E17:I17) -> 900
A18: =C18+7-WEEKDAY(C18+7-7) -> 0 | D18: LUXORTECH | E18: 0 | F18: 0 | G18: 0 | H18: 15100 | I18: 0 | J18: =SUM(E18:I18) -> 15100
A19: =C19+7-WEEKDAY(C19+7-7) -> 0 | D19: MAGMACORP | E19: 0 | F19: 0 | G19: 0 | H19: 0 | I19: 1000 | J19: =SUM(E19:I19) -> 1000
A20: =C20+7-WEEKDAY(C20+7-7) -> 0 | D20: NEOTRONIX | E20: 0 | F20: 0 | G20: 0 | H20: 0 | I20: 700 | J20: =SUM(E20:I20) -> 700
A21: =C21+7-WEEKDAY(C21+7-7) -> 0 | D21: OMEGATECH | E21: 0 | F21: 0 | G21: 0 | H21: 0 | I21: 1000 | J21: =SUM(E21:I21) -> 1000
A22: =C22+7-WEEKDAY(C22+7-7) -> 45339 | B22: 250000 | C22: 45337 | D22: PULSETECH | E22: 0 | F22: 0 | G22: 0 | H22: 0 | I22: 0 | J22: =SUM(E22:I22) -> 0
A23: =C23+7-WEEKDAY(C23+7-7) -> 0 | D23: QUARTZTECH | E23: 0 | F23: 0 | G23: 0 | H23: 0 | I23: 900 | J23: =SUM(E23:I23) -> 900
A24: =C24+7-WEEKDAY(C24+7-7) -> 0 | D24: REFLUXIX | E24: 0 | F24: 0 | G24: 0 | H24: 0 | I24: 500 | J24: =SUM(E24:I24) -> 500
A25: =C25+7-WEEKDAY(C25+7-7) -> 45276 | B25: 120000 | C25: 45275 | D25: SOLARIX | E25: 0 | F25: 132800 | G25: 8400 | H25: 1500 | I25: 90500 | J25: =SUM(E25:I25) -> 233200
A26: =C26+7-WEEKDAY(C26+7-7) -> 45311 | B26: 80000 | C26: 45306 | D26: SOLARIX | E26: 0 | F26: 0 | G26: 0 | H26: 0 | I26: 0 | J26: =SUM(E26:I26) -> 0
A27: =C27+7-WEEKDAY(C27+7-7) -> 0 | D27: TURBOTRON | E27: 0 | F27: 0 | G27: 0 | H27: 0 | I27: 23200 | J27: =SUM(E27:I27) -> 23200
A28: =C28+7-WEEKDAY(C28+7-7) -> 0 | D28: UNITYCORP | E28: 0 | F28: 0 | G28: 0 | H28: 0 | I28: 14000 | J28: =SUM(E28:I28) -> 14000
A29: =C29+7-WEEKDAY(C29+7-7) -> 0 | D29: VIBECH | E29: 0 | F29: 0 | G29: 0 | H29: 0 | I29: 0 | J29: =SUM(E29:I29) -> 0
A30: =C30+7-WEEKDAY(C30+7-7) -> 45325 | B30: 150000 | C30: 45321 | D30: WHIRLIX | E30: 0 | F30: 0 | G30: 0 | H30: 0 | I30: 150000 | J30: =SUM(E30:I30) -> 150000
A31: =C31+7-WEEKDAY(C31+7-7) -> 45283 | B31: 30700 | C31: 45280 | D31: XORTECH | E31: 30700 | F31: 0 | G31: 0 | H31: 0 | I31: 0 | J31: =SUM(E31:I31) -> 30700
A32: =C32+7-WEEKDAY(C32+7-7) -> 45269 | B32: 105000 | C32: 45264 | D32: YONIX | E32: 0 | F32: 900 | G32: 1000 | H32: 2000 | I32: 2600 | J32: =SUM(E32:I32) -> 6500
A33: =C33+7-WEEKDAY(C33+7-7) -> 45283 | B33: 38500 | C33: 45280 | D33: ZIONTECH | E33: 27000 | F33: 0 | G33: 11500 | H33: 0 | I33: 0 | J33: =SUM(E33:I33) -> 38500
A34: =C34+7-WEEKDAY(C34+7-7) -> 0 | D34: ASCENTIX | E34: 0 | F34: 0 | G34: 0 | H34: 0 | I34: 29600 | J34: =SUM(E34:I34) -> 29600
A35: =C35+7-WEEKDAY(C35+7-7) -> 0 | D35: BRILLIATECH | E35: 0 | F35: 0 | G35: 0 | H35: 0 | I35: 0 | J35: =SUM(E35:I35) -> 0
A36: =C36+7-WEEKDAY(C36+7-7) -> 45311 | B36: 50000 | C36: 45311 | D36: CRYSTALTECH | E36: 0 | F36: 0 | G36: 0 | H36: 0 | I36: 0 | J36: =SUM(E36:I36) -> 0
A37: =C37+7-WEEKDAY(C37+7-7) -> 45346 | B37: 150000 | C37: 45342 | D37: CRYSTALTECH | E37: 0 | F37: 0 | G37: 0 | H37: 0 | I37: 0 | J37: =SUM(E37:I37) -> 0
A38: =C38+7-WEEKDAY(C38+7-7) -> 45311 | B38: 66800 | C38: 45306 | D38: THJADETECH | E38: 0 | F38: 6500 | G38: 0 | H38: 2400 | I38: 64000 | J38: =SUM(E38:I38) -> 72900
A39: =C39+7-WEEKDAY(C39+7-7) -> 45346 | B39: 75000 | C39: 45342 | D39: ENERGIX | E39: 0 | F39: 0 | G39: 0 | H39: 0 | I39: 0 | J39: =SUM(E39:I39) -> 0
A40: =C40+7-WEEKDAY(C40+7-7) -> 0 | D40: FLUXATECH | E40: 0 | F40: 0 | G40: 0 | H40: 6500 | I40: 16100 | J40: =SUM(E40:I40) -> 22600
A41: =C41+7-WEEKDAY(C41+7-7) -> 0 | D41: GLOTECH | E41: 0 | F41: 0 | G41: 400 | H41: 3600 | I41: 27600 | J41: =SUM(E41:I41) -> 31600
A42: =C42+7-WEEKDAY(C42+7-7) -> 0 | D42: HALOCORP | E42: 0 | F42: 0 | G42: 0 | H42: 0 | I42: 70900 | J42: =SUM(E42:I42) -> 70900
A43: =C43+7-WEEKDAY(C43+7-7) -> 0 | D43: INTELIX | E43: 0 | F43: 700 | G43: 900 | H43: 2300 | I43: 6000 | J43: =SUM(E43:I43) -> 9900
A44: =C44+7-WEEKDAY(C44+7-7) -> 0 | D44: JUPITERIX | E44: 0 | F44: 0 | G44: 0 | H44: 15200 | I44: 15200 | J44: =SUM(E44:I44) -> 30400
A45: =C45+7-WEEKDAY(C45+7-7) -> 0 | D45: KOSMIX | E45: 0 | F45: 0 | G45: 0 | H45: 0 | I45: 9600 | J45: =SUM(E45:I45) -> 9600
A46: =C46+7-WEEKDAY(C46+7-7) -> 45283 | B46: 125100 | C46: 45280 | D46: ZJADETECH | E46: 0 | F46: 113200 | G46: 0 | H46: 2700 | I46: 9100 | J46: =SUM(E46:I46) -> 125000

Sheet AP Aging 02
B1: ↓ Flows thru Model | E1: ↓ Raw Data from AP Aging Report
A2: Week Ending | B2: Amount | C2: Date | D2: Credit Card? | E2: Vendor | F2: Current | G2: 1 - 30 | H2: 31 - 60 | I2: 61 - 90 | J2: > 90 | K2: TOTAL
A3: =C3+7-WEEKDAY(C3+7-7) -> 45325 | B3: 1300 | C3: 45323 | D3: Yes | E3: METRIX | F3: 1300 | G3: 0 | H3: 0 | I3: 0 | J3: 0 | K3: =SUM(F3:J3) -> 1300
A4: =C4+7-WEEKDAY(C4+7-7) -> 45297 | B4: 5000 | C4: 45292 | D4: Yes | E4: CAPITALONE | F4: 0 | G4: 0 | H4: 0 | I4: 0 | J4: 0 | K4: =SUM(F4:J4) -> 0
A5: =C5+7-WEEKDAY(C5+7-7) -> 45325 | B5: 5000 | C5: 45323 | D5: Yes | E5: CAPITALONE | F5: 0 | G5: 0 | H5: 0 | I5: 0 | J5: 0 | K5: =SUM(F5:J5) -> 0
A6: =C6+7-WEEKDAY(C6+7-7) -> 45353 | B6: 5000 | C6: 45352 | D6: Yes | E6: CAPITALONE | F6: 0 | G6: 0 | H6: 0 | I6: 0 | J6: 0 | K6: =SUM(F6:J6) -> 0
A7: =C7+7-WEEKDAY(C7+7-7) -> 45325 | B7: 1000 | C7: 45323 | D7: Yes | E7: ORACLETECH | F7: 0 | G7: 800 | H7: 100 | I7: 0 | J7: 0 | K7: =SUM(F7:J7) -> 900
A8: =C8+7-WEEKDAY(C8+7-7) -> 45283 | B8: 53200 | C8: 45280 | E8: PHOENIXCORP | F8: 0 | G8: 16200 | H8: 37000 | I8: 0 | J8: 0 | K8: =SUM(F8:J8) -> 53200
A9: =C9+7-WEEKDAY(C9+7-7) -> 45325 | B9: 3100 | C9: 45323 | D9: Yes | E9: QUANTUMIX | F9: 0 | G9: 3100 | H9: 0 | I9: 0 | J9: 0 | K9: =SUM(F9:J9) -> 3100
A10: =C10+7-WEEKDAY(C10+7-7) -> 45325 | B10: 11900 | C10: 45323 | D10: Yes | E10: RIFTTECH | F10: 0 | G10: 11900 | H10: 0 | I10: 0 | J10: 0 | K10: =SUM(F10:J10) -> 11900
A11: =C11+7-WEEKDAY(C11+7-7) -> 45325 | B11: 21500 | C11: 45323 | D11: Yes | E11: SILVERTECH | F11: 1200 | G11: 8200 | H11: 11600 | I11: 300 | J11: 200 | K11: =SUM(F11:J11) -> 21500
A12: =C12+7-WEEKDAY(C12+7-7) -> 45325 | B12: 1700 | C12: 45323 | D12: Yes | E12: TITANIX | F12: 1700 | G12: 0 | H12: 0 | I12: 0 | J12: 0 | K12: =SUM(F12:J12) -> 1700
A13: =C13+7-WEEKDAY(C13+7-7) -> 45325 | B13: 23100 | C13: 45323 | D13: Yes | E13: UNICORE | F13: 15300 | G13: 7000 | H13: 800 | I13: 0 | J13: 0 | K13: =SUM(F13:J13) -> 23100
A14: =C14+7-WEEKDAY(C14+7-7) -> 45283 | B14: 56200 | C14: 45280 | E14: VORTEXCORP | F14: 0 | G14: 56200 | H14: 0 | I14: 0 | J14: 0 | K14: =SUM(F14:J14) -> 56200
A15: =C15+7-WEEKDAY(C15+7-7) -> 45325 | B15: 2000 | C15: 45323 | D15: Yes | E15: WINDTECH | F15: 0 | G15: 2000 | H15: 0 | I15: 0 | J15: 0 | K15: =SUM(F15:J15) -> 2000
A16: =C16+7-WEEKDAY(C16+7-7) -> 45325 | B16: 1300 | C16: 45323 | D16: Yes | E16: GRAVITONIX | F16: 900 | G16: 400 | H16: 0 | I16: 0 | J16: 0 | K16: =SUM(F16:J16) -> 1300
A17: =C17+7-WEEKDAY(C17+7-7) -> 45283 | B17: 800 | C17: 45280 | E17: YONICORP | F17: 0 | G17: 800 | H17: 0 | I17: 0 | J17: 0 | K17: =SUM(F17:J17) -> 800
A18: =C18+7-WEEKDAY(C18+7-7) -> 45325 | B18: 6500 | C18: 45323 | D18: Yes | E18: ZYMOTECH | F18: 6500 | G18: 0 | H18: 0 | I18: 0 | J18: 0 | K18: =SUM(F18:J18) -> 6500
A19: =C19+7-WEEKDAY(C19+7-7) -> 45283 | B19: 30000 | C19: 45280 | E19: ASTRATECH | F19: 1400 | G19: 33400 | H19: 49200 | I19: 17000 | J19: 13300 | K19: =SUM(F19:J19) -> 114300
A20: =C20+7-WEEKDAY(C20+7-7) -> 45311 | B20: 50000 | C20: 45306 | E20: ASTRATECH | F20: 0 | G20: 0 | H20: 0 | I20: 0 | J20: 0 | K20: =SUM(F20:J20) -> 0
A21: =C21+7-WEEKDAY(C21+7-7) -> 45339 | B21: 150000 | C21: 45337 | E21: ASTRATECH | F21: 0 | G21: 0 | H21: 0 | I21: 0 | J21: 0 | K21: =SUM(F21:J21) -> 0
A22: =C22+7-WEEKDAY(C22+7-7) -> 45325 | B22: 3200 | C22: 45323 | D22: Yes | E22: BIOSIX | F22: 3200 | G22: 0 | H22: 0 | I22: 0 | J22: 0 | K22: =SUM(F22:J22) -> 3200
A23: =C23+7-WEEKDAY(C23+7-7) -> 45325 | B23: 122000 | C23: 45323 | D23: Yes | E23: CORETECH | F23: 102600 | G23: 115100 | H23: 96700 | I23: 83500 | J23: 39900 | K23: =SUM(F23:J23) -> 437800
A24: =C24+7-WEEKDAY(C24+7-7) -> 45353 | B24: 211000 | C24: 45352 | D24: Yes | E24: CORETECH | F24: 0 | G24: 0 | H24: 0 | I24: 0 | J24: 0 | K24: =SUM(F24:J24) -> 0
A25: =C25+7-WEEKDAY(C25+7-7) -> 45332 | B25: 300 | C25: 45327 | E25: DIODETECH | F25: 0 | G25: 0 | H25: 300 | I25: 0 | J25: 0 | K25: =SUM(F25:J25) -> 300
A26: =C26+7-WEEKDAY(C26+7-7) -> 45332 | B26: 700 | C26: 45327 | E26: ELEMENTIX | F26: 700 | G26: 0 | H26: 0 | I26: 0 | J26: 0 | K26: =SUM(F26:J26) -> 700
A27: =C27+7-WEEKDAY(C27+7-7) -> 45332 | B27: 6000 | C27: 45327 | E27: FROSTIX | F27: 0 | G27: 6000 | H27: 0 | I27: 0 | J27: 0 | K27: =SUM(F27:J27) -> 6000
A28: =C28+7-WEEKDAY(C28+7-7) -> 45297 | B28: 148000 | C28: 45296 | D28: Yes | E28: DISCOVER | F28: 0 | G28: 10000 | H28: 0 | I28: 0 | J28: 0 | K28: =SUM(F28:J28) -> 10000
A29: =C29+7-WEEKDAY(C29+7-7) -> 45332 | B29: 2500 | C29: 45327 | E29: HYDROTECH | F29: 0 | G29: 1700 | H29: 800 | I29: 0 | J29: 0 | K29: =SUM(F29:J29) -> 2500
A30: =C30+7-WEEKDAY(C30+7-7) -> 45332 | B30: 11700 | C30: 45327 | E30: IMPULSETECH | F30: 0 | G30: 11300 | H30: 400 | I30: 0 | J30: 0 | K30: =SUM(F30:J30) -> 11700
A31: =C31+7-WEEKDAY(C31+7-7) -> 45283 | B31: 300 | C31: 45280 | E31: JOLTIX | F31: 100 | G31: 200 | H31: 0 | I31: 0 | J31: 0 | K31: =SUM(F31:J31) -> 300
A32: =C32+7-WEEKDAY(C32+7-7) -> 45332 | B32: 9200 | C32: 45327 | E32: KONTACTIX | F32: 6600 | G32: 2600 | H32: 0 | I32: 0 | J32: 0 | K32: =SUM(F32:J32) -> 9200
A33: =C33+7-WEEKDAY(C33+7-7) -> 45332 | B33: 3500 | C33: 45327 | E33: LYNXTECH | F33: 0 | G33: 3400 | H33: 200 | I33: 0 | J33: 0 | K33: =SUM(F33:J33) -> 3600
A34: =C34+7-WEEKDAY(C34+7-7) -> 45332 | B34: 7500 | C34: 45327 | E34: MATRIXIX | F34: 0 | G34: 0 | H34: 7500 | I34: 0 | J34: 0 | K34: =SUM(F34:J34) -> 7500
A35: =C35+7-WEEKDAY(C35+7-7) -> 45283 | B35: 5800 | C35: 45280 | E35: NOMADIX | F35: 0 | G35: 5800 | H35: 0 | I35: 0 | J35: 0 | K35: =SUM(F35:J35) -> 5800
A36: =C36+7-WEEKDAY(C36+7-7) -> 45332 | B36: 32200 | C36: 45327 | E36: OXYTECH | F36: 22800 | G36: 9400 | H36: 0 | I36: 0 | J36: 0 | K36: =SUM(F36:J36) -> 32200
A37: =C37+7-WEEKDAY(C37+7-7) -> 45332 | B37: 6800 | C37: 45327 | E37: PIONIX | F37: 0 | G37: 6800 | H37: 0 | I37: 0 | J37: 0 | K37: =SUM(F37:J37) -> 6800
A38: =C38+7-WEEKDAY(C38+7-7) -> 45332 | B38: 2500 | C38: 45327 | E38: QUORATECH | F38: 0 | G38: 2500 | H38: 0 | I38: 0 | J38: 0 | K38: =SUM(F38:J38) -> 2500
A39: =C39+7-WEEKDAY(C39+7-7) -> 45332 | B39: 15700 | C39: 45327 | E39: RAZORIX | F39: 0 | G39: 15700 | H39: 0 | I39: 0 | J39: 0 | K39: =SUM(F39:J39) -> 15700
A40: =C40+7-WEEKDAY(C40+7-7) -> 45332 | B40: 33000 | C40: 45327 | E40: STORMTECH | F40: 33000 | G40: 0 | H40: 100 | I40: 0 | J40: 0 | K40: =SUM(F40:J40) -> 33100
... A46: =C46+7-WEEKDAY(C46+7-7) -> 45332 | B46: 0 | C46: 45327 | E46: YETITECH | F46: 0 | G46: 0 | H46: 0 | I46: 0 | J46: 0 | K46: =SUM(F46:J46) -> 0

Sheet AP Aging 01
B1: ↓ Flows thru Model | E1: ↓ Raw Data from AP Aging Report
A2: Week Ending | B2: Amount | C2: Date | D2: Credit Card? | E2: Vendor | F2: Current | G2: 1 - 30 | H2: 31 - 60 | I2: 61 - 90 | J2: > 90 | K2: TOTAL
A3: =C3+7-WEEKDAY(C3+7-7) -> 45325 | B3: 1300 | C3: 45323 | D3: Yes | E3: METRIX | F3: 1300 | G3: 0 | H3: 0 | I3: 0 | J3: 0 | K3: =SUM(F3:J3) -> 1300
A4: =C4+7-WEEKDAY(C4+7-7) -> 45297 | B4: 5000 | C4: 45292 | D4: Yes | E4: CAPITALONE | F4: 0 | G4: 0 | H4: 0 | I4: 0 | J4: 0 | K4: =SUM(F4:J4) -> 0
A5: =C5+7-WEEKDAY(C5+7-7) -> 45325 | B5: 5000 | C5: 45323 | D5: Yes | E5: CAPITALONE | F5: 0 | G5: 0 | H5: 0 | I5: 0 | J5: 0 | K5: =SUM(F5:J5) -> 0
A6: =C6+7-WEEKDAY(C6+7-7) -> 45353 | B6: 5000 | C6: 45352 | D6: Yes | E6: CAPITALONE | F6: 0 | G6: 0 | H6: 0 | I6: 0 | J6: 0 | K6: =SUM(F6:J6) -> 0
A7: =C7+7-WEEKDAY(C7+7-7) -> 45325 | B7: 900 | C7: 45323 | D7: Yes | E7: ORACLETECH | F7: 0 | G7: 900 | H7: 0 | I7: 0 | J7: 0 | K7: =SUM(F7:J7) -> 900
A8: =C8+7-WEEKDAY(C8+7-7) -> 45283 | B8: 37000 | C8: 45280 | E8: PHOENIXCORP | F8: 0 | G8: 0 | H8: 37000 | I8: 0 | J8: 0 | K8: =SUM(F8:J8) -> 37000
A9: =C9+7-WEEKDAY(C9+7-7) -> 45325 | B9: 3100 | C9: 45323 | D9: Yes | E9: QUANTUMIX | F9: 0 | G9: 3100 | H9: 0 | I9: 0 | J9: 0 | K9: =SUM(F9:J9) -> 3100
A10: =C10+7-WEEKDAY(C10+7-7) -> 45325 | B10: 11900 | C10: 45323 | D10: Yes | E10: RIFTTECH | F10: 0 | G10: 11900 | H10: 0 | I10: 0 | J10: 0 | K10: =SUM(F10:J10) -> 11900
A11: =C11+7-WEEKDAY(C11+7-7) -> 45325 | B11: 1500 | C11: 45323 | D11: Yes | E11: SILVERTECH | F11: 1200 | G11: 1200 | H11: 11600 | I11: 300 | J11: 200 | K11: =SUM(F11:J11) -> 14500
A12: =C12+7-WEEKDAY(C12+7-7) -> 45325 | B12: 1700 | C12: 45323 | D12: Yes | E12: TITANIX | F12: 1700 | G12: 0 | H12: 0 | I12: 0 | J12: 0 | K12: =SUM(F12:J12) -> 1700
A13: =C13+7-WEEKDAY(C13+7-7) -> 45325 | B13: 23100 | C13: 45323 | D13: Yes | E13: UNICORE | F13: 16900 | G13: 6200 | H13: 0 | I13: 0 | J13: 0 | K13: =SUM(F13:J13) -> 23100
A14: =C14+7-WEEKDAY(C14+7-7) -> 45283 | B14: 56200 | C14: 45280 | E14: VORTEXCORP | F14: 0 | G14: 56200 | H14: 0 | I14: 0 | J14: 0 | K14: =SUM(F14:J14) -> 56200
A15: =C15+7-WEEKDAY(C15+7-7) -> 45325 | B15: 2000 | C15: 45323 | D15: Yes | E15: WINDTECH | F15: 0 | G15: 2000 | H15: 0 | I15: 0 | J15: 0 | K15: =SUM(F15:J15) -> 2000
A16: =C16+7-WEEKDAY(C16+7-7) -> 45325 | B16: 500 | C16: 45323 | D16: Yes | E16: GRAVITONIX | F16: 500 | G16: 0 | H16: 0 | I16: 0 | J16: 0 | K16: =SUM(F16:J16) -> 500
A17: =C17+7-WEEKDAY(C17+7-7) -> 45269 | B17: 800 | C17: 45266 | E17: YONICORP | F17: 0 | G17: 800 | H17: 0 | I17: 0 | J17: 0 | K17: =SUM(F17:J17) -> 800
A18: =C18+7-WEEKDAY(C18+7-7) -> 45325 | B18: 6500 | C18: 45323 | D18: Yes | E18: ZYMOTECH | F18: 6500 | G18: 0 | H18: 0 | I18: 0 | J18: 0 | K18: =SUM(F18:J18) -> 6500
A19: =C19+7-WEEKDAY(C19+7-7) -> 45283 | B19: 30000 | C19: 45280 | E19: ASTRATECH | F19: 0 | G19: 61400 | H19: 40400 | I19: 17000 | J19: 13300 | K19: =SUM(F19:J19) -> 132100
A20: =C20+7-WEEKDAY(C20+7-7) -> 45297 | B20: 50000 | C20: 45296 | D20: Yes | E20: ASTRATECH | F20: 0 | G20: 0 | H20: 0 | I20: 0 | J20: 0 | K20: =SUM(F20:J20) -> 0
A21: =C21+7-WEEKDAY(C21+7-7) -> 45339 | B21: 50000 | C21: 45337 | E21: ASTRATECH | F21: 0 | G21: 0 | H21: 0 | I21: 0 | J21: 0 | K21: =SUM(F21:J21) -> 0
A22: =C22+7-WEEKDAY(C22+7-7) -> 45325 | B22: 2000 | C22: 45323 | D22: Yes | E22: BIOSIX | F22: 2000 | G22: 0 | H22: 0 | I22: 0 | J22: 0 | K22: =SUM(F22:J22) -> 2000
A23: =C23+7-WEEKDAY(C23+7-7) -> 45325 | B23: 120000 | C23: 45323 | D23: Yes | E23: CORETECH | F23: 75200 | G23: 156500 | H23: 74200 | I23: 95500 | J23: 15500 | K23: =SUM(F23:J23) -> 416900
A24: =C24+7-WEEKDAY(C24+7-7) -> 45353 | B24: 205000 | C24: 45352 | D24: Yes | E24: CORETECH | F24: 0 | G24: 0 | H24: 0 | I24: 0 | J24: 0 | K24: =SUM(F24:J24) -> 0
A25: =C25+7-WEEKDAY(C25+7-7) -> 45332 | B25: 300 | C25: 45327 | E25: DIODETECH | F25: 0 | G25: 300 | H25: 0 | I25: 0 | J25: 0 | K25: =SUM(F25:J25) -> 300
A26: =C26+7-WEEKDAY(C26+7-7) -> 45332 | B26: 700 | C26: 45327 | E26: ELEMENTIX | F26: 700 | G26: 0 | H26: 0 | I26: 0 | J26: 0 | K26: =SUM(F26:J26) -> 700
A27: =C27+7-WEEKDAY(C27+7-7) -> 45332 | B27: 6000 | C27: 45327 | E27: FROSTIX | F27: 0 | G27: 6000 | H27: 0 | I27: 0 | J27: 0 | K27: =SUM(F27:J27) -> 6000
A28: =C28+7-WEEKDAY(C28+7-7) -> 45269 | B28: 350000 | C28: 45265 | D28: Yes | E28: DISCOVER | F28: 0 | G28: 355300 | H28: 0 | I28: 0 | J28: 0 | K28: =SUM(F28:J28) -> 355300
A29: =C29+7-WEEKDAY(C29+7-7) -> 45332 | B29: 2500 | C29: 45327 | E29: HYDROTECH | F29: 0 | G29: 1700 | H29: 800 | I29: 0 | J29: 0 | K29: =SUM(F29:J29) -> 2500
A30: =C30+7-WEEKDAY(C30+7-7) -> 45332 | B30: 11700 | C30: 45327 | E30: IMPULSETECH | F30: 0 | G30: 11300 | H30: 400 | I30: 0 | J30: 0 | K30: =SUM(F30:J30) -> 11700
A31: =C31+7-WEEKDAY(C31+7-7) -> 45283 | B31: 300 | C31: 45280 | E31: JOLTIX | F31: 100 | G31: 200 | H31: 0 | I31: 0 | J31: 0 | K31: =SUM(F31:J31) -> 300
A32: =C32+7-WEEKDAY(C32+7-7) -> 45332 | B32: 6600 | C32: 45327 | E32: KONTACTIX | F32: 6600 | G32: 0 | H32: 0 | I32: 0 | J32: 0 | K32: =SUM(F32:J32) -> 6600
A33: =C33+7-WEEKDAY(C33+7-7) -> 45332 | B33: 3600 | C33: 45327 | E33: LYNXTECH | F33: 0 | G33: 3400 | H33: 200 | I33: 0 | J33: 0 | K33: =SUM(F33:J33) -> 3600
A34: =C34+7-WEEKDAY(C34+7-7) -> 45332 | B34: 7500 | C34: 45327 | E34: MATRIXIX | F34: 0 | G34: 7500 | H34: 0 | I34: 0 | J34: 0 | K34: =SUM(F34:J34) -> 7500
A35: =C35+7-WEEKDAY(C35+7-7) -> 45283 | B35: 5800 | C35: 45280 | E35: NOMADIX | F35: 0 | G35: 5800 | H35: 0 | I35: 0 | J35: 0 | K35: =SUM(F35:J35) -> 5800
A36: =C36+7-WEEKDAY(C36+7-7) -> 45332 | B36: 32000 | C36: 45327 | E36: OXYTECH | F36: 22800 | G36: 23100 | H36: 0 | I36: 0 | J36: 0 | K36: =SUM(F36:J36) -> 45900
A37: =C37+7-WEEKDAY(C37+7-7) -> 45332 | B37: 6800 | C37: 45327 | E37: PIONIX | F37: 0 | G37: 6800 | H37: 0 | I37: 0 | J37: 0 | K37: =SUM(F37:J37) -> 6800
A38: =C38+7-WEEKDAY(C38+7-7) -> 45332 | B38: 2500 | C38: 45327 | E38: QUORATECH | F38: 0 | G38: 2500 | H38: 0 | I38: 0 | J38: 0 | K38: =SUM(F38:J38) -> 2500
A39: =C39+7-WEEKDAY(C39+7-7) -> 45332 | B39: 15700 | C39: 45327 | E39: RAZORIX | F39: 0 | G39: 15700 | H39: 0 | I39: 0 | J39: 0 | K39: =SUM(F39:J39) -> 15700
A40: =C40+7-WEEKDAY(C40+7-7) -> 45332 | B40: 30000 | C40: 45327 | E40: STORMTECH | F40: 1000 | G40: 0 | H40: 100 | I40: 0 | J40: 0 | K40: =SUM(F40:J40) -> 1100
... A46: =C46+7-WEEKDAY(C46+7-7) -> 45332 | B46: 0 | C46: 45327 | E46: YETITECH | F46: 0 | G46: 0 | H46: 0 | I46: 0 | J46: 0 | K46: =SUM(F46:J46) -> 0

Sheet Actuals
A1: Week Ending | B1: Unique ID | C1: Category | D1: Category Check | E1: Transaction Number | F1: DATE | G1: TRANSACTION | H1: DESCRIPTION | I1: AMOUNT | J1: BALANCE
A2: =F2+7-WEEKDAY(F2+7-7) -> 45220 | B2: =E2&H2 -> 1WEB AUTHORIZED PMT KRYPTONIX | C2: {=IFERROR(INDEX(Table1[Category],MATCH(B2,Table1[Unique ID Matches],0)),INDEX(Table2[Category],MATCH(TRUE,ISNUMBER(SEARCH(Table2[Unique ID Contains],B2)),0)))} -> Dues & Subscriptions | D2: =INDEX('13 weeks CF'!$C$9:$C$59,MATCH(C2,'13 weeks CF'!$C$9:$C$59,0)) -> Dues & Subscriptions | E2: 1 | F2: 45215 | G2: DEBIT | H2: WEB AUTHORIZED PMT KRYPTONIX | I2: -83 | J2: 29760
A3: =F3+7-WEEKDAY(F3+7-7) -> 45220 | B3: =E3&H3 -> 2WEB AUTHORIZED PMT KRYPTONIX | C3: {=IFERROR(INDEX(Table1[Category],MATCH(B3,Table1[Unique ID Matches],0)),INDEX(Table2[Category],MATCH(TRUE,ISNUMBER(SEARCH(Table2[Unique ID Contains],B3)),0)))} -> Dues & Subscriptions | D3: =INDEX('13 weeks CF'!$C$9:$C$59,MATCH(C3,'13 weeks CF'!$C$9:$C$59,0)) -> Dues & Subscriptions | E3: 2 | F3: 45215 | G3: DEBIT | H3: WEB AUTHORIZED PMT KRYPTONIX | I3: -230 | J3: 29530
A4: =F4+7-WEEKDAY(F4+7-7) -> 45220 | B4: =E4&H4 -> 3CHECK | C4: {=IFERROR(INDEX(Table1[Category],MATCH(B4,Table1[Unique ID Matches],0)),INDEX(Table2[Category],MATCH(TRUE,ISNUMBER(SEARCH(Table2[Unique ID Contains],B4)),0)))} -> Payroll | D4: =INDEX('13 weeks CF'!$C$9:$C$59,MATCH(C4,'13 weeks CF'!$C$9:$C$59,0)) -> Payroll | E4: 3 | F4: 45215 | G4: 79613 | H4: CHECK | I4: -2000 | J4: 27530
A5: =F5+7-WEEKDAY(F5+7-7) -> 45220 | B5: =E5&H5 -> 4CHECK | C5: {=IFERROR(INDEX(Table1[Category],MATCH(B5,Table1[Unique ID Matches],0)),INDEX(Table2[Category],MATCH(TRUE,ISNUMBER(SEARCH(Table2[Unique ID Contains],B5)),0)))} -> Payroll | D5: =INDEX('13 weeks CF'!$C$9:$C$59,MATCH(C5,'13 weeks CF'!$C$9:$C$59,0)) -> Payroll | E5: 4 | F5: 45215 | G5: 79671 | H5: CHECK | I5: -1270 | J5: 26260
A6: =F6+7-WEEKDAY(F6+7-7) -> 45220 | B6: =E6&H6 -> 5CHECK | C6: {=IFERROR(INDEX(Table1[Category],MATCH(B6,Table1[Unique ID Matches],0)),INDEX(Table2[Category],MATCH(TRUE,ISNUMBER(SEARCH(Table2[Unique ID Contains],B6)),0)))} -> Accounts Payable | D6: =INDEX('13 weeks CF'!$C$9:$C$59,MATCH(C6,'13 weeks CF'!$C$9:$C$59,0)) -> Accounts Payable | E6: 5 | F6: 45215 | G6: 79673 | H6: CHECK | I6: -6570 | J6: 19690
A7: =F7+7-WEEKDAY(F7+7-7) -> 45220 | B7: =E7&H7 -> 6DEPOSIT | C7: {=IFERROR(INDEX(Table1[Category],MATCH(B7,Table1[Unique ID Matches],0)),INDEX(Table2[Category],MATCH(TRUE,ISNUMBER(SEARCH(Table2[Unique ID Contains],B7)),0)))} -> Invoiced AR + New Revenue | D7: =INDEX('13 weeks CF'!$C$9:$C$59,MATCH(C7,'13 weeks CF'!$C$9:$C$59,0)) -> Invoiced AR + New Revenue | E7: 6 | F7: 45216 | G7: CREDIT | H7: DEPOSIT | I7: 3270 | J7: 22960
A8: =F8+7-WEEKDAY(F8+7-7) -> 45220 | B8: =E8&H8 -> 7ELECTRONIC WITHDRAWAL GLOWTECH | C8: {=IFERROR(INDEX(Table1[Category],MATCH(B8,Table1[Unique ID Matches],0)),INDEX(Table2[Category],MATCH(TRUE,ISNUMBER(SEARCH(Table2[Unique ID Contains],B8)),0)))} -> Technology | D8: =INDEX('13 weeks CF'!$C$9:$C$59,MATCH(C8,'13 weeks CF'!$C$9:$C$59,0)) -> Technology | E8: 7 | F8: 45216 | G8: DEBIT | H8: ELECTRONIC WITHDRAWAL GLOWTECH | I8: -1030 | J8: 21930
A9: =F9+7-WEEKDAY(F9+7-7) -> 45220 | B9: =E9&H9 -> 8CHECK | C9: {=IFERROR(INDEX(Table1[Category],MATCH(B9,Table1[Unique ID Matches],0)),INDEX(Table2[Category],MATCH(TRUE,ISNUMBER(SEARCH(Table2[Unique ID Contains],B9)),0)))} -> Payroll | D9: =INDEX('13 weeks CF'!$C$9:$C$59,MATCH(C9,'13 weeks CF'!$C$9:$C$59,0)) -> Payroll | E9: 8 | F9: 45216 | G9: 79685 | H9: CHECK | I9: -1150 | J9: 20780
A10: =F10+7-WEEKDAY(F10+7-7) -> 45220 | B10: =E10&H10 -> 9CHECK | C10: {=IFERROR(INDEX(Table1[Category],MATCH(B10,Table1[Unique ID Matches],0)),INDEX(Table2[Category],MATCH(TRUE,ISNUMBER(SEARCH(Table2[Unique ID Contains],B10)),0)))} -> Payroll | D10: =INDEX('13 weeks CF'!$C$9:$C$59,MATCH(C10,'13 weeks CF'!$C$9:$C$59,0)) -> Payroll | E10: 9 | F10: 45216 | G10: 79719 | H10: CHECK | I10: -100 | J10: 20680
A11: =F11+7-WEEKDAY(F11+7-7) -> 45220 | B11: =E11&H11 -> 10DEPOSIT | C11: {=IFERROR(INDEX(Table1[Category],MATCH(B11,Table1[Unique ID Matches],0)),INDEX(Table2[Category],MATCH(TRUE,ISNUMBER(SEARCH(Table2[Unique ID Contains],B11)),0)))} -> Invoiced AR + New Revenue | D11: =INDEX('13 weeks CF'!$C$9:$C$59,MATCH(C11,'13 weeks CF'!$C$9:$C$59,0)) -> Invoiced AR + New Revenue | E11: 10 | F11: 45217 | G11: CREDIT | H11: DEPOSIT | I11: 20000 | J11: 40680
A12: =F12+7-WEEKDAY(F12+7-7) -> 45220 | B12: =E12&H12 -> 11DEPOSIT | C12: {=IFERROR(INDEX(Table1[Category],MATCH(B12,Table1[Unique ID Matches],0)),INDEX(Table2[Category],MATCH(TRUE,ISNUMBER(SEARCH(Table2[Unique ID Contains],B12)),0)))} -> Invoiced AR + New Revenue | D12: =INDEX('13 weeks CF'!$C$9:$C$59,MATCH(C12,'13 weeks CF'!$C$9:$C$59,0)) -> Invoiced AR + New Revenue | E12: 11 | F12: 45217 | G12: CREDIT | H12: DEPOSIT | I12: 12180 | J12: 52860
A13: =F13+7-WEEKDAY(F13+7-7) -> 45220 | B13: =E13&H13 -> 12DEPOSIT | C13: {=IFERROR(INDEX(Table1[Category],MATCH(B13,Table1[Unique ID Matches],0)),INDEX(Table2[Category],MATCH(TRUE,ISNUMBER(SEARCH(Table2[Unique ID Contains],B13)),0)))} -> Invoiced AR + New Revenue | D13: =INDEX('13 weeks CF'!$C$9:$C$59,MATCH(C13,'13 weeks CF'!$C$9:$C$59,0)) -> Invoiced AR + New Revenue | E13: 12 | F13: 45217 | G13: CREDIT | H13: DEPOSIT | I13: 7780 | J13: 60640
A14: =F14+7-WEEKDAY(F14+7-7) -> 45220 | B14: =E14&H14 -> 13ELECTRONIC WITHDRAWAL STATE DEPT REVENUE | C14: {=IFERROR(INDEX(Table1[Category],MATCH(B14,Table1[Unique ID Matches],0)),INDEX(Table2[Category],MATCH(TRUE,ISNUMBER(SEARCH(Table2[Unique ID Contains],B14)),0)))} -> Tax Distributions | D14: =INDEX('13 weeks CF'!$C$9:$C$59,MATCH(C14,'13 weeks CF'!$C$9:$C$59,0)) -> Tax Distributions | E14: 13 | F14: 45217 | G14: DEBIT | H14: ELECTRONIC WITHDRAWAL STATE DEPT REVENUE | I14: -3230 | J14: 57410
A15: =F15+7-WEEKDAY(F15+7-7) -> 45220 | B15: =E15&H15 -> 14ELECTRONIC WITHDRAWAL IRS | C15: {=IFERROR(INDEX(Table1[Category],MATCH(B15,Table1[Unique ID Matches],0)),INDEX(Table2[Category],MATCH(TRUE,ISNUMBER(SEARCH(Table2[Unique ID Contains],B15)),0)))} -> Tax Distributions | D15: =INDEX('13 weeks CF'!$C$9:$C$59,MATCH(C15,'13 weeks CF'!$C$9:$C$59,0)) -> Tax Distributions | E15: 14 | F15: 45217 | G15: DEBIT | H15: ELECTRONIC WITHDRAWAL IRS | I15: -16370 | J15: 41040
A16: =F16+7-WEEKDAY(F16+7-7) -> 45220 | B16: =E16&H16 -> 15CHECK | C16: {=IFERROR(INDEX(Table1[Category],MATCH(B16,Table1[Unique ID Matches],0)),INDEX(Table2[Category],MATCH(TRUE,ISNUMBER(SEARCH(Table2[Unique ID Contains],B16)),0)))} -> Accounts Payable | D16: =INDEX('13 weeks CF'!$C$9:$C$59,MATCH(C16,'13 weeks CF'!$C$9:$C$59,0)) -> Accounts Payable | E16: 15 | F16: 45217 | G16: 79665 | H16: CHECK | I16: -11630 | J16: 29410
A17: =F17+7-WEEKDAY(F17+7-7) -> 45220 | B17: =E17&H17 -> 16DEPOSIT | C17: {=IFERROR(INDEX(Table1[Category],MATCH(B17,Table1[Unique ID Matches],0)),INDEX(Table2[Category],MATCH(TRUE,ISNUMBER(SEARCH(Table2[Unique ID Contains],B17)),0)))} -> Invoiced AR + New Revenue | D17: =INDEX('13 weeks CF'!$C$9:$C$59,MATCH(C17,'13 weeks CF'!$C$9:$C$59,0)) -> Invoiced AR + New Revenue | E17: 16 | F17: 45218 | G17: CREDIT | H17: DEPOSIT | I17: 475690 | J17: 505100
A18: =F18+7-WEEKDAY(F18+7-7) -> 45220 | B18: =E18&H18 -> 17ELECTRONIC WITHDRAWAL PAYROLL | C18: {=IFERROR(INDEX(Table1[Category],MATCH(B18,Table1[Unique ID Matches],0)),INDEX(Table2[Category],MATCH(TRUE,ISNUMBER(SEARCH(Table2[Unique ID Contains],B18)),0)))} -> Payroll | D18: =INDEX('13 weeks CF'!$C$9:$C$59,MATCH(C18,'13 weeks CF'!$C$9:$C$59,0)) -> Payroll | E18: 17 | F18: 45218 | G18: DEBIT | H18: ELECTRONIC WITHDRAWAL PAYROLL | I18: -21670 | J18: 483430
A19: =F19+7-WEEKDAY(F19+7-7) -> 45220 | B19: =E19&H19 -> 18CHECK | C19: {=IFERROR(INDEX(Table1[Category],MATCH(B19,Table1[Unique ID Matches],0)),INDEX(Table2[Category],MATCH(TRUE,ISNUMBER(SEARCH(Table2[Unique ID Contains],B19)),0)))} -> Accounts Payable | D19: =INDEX('13 weeks CF'!$C$9:$C$59,MATCH(C19,'13 weeks CF'!$C$9:$C$59,0)) -> Accounts Payable | E19: 18 | F19: 45218 | G19: 79764 | H19: CHECK | I19: -94000 | J19: 389430
A20: =F20+7-WEEKDAY(F20+7-7) -> 45220 | B20: =E20&H20 -> 19DEPOSIT | C20: {=IFERROR(INDEX(Table1[Category],MATCH(B20,Table1[Unique ID Matches],0)),INDEX(Table2[Category],MATCH(TRUE,ISNUMBER(SEARCH(Table2[Unique ID Contains],B20)),0)))} -> Invoiced AR + New Revenue | D20: =INDEX('13 weeks CF'!$C$9:$C$59,MATCH(C20,'13 weeks CF'!$C$9:$C$59,0)) -> Invoiced AR + New Revenue | E20: 19 | F20: 45219 | G20: CREDIT | H20: DEPOSIT | I20: 1650 | J20: 391080
A21: =F21+7-WEEKDAY(F21+7-7) -> 45220 | B21: =E21&H21 -> 20ELECTRONIC WITHDRAWAL FRACTALIX | C21: {=IFERROR(INDEX(Table1[Category],MATCH(B21,Table1[Unique ID Matches],0)),INDEX(Table2[Category],MATCH(TRUE,ISNUMBER(SEARCH(Table2[Unique ID Contains],B21)),0)))} -> Lease Payments | D21: =INDEX('13 weeks CF'!$C$9:$C$59,MATCH(C21,'13 weeks CF'!$C$9:$C$59,0)) -> Lease Payments | E21: 20 | F21: 45219 | G21: DEBIT | H21: ELECTRONIC WITHDRAWAL FRACTALIX | I21: -1350 | J21: 389730
A22: =F22+7-WEEKDAY(F22+7-7) -> 45220 | B22: =E22&H22 -> 21CHECK | C22: {=IFERROR(INDEX(Table1[Category],MATCH(B22,Table1[Unique ID Matches],0)),INDEX(Table2[Category],MATCH(TRUE,ISNUMBER(SEARCH(Table2[Unique ID Contains],B22)),0)))} -> Payroll | D22: =INDEX('13 weeks CF'!$C$9:$C$59,MATCH(C22,'13 weeks CF'!$C$9:$C$59,0)) -> Payroll | E22: 21 | F22: 45219 | G22: 79722 | H22: CHECK | I22: -1110 | J22: 388620
A23: =F23+7-WEEKDAY(F23+7-7) -> 45220 | B23: =E23&H23 -> 22CHECK | C23: {=IFERROR(INDEX(Table1[Category],MATCH(B23,Table1[Unique ID Matches],0)),INDEX(Table2[Category],MATCH(TRUE,ISNUMBER(SEARCH(Table2[Unique ID Contains],B23)),0)))} -> Payroll | D23: =INDEX('13 weeks CF'!$C$9:$C$59,MATCH(C23,'13 weeks CF'!$C$9:$C$59,0)) -> Payroll | E23: 22 | F23: 45219 | G23: 79723 | H23: CHECK | I23: -760 | J23: 387860
A24: =F24+7-WEEKDAY(F24+7-7) -> 45220 | B24: =E24&H24 -> 23CHECK | C24: {=IFERROR(INDEX(Table1[Category],MATCH(B24,Table1[Unique ID Matches],0)),INDEX(Table2[Category],MATCH(TRUE,ISNUMBER(SEARCH(Table2[Unique ID Contains],B24)),0)))} -> Payroll | D24: =INDEX('13 weeks CF'!$C$9:$C$59,MATCH(C24,'13 weeks CF'!$C$9:$C$59,0)) -> Payroll | E24: 23 | F24: 45219 | G24: 79724 | H24: CHECK | I24: -720 | J24: 387140
A25: =F25+7-WEEKDAY(F25+7-7) -> 45220 | B25: =E25&H25 -> 24CHECK | C25: {=IFERROR(INDEX(Table1[Category],MATCH(B25,Table1[Unique ID Matches],0)),INDEX(Table2[Category],MATCH(TRUE,ISNUMBER(SEARCH(Table2[Unique ID Contains],B25)),0)))} -> Payroll | D25: =INDEX('13 weeks CF'!$C$9:$C$59,MATCH(C25,'13 weeks CF'!$C$9:$C$59,0)) -> Payroll | E25: 24 | F25: 45219 | G25: 79726 | H25: CHECK | I25: -1880 | J25: 385260
A26: =F26+7-WEEKDAY(F26+7-7) -> 45220 | B26: =E26&H26 -> 25CHECK | C26: {=IFERROR(INDEX(Table1[Category],MATCH(B26,Table1[Unique ID Matches],0)),INDEX(Table2[Category],MATCH(TRUE,ISNUMBER(SEARCH(Table2[Unique ID Contains],B26)),0)))} -> Payroll | D26: =INDEX('13 weeks CF'!$C$9:$C$59,MATCH(C26,'13 weeks CF'!$C$9:$C$59,0)) -> Payroll | E26: 25 | F26: 45219 | G26: 79727 | H26: CHECK | I26: -1130 | J26: 384130
A27: =F27+7-WEEKDAY(F27+7-7) -> 45220 | B27: =E27&H27 -> 26CHECK | C27: {=IFERROR(INDEX(Table1[Category],MATCH(B27,Table1[Unique ID Matches],0)),INDEX(Table2[Category],MATCH(TRUE,ISNUMBER(SEARCH(Table2[Unique ID Contains],B27)),0)))} -> Payroll | D27: =INDEX('13 weeks CF'!$C$9:$C$59,MATCH(C27,'13 weeks CF'!$C$9:$C$59,0)) -> Payroll | E27: 26 | F27: 45219 | G27: 79728 | H27: CHECK | I27: -1260 | J27: 382870
A28: =F28+7-WEEKDAY(F28+7-7) -> 45220 | B28: =E28&H28 -> 27CHECK | C28: {=IFERROR(INDEX(Table1[Category],MATCH(B28,Table1[Unique ID Matches],0)),INDEX(Table2[Category],MATCH(TRUE,ISNUMBER(SEARCH(Table2[Unique ID Contains],B28)),0)))} -> Payroll | D28: =INDEX('13 weeks CF'!$C$9:$C$59,MATCH(C28,'13 weeks CF'!$C$9:$C$59,0)) -> Payroll | E28: 27 | F28: 45219 | G28: 79729 | H28: CHECK | I28: -1160 | J28: 381710
A29: =F29+7-WEEKDAY(F29+7-7) -> 45220 | B29: =E29&H29 -> 28CHECK | C29: {=IFERROR(INDEX(Table1[Category],MATCH(B29,Table1[Unique ID Matches],0)),INDEX(Table2[Category],MATCH(TRUE,ISNUMBER(SEARCH(Table2[Unique ID Contains],B29)),0)))} -> Payroll | D29: =INDEX('13 weeks CF'!$C$9:$C$59,MATCH(C29,'13 weeks CF'!$C$9:$C$59,0)) -> Payroll | E29: 28 | F29: 45219 | G29: 79730 | H29: CHECK | I29: -1280 | J29: 380430
A30: =F30+7-WEEKDAY(F30+7-7) -> 45220 | B30: =E30&H30 -> 29CHECK | C30: {=IFERROR(INDEX(Table1[Category],MATCH(B30,Table1[Unique ID Matches],0)),INDEX(Table2[Category],MATCH(TRUE,ISNUMBER(SEARCH(Table2[Unique ID Contains],B30)),0)))} -> Payroll | D30: =INDEX('13 weeks CF'!$C$9:$C$59,MATCH(C30,'13 weeks CF'!$C$9:$C$59,0)) -> Payroll | E30: 29 | F30: 45219 | G30: 79731 | H30: CHECK | I30: -1180 | J30: 379250
A31: =F31+7-WEEKDAY(F31+7-7) -> 45220 | B31: =E31&H31 -> 30CHECK | C31: {=IFERROR(INDEX(Table1[Category],MATCH(B31,Table1[Unique ID Matches],0)),INDEX(Table2[Category],MATCH(TRUE,ISNUMBER(SEARCH(Table2[Unique ID Contains],B31)),0)))} -> Payroll | D31: =INDEX('13 weeks CF'!$C$9:$C$59,MATCH(C31,'13 weeks CF'!$C$9:$C$59,0)) -> Payroll | E31: 30 | F31: 45219 | G31: 79732 | H31: CHECK | I31: -1260 | J31: 377990
A32: =F32+7-WEEKDAY(F32+7-7) -> 45220 | B32: =E32&H32 -> 31CHECK | C32: {=IFERROR(INDEX(Table1[Category],MATCH(B32,Table1[Unique ID Matches],0)),INDEX(Table2[Category],MATCH(TRUE,ISNUMBER(SEARCH(Table2[Unique ID Contains],B32)),0)))} -> Payroll | D32: =INDEX('13 weeks CF'!$C$9:$C$59,MATCH(C32,'13 weeks CF'!$C$9:$C$59,0)) -> Payroll | E32: 31 | F32: 45219 | G32: 79734 | H32: CHECK | I32: -1310 | J32: 376680
A33: =F33+7-WEEKDAY(F33+7-7) -> 45220 | B33: =E33&H33 -> 32CHECK | C33: {=IFERROR(INDEX(Table1[Category],MATCH(B33,Table1[Unique ID Matches],0)),INDEX(Table2[Category],MATCH(TRUE,ISNUMBER(SEARCH(Table2[Unique ID Contains],B33)),0)))} -> Payroll | D33: =INDEX('13 weeks CF'!$C$9:$C$59,MATCH(C33,'13 weeks CF'!$C$9:$C$59,0)) -> Payroll | E33: 32 | F33: 45219 | G33: 79736 | H33: CHECK | I33: -1020 | J33: 375660
... A56: =F56+7-WEEKDAY(F56+7-7) -> 45220 | B56: =E56&H56 -> 55CHECK | C56: {=IFERROR(INDEX(Table1[Category],MATCH(B56,Table1[Unique ID Matches],0)),INDEX(Table2[Category],MATCH(TRUE,ISNUMBER(SEARCH(Table2[Unique ID Contains],B56)),0)))} -> Payroll | D56: =INDEX('13 weeks CF'!$C$9:$C$59,MATCH(C56,'13 weeks CF'!$C$9:$C$59,0)) -> Payroll | E56: 55 | F56: 45219 | G56: 79763 | H56: CHECK | I56: -1040 | J56: 345580
A57: =F57+7-WEEKDAY(F57+7-7) -> 45227 | B57: =E57&H57 -> 56WEB AUTHORIZED PMT KRYPTONIX | C57: {=IFERROR(INDEX(Table1[Category],MATCH(B57,Table1[Unique ID Matches],0)),INDEX(Table2[Category],MATCH(TRUE,ISNUMBER(SEARCH(Table2[Unique ID Contains],B57)),0)))} -> Dues & Subscriptions | D57: =INDEX('13 weeks CF'!$C$9:$C$59,MATCH(C57,'13 weeks CF'!$C$9:$C$59,0)) -> Dues & Subscriptions | E57: 56 | F57: 45222 | G57: DEBIT | H57: WEB AUTHORIZED PMT KRYPTONIX | I57: -80 | J57: 345500
A58: =F58+7-WEEKDAY(F58+7-7) -> 45227 | B58: =E58&H58 -> 57WEB AUTHORIZED PMT KRYPTONIX | C58: {=IFERROR(INDEX(Table1[Category],MATCH(B58,Table1[Unique ID Matches],0)),INDEX(Table2[Category],MATCH(TRUE,ISNUMBER(SEARCH(Table2[Unique ID Contains],B58)),0)))} -> Dues & Subscriptions | D58: =INDEX('13 weeks CF'!$C$9:$C$59,MATCH(C58,'13 weeks CF'!$C$9:$C$59,0)) -> Dues & Subscriptions | E58: 57 | F58: 45222 | G58: DEBIT | H58: WEB AUTHORIZED PMT KRYPTONIX | I58: -230 | J58: 345270
A59: =F59+7-WEEKDAY(F59+7-7) -> 45227 | B59: =E59&H59 -> 58CHECK | C59: {=IFERROR(INDEX(Table1[Category],MATCH(B59,Table1[Unique ID Matches],0)),INDEX(Table2[Category],MATCH(TRUE,ISNUMBER(SEARCH(Table2[Unique ID Contains],B59)),0)))} -> Payroll | D59: =INDEX('13 weeks CF'!$C$9:$C$59,MATCH(C59,'13 weeks CF'!$C$9:$C$59,0)) -> Payroll | E59: 58 | F59: 45222 | G59: 79725 | H59: CHECK | I59: -1210 | J59: 344060
A60: =F60+7-WEEKDAY(F60+7-7) -> 45227 | B60: =E60&H60 -> 59CHECK | C60: {=IFERROR(INDEX(Table1[Category],MATCH(B60,Table1[Unique ID Matches],0)),INDEX(Table2[Category],MATCH(TRUE,ISNUMBER(SEARCH(Table2[Unique ID Contains],B60)),0)))} -> Payroll | D60: =INDEX('13 weeks CF'!$C$9:$C$59,MATCH(C60,'13 weeks CF'!$C$9:$C$59,0)) -> Payroll | E60: 59 | F60: 45222 | G60: 79733 | H60: CHECK | I60: -1270 | J60: 342790
A61: =F61+7-WEEKDAY(F61+7-7) -> 45227 | B61: =E61&H61 -> 60CHECK | C61: {=IFERROR(INDEX(Table1[Category],MATCH(B61,Table1[Unique ID Matches],0)),INDEX(Table2[Category],MATCH(TRUE,ISNUMBER(SEARCH(Table2[Unique ID Contains],B61)),0)))} -> Payroll | D61: =INDEX('13 weeks CF'!$C$9:$C$59,MATCH(C61,'13 weeks CF'!$C$9:$C$59,0)) -> Payroll | E61: 60 | F61: 45222 | G61: 79737 | H61: CHECK | I61: -1340 | J61: 341450
A62: =F62+7-WEEKDAY(F62+7-7) -> 45227 | B62: =E62&H62 -> 61CHECK | C62: {=IFERROR(INDEX(Table1[Category],MATCH(B62,Table1[Unique ID Matches],0)),INDEX(Table2[Category],MATCH(TRUE,ISNUMBER(SEARCH(Table2[Unique ID Contains],B62)),0)))} -> Payroll | D62: =INDEX('13 weeks CF'!$C$9:$C$59,MATCH(C62,'13 weeks CF'!$C$9:$C$59,0)) -> Payroll | E62: 61 | F62: 45222 | G62: 79742 | H62: CHECK | I62: -1690 | J62: 339760
A63: =F63+7-WEEKDAY(F63+7-7) -> 45227 | B63: =E63&H63 -> 62CHECK | C63: {=IFERROR(INDEX(Table1[Category],MATCH(B63,Table1[Unique ID Matches],0)),INDEX(Table2[Category],MATCH(TRUE,ISNUMBER(SEARCH(Table2[Unique ID Contains],B63)),0)))} -> Payroll | D63: =INDEX('13 weeks CF'!$C$9:$C$59,MATCH(C63,'13 weeks CF'!$C$9:$C$59,0)) -> Payroll | E63: 62 | F63: 45222 | G63: 79746 | H63: CHECK | I63: -150 | J63: 339610
A64: =F64+7-WEEKDAY(F64+7-7) -> 45227 | B64: =E64&H64 -> 63CHECK | C64: {=IFERROR(INDEX(Table1[Category],MATCH(B64,Table1[Unique ID Matches],0)),INDEX(Table2[Category],MATCH(TRUE,ISNUMBER(SEARCH(Table2[Unique ID Contains],B64)),0)))} -> Payroll | D64: =INDEX('13 weeks CF'!$C$9:$C$59,MATCH(C64,'13 weeks CF'!$C$9:$C$59,0)) -> Payroll | E64: 63 | F64: 45222 | G64: 79765 | H64: CHECK | I64: -290 | J64: 339320
A65: =F65+7-WEEKDAY(F65+7-7) -> 45227 | B65: =E65&H65 -> 64ELECTRONIC WITHDRAWAL GLOWTECH | C65: {=IFERROR(INDEX(Table1[Category],MATCH(B65,Table1[Unique ID Matches],0)),INDEX(Table2[Category],MATCH(TRUE,ISNUMBER(SEARCH(Table2[Unique ID Contains],B65)),0)))} -> Technology | D65: =INDEX('13 weeks CF'!$C$9:$C$59,MATCH(C65,'13 weeks CF'!$C$9:$C$59,0)) -> Technology | E65: 64 | F65: 45223 | G65: DEBIT | H65: ELECTRONIC WITHDRAWAL GLOWTECH | I65: -1110 | J65: 338210
A66: =F66+7-WEEKDAY(F66+7-7) -> 45227 | B66: =E66&H66 -> 65CHECK | C66: {=IFERROR(INDEX(Table1[Category],MATCH(B66,Table1[Unique ID Matches],0)),INDEX(Table2[Category],MATCH(TRUE,ISNUMBER(SEARCH(Table2[Unique ID Contains],B66)),0)))} -> Payroll | D66: =INDEX('13 weeks CF'!$C$9:$C$59,MATCH(C66,'13 weeks CF'!$C$9:$C$59,0)) -> Payroll | E66: 65 | F66: 45223 | G66: 79768 | H66: CHECK | I66: -260 | J66: 337950
A67: =F67+7-WEEKDAY(F67+7-7) -> 45227 | B67: =E67&H67 -> 66ELECTRONIC WITHDRAWAL CRYONIX | C67: {=IFERROR(INDEX(Table1[Category],MATCH(B67,Table1[Unique ID Matches],0)),INDEX(Table2[Category],MATCH(TRUE,ISNUMBER(SEARCH(Table2[Unique ID Contains],B67)),0)))} -> Other Operating Outflows | D67: =INDEX('13 weeks CF'!$C$9:$C$59,MATCH(C67,'13 weeks CF'!$C$9:$C$59,0)) -> Other Operating Outflows | E67: 66 | F67: 45224 | G67: DEBIT | H67: ELECTRONIC WITHDRAWAL CRYONIX | I67: -1270 | J67: 336680
A68: =F68+7-WEEKDAY(F68+7-7) -> 45227 | B68: =E68&H68 -> 67ELECTRONIC WITHDRAWAL PAYROLL | C68: {=IFERROR(INDEX(Table1[Category],MATCH(B68,Table1[Unique ID Matches],0)),INDEX(Table2[Category],MATCH(TRUE,ISNUMBER(SEARCH(Table2[Unique ID Contains],B68)),0)))} -> Payroll | D68: =INDEX('13 weeks CF'!$C$9:$C$59,MATCH(C68,'13 weeks CF'!$C$9:$C$59,0)) -> Payroll | E68: 67 | F68: 45225 | G68: DEBIT | H68: ELECTRONIC WITHDRAWAL PAYROLL | I68: -22720 | J68: 313960
A69: =F69+7-WEEKDAY(F69+7-7) -> 45227 | B69: =E69&H69 -> 68ELECTRONIC WITHDRAWAL IRS | C69: {=IFERROR(INDEX(Table1[Category],MATCH(B69,Table1[Unique ID Matches],0)),INDEX(Table2[Category],MATCH(TRUE,ISNUMBER(SEARCH(Table2[Unique ID Contains],B69)),0)))} -> Tax Distributions | D69: =INDEX('13 weeks CF'!$C$9:$C$59,MATCH(C69,'13 weeks CF'!$C$9:$C$59,0)) -> Tax Distributions | E69: 68 | F69: 45225 | G69: DEBIT | H69: ELECTRONIC WITHDRAWAL IRS | I69: -17760 | J69: 296200
A70: =F70+7-WEEKDAY(F70+7-7) -> 45227 | B70: =E70&H70 -> 69CHECK | C70: {=IFERROR(INDEX(Table1[Category],MATCH(B70,Table1[Unique ID Matches],0)),INDEX(Table2[Category],MATCH(TRUE,ISNUMBER(SEARCH(Table2[Unique ID Contains],B70)),0)))} -> Accounts Payable | D70: =INDEX('13 weeks CF'!$C$9:$C$59,MATCH(C70,'13 weeks CF'!$C$9:$C$59,0)) -> Accounts Payable | E70: 69 | F70: 45225 | G70: 79805 | H70: CHECK | I70: -3580 | J70: 292620
A71: =F71+7-WEEKDAY(F71+7-7) -> 45227 | B71: =E71&H71 -> 70ELECTRONIC WITHDRAWAL STATE DEPT REVENUE | C71: {=IFERROR(INDEX(Table1[Category],MATCH(B71,Table1[Unique ID Matches],0)),INDEX(Table2[Category],MATCH(TRUE,ISNUMBER(SEARCH(Table2[Unique ID Contains],B71)),0)))} -> Tax Distributions | D71: =INDEX('13 weeks CF'!$C$9:$C$59,MATCH(C71,'13 weeks CF'!$C$9:$C$59,0)) -> Tax Distributions | E71: 70 | F71: 45226 | G71: DEBIT | H71: ELECTRONIC WITHDRAWAL STATE DEPT REVENUE | I71: -3470 | J71: 289150
A72: =F72+7-WEEKDAY(F72+7-7) -> 45227 | B72: =E72&H72 -> 71CHECK | C72: {=IFERROR(INDEX(Table1[Category],MATCH(B72,Table1[Unique ID Matches],0)),INDEX(Table2[Category],MATCH(TRUE,ISNUMBER(SEARCH(Table2[Unique ID Contains],B72)),0)))} -> Payroll | D72: =INDEX('13 weeks CF'!$C$9:$C$59,MATCH(C72,'13 weeks CF'!$C$9:$C$59,0)) -> Payroll | E72: 71 | F72: 45226 | G72: 79767 | H72: CHECK | I72: -210 | J72: 288940
A73: =F73+7-WEEKDAY(F73+7-7) -> 45227 | B73: =E73&H73 -> 72CHECK | C73: {=IFERROR(INDEX(Table1[Category],MATCH(B73,Table1[Unique ID Matches],0)),INDEX(Table2[Category],MATCH(TRUE,ISNUMBER(SEARCH(Table2[Unique ID Contains],B73)),0)))} -> Accounts Payable | D73: =INDEX('13 weeks CF'!$C$9:$C$59,MATCH(C73,'13 weeks CF'!$C$9:$C$59,0)) -> Accounts Payable | E73: 72 | F73: 45226 | G73: 79806 | H73: CHECK | I73: -6420 | J73: 282520
A74: =F74+7-WEEKDAY(F74+7-7) -> 45227 | B74: =E74&H74 -> 73CHECK | C74: {=IFERROR(INDEX(Table1[Category],MATCH(B74,Table1[Unique ID Matches],0)),INDEX(Table2[Category],MATCH(TRUE,ISNUMBER(SEARCH(Table2[Unique ID Contains],B74)),0)))} -> Accounts Payable | D74: =INDEX('13 weeks CF'!$C$9:$C$59,MATCH(C74,'13 weeks CF'!$C$9:$C$59,0)) -> Accounts Payable | E74: 73 | F74: 45226 | G74: 79807 | H74: CHECK | I74: -23620 | J74: 258900
A75: =F75+7-WEEKDAY(F75+7-7) -> 45227 | B75: =E75&H75 -> 74CHECK | C75: {=IFERROR(INDEX(Table1[Category],MATCH(B75,Table1[Unique ID Matches],0)),INDEX(Table2[Category],MATCH(TRUE,ISNUMBER(SEARCH(Table2[Unique ID Contains],B75)),0)))} -> Payroll | D75: =INDEX('13 weeks CF'!$C$9:$C$59,MATCH(C75,'13 weeks CF'!$C$9:$C$59,0)) -> Payroll | E75: 74 | F75: 45226 | G75: 79810 | H75: CHECK | I75: -1360 | J75: 257540
A76: =F76+7-WEEKDAY(F76+7-7) -> 45227 | B76: =E76&H76 -> 75CHECK | C76: {=IFERROR(INDEX(Table1[Category],MATCH(B76,Table1[Unique ID Matches],0)),INDEX(Table2[Category],MATCH(TRUE,ISNUMBER(SEARCH(Table2[Unique ID Contains],B76)),0)))} -> Payroll | D76: =INDEX('13 weeks CF'!$C$9:$C$59,MATCH(C76,'13 weeks CF'!$C$9:$C$59,0)) -> Payroll | E76: 75 | F76: 45226 | G76: 79811 | H76: CHECK | I76: -1300 | J76: 256240
A77: =F77+7-WEEKDAY(F77+7-7) -> 45227 | B77: =E77&H77 -> 76CHECK | C77: {=IFERROR(INDEX(Table1[Category],MATCH(B77,Table1[Unique ID Matches],0)),INDEX(Table2[Category],MATCH(TRUE,ISNUMBER(SEARCH(Table2[Unique ID Contains],B77)),0)))} -> Payroll | D77: =INDEX('13 weeks CF'!$C$9:$C$59,MATCH(C77,'13 weeks CF'!$C$9:$C$59,0)) -> Payroll | E77: 76 | F77: 45226 | G77: 79813 | H77: CHECK | I77: -1880 | J77: 254360
A78: =F78+7-WEEKDAY(F78+7-7) -> 45227 | B78: =E78&H78 -> 77CHECK | C78: {=IFERROR(INDEX(Table1[Category],MATCH(B78,Table1[Unique ID Matches],0)),INDEX(Table2[Category],MATCH(TRUE,ISNUMBER(SEARCH(Table2[Unique ID Contains],B78)),0)))} -> Payroll | D78: =INDEX('13 weeks CF'!$C$9:$C$59,MATCH(C78,'13 weeks CF'!$C$9:$C$59,0)) -> Payroll | E78: 77 | F78: 45226 | G78: 79814 | H78: CHECK | I78: -1300 | J78: 253060
A79: =F79+7-WEEKDAY(F79+7-7) -> 45227 | B79: =E79&H79 -> 78CHECK | C79: {=IFERROR(INDEX(Table1[Category],MATCH(B79,Table1[Unique ID Matches],0)),INDEX(Table2[Category],MATCH(TRUE,ISNUMBER(SEARCH(Table2[Unique ID Contains],B79)),0)))} -> Payroll | D79: =INDEX('13 weeks CF'!$C$9:$C$59,MATCH(C79,'13 weeks CF'!$C$9:$C$59,0)) -> Payroll | E79: 78 | F79: 45226 | G79: 79816 | H79: CHECK | I79: -1300 | J79: 251760
A80: =F80+7-WEEKDAY(F80+7-7) -> 45227 | B80: =E80&H80 -> 79CHECK | C80: {=IFERROR(INDEX(Table1[Category],MATCH(B80,Table1[Unique ID Matches],0)),INDEX(Table2[Category],MATCH(TRUE,ISNUMBER(SEARCH(Table2[Unique ID Contains],B80)),0)))} -> Payroll | D80: =INDEX('13 weeks CF'!$C$9:$C$59,MATCH(C80,'13 weeks CF'!$C$9:$C$59,0)) -> Payroll | E80: 79 | F80: 45226 | G80: 79817 | H80: CHECK | I80: -1320 | J80: 250440
A81: =F81+7-WEEKDAY(F81+7-7) -> 45227 | B81: =E81&H81 -> 80CHECK | C81: {=IFERROR(INDEX(Table1[Category],MATCH(B81,Table1[Unique ID Matches],0)),INDEX(Table2[Category],MATCH(TRUE,ISNUMBER(SEARCH(Table2[Unique ID Contains],B81)),0)))} -> Payroll | D81: =INDEX('13 weeks CF'!$C$9:$C$59,MATCH(C81,'13 weeks CF'!$C$9:$C$59,0)) -> Payroll | E81: 80 | F81: 45226 | G81: 79818 | H81: CHECK | I81: -1080 | J81: 249360
A82: =F82+7-WEEKDAY(F82+7-7) -> 45227 | B82: =E82&H82 -> 81CHECK | C82: {=IFERROR(INDEX(Table1[Category],MATCH(B82,Table1[Unique ID Matches],0)),INDEX(Table2[Category],MATCH(TRUE,ISNUMBER(SEARCH(Table2[Unique ID Contains],B82)),0)))} -> Payroll | D82: =INDEX('13 weeks CF'!$C$9:$C$59,MATCH(C82,'13 weeks CF'!$C$9:$C$59,0)) -> Payroll | E82: 81 | F82: 45226 | G82: 79819 | H82: CHECK | I82: -1390 | J82: 247970
A83: =F83+7-WEEKDAY(F83+7-7) -> 45227 | B83: =E83&H83 -> 82CHECK | C83: {=IFERROR(INDEX(Table1[Category],MATCH(B83,Table1[Unique ID Matches],0)),INDEX(Table2[Category],MATCH(TRUE,ISNUMBER(SEARCH(Table2[Unique ID Contains],B83)),0)))} -> Payroll | D83: =INDEX('13 weeks CF'!$C$9:$C$59,MATCH(C83,'13 weeks CF'!$C$9:$C$59,0)) -> Payroll | E83: 82 | F83: 45226 | G83: 79822 | H83: CHECK | I83: -1340 | J83: 246630
... A110: =F110+7-WEEKDAY(F110+7-7) -> 45227 | B110: =E110&H110 -> 109CHECK | C110: {=IFERROR(INDEX(Table1[Category],MATCH(B110,Table1[Unique ID Matches],0)),INDEX(Table2[Category],MATCH(TRUE,ISNUMBER(SEARCH(Table2[Unique ID Contains],B110)),0)))} -> Payroll | D110: =INDEX('13 weeks CF'!$C$9:$C$59,MATCH(C110,'13 weeks CF'!$C$9:$C$59,0)) -> Payroll | E110: 109 | F110: 45226 | G110: 79858 | H110: CHECK | I110: -1200 | J110: 210210
A111: =F111+7-WEEKDAY(F111+7-7) -> 45234 | B111: =E111&H111 -> 110WEB AUTHORIZED PMT KRYPTONIX | C111: {=IFERROR(INDEX(Table1[Category],MATCH(B111,Table1[Unique ID Matches],0)),INDEX(Table2[Category],MATCH(TRUE,ISNUMBER(SEARCH(Table2[Unique ID Contains],B111)),0)))} -> Dues & Subscriptions | D111: =INDEX('13 weeks CF'!$C$9:$C$59,MATCH(C111,'13 weeks CF'!$C$9:$C$59,0)) -> Dues & Subscriptions | E111: 110 | F111: 45229 | G111: DEBIT | H111: WEB AUTHORIZED PMT KRYPTONIX | I111: -80 | J111: 210130
A112: =F112+7-WEEKDAY(F112+7-7) -> 45234 | B112: =E112&H112 -> 111WEB AUTHORIZED PMT KRYPTONIX | C112: {=IFERROR(INDEX(Table1[Category],MATCH(B112,Table1[Unique ID Matches],0)),INDEX(Table2[Category],MATCH(TRUE,ISNUMBER(SEARCH(Table2[Unique ID Contains],B112)),0)))} -> Dues & Subscriptions | D112: =INDEX('13 weeks CF'!$C$9:$C$59,MATCH(C112,'13 weeks CF'!$C$9:$C$59,0)) -> Dues & Subscriptions | E112: 111 | F112: 45229 | G112: DEBIT | H112: WEB AUTHORIZED PMT KRYPTONIX | I112: -230 | J112: 209900
A113: =F113+7-WEEKDAY(F113+7-7) -> 45234 | B113: =E113&H113 -> 112ELECTRONIC WITHDRAWAL FRACTALIX | C113: {=IFERROR(INDEX(Table1[Category],MATCH(B113,Table1[Unique ID Matches],0)),INDEX(Table2[Category],MATCH(TRUE,ISNUMBER(SEARCH(Table2[Unique ID Contains],B113)),0)))} -> Lease Payments | D113: =INDEX('13 weeks CF'!$C$9:$C$59,MATCH(C113,'13 weeks CF'!$C$9:$C$59,0)) -> Lease Payments | E113: 112 | F113: 45229 | G113: DEBIT | H113: ELECTRONIC WITHDRAWAL FRACTALIX | I113: -1350 | J113: 208550
A114: =F114+7-WEEKDAY(F114+7-7) -> 45234 | B114: =E114&H114 -> 113CHECK | C114: {=IFERROR(INDEX(Table1[Category],MATCH(B114,Table1[Unique ID Matches],0)),INDEX(Table2[Category],MATCH(TRUE,ISNUMBER(SEARCH(Table2[Unique ID Contains],B114)),0)))} -> Payroll | D114: =INDEX('13 weeks CF'!$C$9:$C$59,MATCH(C114,'13 weeks CF'!$C$9:$C$59,0)) -> Payroll | E114: 113 | F114: 45229 | G114: 79735 | H114: CHECK | I114: -1130 | J114: 207420
A115: =F115+7-WEEKDAY(F115+7-7) -> 45234 | B115: =E115&H115 -> 114CHECK | C115: {=IFERROR(INDEX(Table1[Category],MATCH(B115,Table1[Unique ID Matches],0)),INDEX(Table2[Category],MATCH(TRUE,ISNUMBER(SEARCH(Table2[Unique ID Contains],B115)),0)))} -> Payroll | D115: =INDEX('13 weeks CF'!$C$9:$C$59,MATCH(C115,'13 weeks CF'!$C$9:$C$59,0)) -> Payroll | E115: 114 | F115: 45229 | G115: 79808 | H115: CHECK | I115: -100 | J115: 207320
A116: =F116+7-WEEKDAY(F116+7-7) -> 45234 | B116: =E116&H116 -> 115CHECK | C116: {=IFERROR(INDEX(Table1[Category],MATCH(B116,Table1[Unique ID Matches],0)),INDEX(Table2[Category],MATCH(TRUE,ISNUMBER(SEARCH(Table2[Unique ID Contains],B116)),0)))} -> Payroll | D116: =INDEX('13 weeks CF'!$C$9:$C$59,MATCH(C116,'13 weeks CF'!$C$9:$C$59,0)) -> Payroll | E116: 115 | F116: 45229 | G116: 79812 | H116: CHECK | I116: -1210 | J116: 206110
A117: =F117+7-WEEKDAY(F117+7-7) -> 45234 | B117: =E117&H117 -> 116CHECK | C117: {=IFERROR(INDEX(Table1[Category],MATCH(B117,Table1[Unique ID Matches],0)),INDEX(Table2[Category],MATCH(TRUE,ISNUMBER(SEARCH(Table2[Unique ID Contains],B117)),0)))} -> Payroll | D117: =INDEX('13 weeks CF'!$C$9:$C$59,MATCH(C117,'13 weeks CF'!$C$9:$C$59,0)) -> Payroll | E117: 116 | F117: 45229 | G117: 79820 | H117: CHECK | I117: -1190 | J117: 204920
A118: =F118+7-WEEKDAY(F118+7-7) -> 45234 | B118: =E118&H118 -> 117CHECK | C118: {=IFERROR(INDEX(Table1[Category],MATCH(B118,Table1[Unique ID Matches],0)),INDEX(Table2[Category],MATCH(TRUE,ISNUMBER(SEARCH(Table2[Unique ID Contains],B118)),0)))} -> Payroll | D118: =INDEX('13 weeks CF'!$C$9:$C$59,MATCH(C118,'13 weeks CF'!$C$9:$C$59,0)) -> Payroll | E118: 117 | F118: 45229 | G118: 79827 | H118: CHECK | I118: -1770 | J118: 203150
A119: =F119+7-WEEKDAY(F119+7-7) -> 45234 | B119: =E119&H119 -> 118CHECK | C119: {=IFERROR(INDEX(Table1[Category],MATCH(B119,Table1[Unique ID Matches],0)),INDEX(Table2[Category],MATCH(TRUE,ISNUMBER(SEARCH(Table2[Unique ID Contains],B119)),0)))} -> Payroll | D119: =INDEX('13 weeks CF'!$C$9:$C$59,MATCH(C119,'13 weeks CF'!$C$9:$C$59,0)) -> Payroll | E119: 118 | F119: 45229 | G119: 79846 | H119: CHECK | I119: -990 | J119: 202160
A120: =F120+7-WEEKDAY(F120+7-7) -> 45234 | B120: =E120&H120 -> 119ELECTRONIC WITHDRAWAL HYPERTECH | C120: {=IFERROR(INDEX(Table1[Category],MATCH(B120,Table1[Unique ID Matches],0)),INDEX(Table2[Category],MATCH(TRUE,ISNUMBER(SEARCH(Table2[Unique ID Contains],B120)),0)))} -> Marketing | D120: =INDEX('13 weeks CF'!$C$9:$C$59,MATCH(C120,'13 weeks CF'!$C$9:$C$59,0)) -> Marketing | E120: 119 | F120: 45230 | G120: DEBIT | H120: ELECTRONIC WITHDRAWAL HYPERTECH | I120: -1510 | J120: 200650
A121: =F121+7-WEEKDAY(F121+7-7) -> 45234 | B121: =E121&H121 -> 120ELECTRONIC WITHDRAWAL IRS | C121: {=IFERROR(INDEX(Table1[Category],MATCH(B121,Table1[Unique ID Matches],0)),INDEX(Table2[Category],MATCH(TRUE,ISNUMBER(SEARCH(Table2[Unique ID Contains],B121)),0)))} -> Tax Distributions | D121: =INDEX('13 weeks CF'!$C$9:$C$59,MATCH(C121,'13 weeks CF'!$C$9:$C$59,0)) -> Tax Distributions | E121: 120 | F121: 45230 | G121: DEBIT | H121: ELECTRONIC WITHDRAWAL IRS | I121: -1140 | J121: 199510
A122: =F122+7-WEEKDAY(F122+7-7) -> 45234 | B122: =E122&H122 -> 121CHECK | C122: {=IFERROR(INDEX(Table1[Category],MATCH(B122,Table1[Unique ID Matches],0)),INDEX(Table2[Category],MATCH(TRUE,ISNUMBER(SEARCH(Table2[Unique ID Contains],B122)),0)))} -> Payroll | D122: =INDEX('13 weeks CF'!$C$9:$C$59,MATCH(C122,'13 weeks CF'!$C$9:$C$59,0)) -> Payroll | E122: 121 | F122: 45230 | G122: 79721 | H122: CHECK | I122: -600 | J122: 198910
A123: =F123+7-WEEKDAY(F123+7-7) -> 45234 | B123: =E123&H123 -> 122ELECTRONIC DEPOSIT ZONIX | C123: {=IFERROR(INDEX(Table1[Category],MATCH(B123,Table1[Unique ID Matches],0)),INDEX(Table2[Category],MATCH(TRUE,ISNUMBER(SEARCH(Table2[Unique ID Contains],B123)),0)))} -> Invoiced AR + New Revenue | D123: =INDEX('13 weeks CF'!$C$9:$C$59,MATCH(C123,'13 weeks CF'!$C$9:$C$59,0)) -> Invoiced AR + New Revenue | E123: 122 | F123: 45231 | G123: CREDIT | H123: ELECTRONIC DEPOSIT ZONIX | I123: 131830 | J123: 330740
A124: =F124+7-WEEKDAY(F124+7-7) -> 45234 | B124: =E124&H124 -> 123ELECTRONIC WITHDRAWAL GLOWTECH | C124: {=IFERROR(INDEX(Table1[Category],MATCH(B124,Table1[Unique ID Matches],0)),INDEX(Table2[Category],MATCH(TRUE,ISNUMBER(SEARCH(Table2[Unique ID Contains],B124)),0)))} -> Technology | D124: =INDEX('13 weeks CF'!$C$9:$C$59,MATCH(C124,'13 weeks CF'!$C$9:$C$59,0)) -> Technology | E124: 123 | F124: 45231 | G124: DEBIT | H124: ELECTRONIC WITHDRAWAL GLOWTECH | I124: -1150 | J124: 329590
A125: =F125+7-WEEKDAY(F125+7-7) -> 45234 | B125: =E125&H125 -> 124WEB AUTHORIZED PMT LUCENTIX | C125: {=IFERROR(INDEX(Table1[Category],MATCH(B125,Table1[Unique ID Matches],0)),INDEX(Table2[Category],MATCH(TRUE,ISNUMBER(SEARCH(Table2[Unique ID Contains],B125)),0)))} -> Vehicles | D125: =INDEX('13 weeks CF'!$C$9:$C$59,MATCH(C125,'13 weeks CF'!$C$9:$C$59,0)) -> Vehicles | E125: 124 | F125: 45231 | G125: DEBIT | H125: WEB AUTHORIZED PMT LUCENTIX | I125: -4480 | J125: 325110
A126: =F126+7-WEEKDAY(F126+7-7) -> 45234 | B126: =E126&H126 -> 125ELECTRONIC WITHDRAWAL IRS | C126: {=IFERROR(INDEX(Table1[Category],MATCH(B126,Table1[Unique ID Matches],0)),INDEX(Table2[Category],MATCH(TRUE,ISNUMBER(SEARCH(Table2[Unique ID Contains],B126)),0)))} -> Tax Distributions | D126: =INDEX('13 weeks CF'!$C$9:$C$59,MATCH(C126,'13 weeks CF'!$C$9:$C$59,0)) -> Tax Distributions | E126: 125 | F126: 45231 | G126: DEBIT | H126: ELECTRONIC WITHDRAWAL IRS | I126: -19800 | J126: 305310
A127: =F127+7-WEEKDAY(F127+7-7) -> 45234 | B127: =E127&H127 -> 126ELECTRONIC WITHDRAWAL STATE DMV | C127: {=IFERROR(INDEX(Table1[Category],MATCH(B127,Table1[Unique ID Matches],0)),INDEX(Table2[Category],MATCH(TRUE,ISNUMBER(SEARCH(Table2[Unique ID Contains],B127)),0)))} -> Vehicles | D127: =INDEX('13 weeks CF'!$C$9:$C$59,MATCH(C127,'13 weeks CF'!$C$9:$C$59,0)) -> Vehicles | E127: 126 | F127: 45231 | G127: DEBIT | H127: ELECTRONIC WITHDRAWAL STATE DMV | I127: -300 | J127: 305010
A128: =F128+7-WEEKDAY(F128+7-7) -> 45234 | B128: =E128&H128 -> 127ELECTRONIC WITHDRAWAL STATE DMV | C128: {=IFERROR(INDEX(Table1[Category],MATCH(B128,Table1[Unique ID Matches],0)),INDEX(Table2[Category],MATCH(TRUE,ISNUMBER(SEARCH(Table2[Unique ID Contains],B128)),0)))} -> Vehicles | D128: =INDEX('13 weeks CF'!$C$9:$C$59,MATCH(C128,'13 weeks CF'!$C$9:$C$59,0)) -> Vehicles | E128: 127 | F128: 45231 | G128: DEBIT | H128: ELECTRONIC WITHDRAWAL STATE DMV | I128: -2880 | J128: 302130
A129: =F129+7-WEEKDAY(F129+7-7) -> 45234 | B129: =E129&H129 -> 128DEPOSIT | C129: {=IFERROR(INDEX(Table1[Category],MATCH(B129,Table1[Unique ID Matches],0)),INDEX(Table2[Category],MATCH(TRUE,ISNUMBER(SEARCH(Table2[Unique ID Contains],B129)),0)))} -> Invoiced AR + New Revenue | D129: =INDEX('13 weeks CF'!$C$9:$C$59,MATCH(C129,'13 weeks CF'!$C$9:$C$59,0)) -> Invoiced AR + New Revenue | E129: 128 | F129: 45232 | G129: CREDIT | H129: DEPOSIT | I129: 122750 | J129: 424880
A130: =F130+7-WEEKDAY(F130+7-7) -> 45234 | B130: =E130&H130 -> 129DEPOSIT | C130: {=IFERROR(INDEX(Table1[Category],MATCH(B130,Table1[Unique ID Matches],0)),INDEX(Table2[Category],MATCH(TRUE,ISNUMBER(SEARCH(Table2[Unique ID Contains],B130)),0)))} -> Invoiced AR + New Revenue | D130: =INDEX('13 weeks CF'!$C$9:$C$59,MATCH(C130,'13 weeks CF'!$C$9:$C$59,0)) -> Invoiced AR + New Revenue | E130: 129 | F130: 45232 | G130: CREDIT | H130: DEPOSIT | I130: 71280 | J130: 496160
A131: =F131+7-WEEKDAY(F131+7-7) -> 45234 | B131: =E131&H131 -> 130ELECTRONIC WITHDRAWAL BLITZIX | C131: {=IFERROR(INDEX(Table1[Category],MATCH(B131,Table1[Unique ID Matches],0)),INDEX(Table2[Category],MATCH(TRUE,ISNUMBER(SEARCH(Table2[Unique ID Contains],B131)),0)))} -> Other Operating Outflows | D131: =INDEX('13 weeks CF'!$C$9:$C$59,MATCH(C131,'13 weeks CF'!$C$9:$C$59,0)) -> Other Operating Outflows | E131: 130 | F131: 45232 | G131: DEBIT | H131: ELECTRONIC WITHDRAWAL BLITZIX | I131: -1780 | J131: 494380
A132: =F132+7-WEEKDAY(F132+7-7) -> 45234 | B132: =E132&H132 -> 131ELECTRONIC WITHDRAWAL STATE DEPT REVENUE | C132: {=IFERROR(INDEX(Table1[Category],MATCH(B132,Table1[Unique ID Matches],0)),INDEX(Table2[Category],MATCH(TRUE,ISNUMBER(SEARCH(Table2[Unique ID Contains],B132)),0)))} -> Tax Distributions | D132: =INDEX('13 weeks CF'!$C$9:$C$59,MATCH(C132,'13 weeks CF'!$C$9:$C$59,0)) -> Tax Distributions | E132: 131 | F132: 45232 | G132: DEBIT | H132: ELECTRONIC WITHDRAWAL STATE DEPT REVENUE | I132: -3800 | J132: 490580
A133: =F133+7-WEEKDAY(F133+7-7) -> 45234 | B133: =E133&H133 -> 132ELECTRONIC WITHDRAWAL CAPITALONE | C133: {=IFERROR(INDEX(Table1[Category],MATCH(B133,Table1[Unique ID Matches],0)),INDEX(Table2[Category],MATCH(TRUE,ISNUMBER(SEARCH(Table2[Unique ID Contains],B133)),0)))} -> Credit Cards | D133: =INDEX('13 weeks CF'!$C$9:$C$59,MATCH(C133,'13 weeks CF'!$C$9:$C$59,0)) -> Credit Cards | E133: 132 | F133: 45232 | G133: DEBIT | H133: ELECTRONIC WITHDRAWAL CAPITALONE | I133: -6270 | J133: 484310
A134: =F134+7-WEEKDAY(F134+7-7) -> 45234 | B134: =E134&H134 -> 133ELECTRONIC WITHDRAWAL PAYROLL | C134: {=IFERROR(INDEX(Table1[Category],MATCH(B134,Table1[Unique ID Matches],0)),INDEX(Table2[Category],MATCH(TRUE,ISNUMBER(SEARCH(Table2[Unique ID Contains],B134)),0)))} -> Payroll | D134: =INDEX('13 weeks CF'!$C$9:$C$59,MATCH(C134,'13 weeks CF'!$C$9:$C$59,0)) -> Payroll | E134: 133 | F134: 45232 | G134: DEBIT | H134: ELECTRONIC WITHDRAWAL PAYROLL | I134: -12260 | J134: 472050
A135: =F135+7-WEEKDAY(F135+7-7) -> 45234 | B135: =E135&H135 -> 134ELECTRONIC WITHDRAWAL ETERNIX | C135: {=IFERROR(INDEX(Table1[Category],MATCH(B135,Table1[Unique ID Matches],0)),INDEX(Table2[Category],MATCH(TRUE,ISNUMBER(SEARCH(Table2[Unique ID Contains],B135)),0)))} -> Professional Fees | D135: =INDEX('13 weeks CF'!$C$9:$C$59,MATCH(C135,'13 weeks CF'!$C$9:$C$59,0)) -> Professional Fees | E135: 134 | F135: 45232 | G135: DEBIT | H135: ELECTRONIC WITHDRAWAL ETERNIX | I135: -5000 | J135: 467050
A136: =F136+7-WEEKDAY(F136+7-7) -> 45234 | B136: =E136&H136 -> 135CHECK | C136: {=IFERROR(INDEX(Table1[Category],MATCH(B136,Table1[Unique ID Matches],0)),INDEX(Table2[Category],MATCH(TRUE,ISNUMBER(SEARCH(Table2[Unique ID Contains],B136)),0)))} -> Payroll | D136: =INDEX('13 weeks CF'!$C$9:$C$59,MATCH(C136,'13 weeks CF'!$C$9:$C$59,0)) -> Payroll | E136: 135 | F136: 45232 | G136: 79770 | H136: CHECK | I136: -190 | J136: 466860
A137: =F137+7-WEEKDAY(F137+7-7) -> 45234 | B137: =E137&H137 -> 136CHECK | C137: {=IFERROR(INDEX(Table1[Category],MATCH(B137,Table1[Unique ID Matches],0)),INDEX(Table2[Category],MATCH(TRUE,ISNUMBER(SEARCH(Table2[Unique ID Contains],B137)),0)))} -> Accounts Payable | D137: =INDEX('13 weeks CF'!$C$9:$C$59,MATCH(C137,'13 weeks CF'!$C$9:$C$59,0)) -> Accounts Payable | E137: 136 | F137: 45232 | G137: 79772 | H137: CHECK | I137: -3060 | J137: 463800
A138: =F138+7-WEEKDAY(F138+7-7) -> 45234 | B138: =E138&H138 -> 137CHECK | C138: {=IFERROR(INDEX(Table1[Category],MATCH(B138,Table1[Unique ID Matches],0)),INDEX(Table2[Category],MATCH(TRUE,ISNUMBER(SEARCH(Table2[Unique ID Contains],B138)),0)))} -> Payroll | D138: =INDEX('13 weeks CF'!$C$9:$C$59,MATCH(C138,'13 weeks CF'!$C$9:$C$59,0)) -> Payroll | E138: 137 | F138: 45232 | G138: 79780 | H138: CHECK | I138: -1730 | J138: 462070
A139: =F139+7-WEEKDAY(F139+7-7) -> 45234 | B139: =E139&H139 -> 138CHECK | C139: {=IFERROR(INDEX(Table1[Category],MATCH(B139,Table1[Unique ID Matches],0)),INDEX(Table2[Category],MATCH(TRUE,ISNUMBER(SEARCH(Table2[Unique ID Contains],B139)),0)))} -> Payroll | D139: =INDEX('13 weeks CF'!$C$9:$C$59,MATCH(C139,'13 weeks CF'!$C$9:$C$59,0)) -> Payroll | E139: 138 | F139: 45232 | G139: 79781 | H139: CHECK | I139: -1580 | J139: 460490
A140: =F140+7-WEEKDAY(F140+7-7) -> 45234 | B140: =E140&H140 -> 139CHECK | C140: {=IFERROR(INDEX(Table1[Category],MATCH(B140,Table1[Unique ID Matches],0)),INDEX(Table2[Category],MATCH(TRUE,ISNUMBER(SEARCH(Table2[Unique ID Contains],B140)),0)))} -> Payroll | D140: =INDEX('13 weeks CF'!$C$9:$C$59,MATCH(C140,'13 weeks CF'!$C$9:$C$59,0)) -> Payroll | E140: 139 | F140: 45232 | G140: 79783 | H140: CHECK | I140: -1580 | J140: 458910
A141: =F141+7-WEEKDAY(F141+7-7) -> 45234 | B141: =E141&H141 -> 140CHECK | C141: {=IFERROR(INDEX(Table1[Category],MATCH(B141,Table1[Unique ID Matches],0)),INDEX(Table2[Category],MATCH(TRUE,ISNUMBER(SEARCH(Table2[Unique ID Contains],B141)),0)))} -> Payroll | D141: =INDEX('13 weeks CF'!$C$9:$C$59,MATCH(C141,'13 weeks CF'!$C$9:$C$59,0)) -> Payroll | E141: 140 | F141: 45232 | G141: 79784 | H141: CHECK | I141: -1440 | J141: 457470
A142: =F142+7-WEEKDAY(F142+7-7) -> 45234 | B142: =E142&H142 -> 141CHECK | C142: {=IFERROR(INDEX(Table1[Category],MATCH(B142,Table1[Unique ID Matches],0)),INDEX(Table2[Category],MATCH(TRUE,ISNUMBER(SEARCH(Table2[Unique ID Contains],B142)),0)))} -> Payroll | D142: =INDEX('13 weeks CF'!$C$9:$C$59,MATCH(C142,'13 weeks CF'!$C$9:$C$59,0)) -> Payroll | E142: 141 | F142: 45232 | G142: 79785 | H142: CHECK | I142: -1640 | J142: 455830
A143: =F143+7-WEEKDAY(F143+7-7) -> 45234 | B143: =E143&H143 -> 142CHECK | C143: {=IFERROR(INDEX(Table1[Category],MATCH(B143,Table1[Unique ID Matches],0)),INDEX(Table2[Category],MATCH(TRUE,ISNUMBER(SEARCH(Table2[Unique ID Contains],B143)),0)))} -> Payroll | D143: =INDEX('13 weeks CF'!$C$9:$C$59,MATCH(C143,'13 weeks CF'!$C$9:$C$59,0)) -> Payroll | E143: 142 | F143: 45232 | G143: 79786 | H143: CHECK | I143: -1610 | J143: 454220
A144: =F144+7-WEEKDAY(F144+7-7) -> 45234 | B144: =E144&H144 -> 143CHECK | C144: {=IFERROR(INDEX(Table1[Category],MATCH(B144,Table1[Unique ID Matches],0)),INDEX(Table2[Category],MATCH(TRUE,ISNUMBER(SEARCH(Table2[Unique ID Contains],B144)),0)))} -> Payroll | D144: =INDEX('13 weeks CF'!$C$9:$C$59,MATCH(C144,'13 weeks CF'!$C$9:$C$59,0)) -> Payroll | E144: 143 | F144: 45232 | G144: 79787 | H144: CHECK | I144: -1430 | J144: 452790
A145: =F145+7-WEEKDAY(F145+7-7) -> 45234 | B145: =E145&H145 -> 144CHECK | C145: {=IFERROR(INDEX(Table1[Category],MATCH(B145,Table1[Unique ID Matches],0)),INDEX(Table2[Category],MATCH(TRUE,ISNUMBER(SEARCH(Table2[Unique ID Contains],B145)),0)))} -> Payroll | D145: =INDEX('13 weeks CF'!$C$9:$C$59,MATCH(C145,'13 weeks CF'!$C$9:$C$59,0)) -> Payroll | E145: 144 | F145: 45232 | G145: 79788 | H145: CHECK | I145: -1460 | J145: 451330
A146: =F146+7-WEEKDAY(F146+7-7) -> 45234 | B146: =E146&H146 -> 145CHECK | C146: {=IFERROR(INDEX(Table1[Category],MATCH(B146,Table1[Unique ID Matches],0)),INDEX(Table2[Category],MATCH(TRUE,ISNUMBER(SEARCH(Table2[Unique ID Contains],B146)),0)))} -> Payroll | D146: =INDEX('13 weeks CF'!$C$9:$C$59,MATCH(C146,'13 weeks CF'!$C$9:$C$59,0)) -> Payroll | E146: 145 | F146: 45232 | G146: 79789 | H146: CHECK | I146: -1660 | J146: 449670
A147: =F147+7-WEEKDAY(F147+7-7) -> 45234 | B147: =E147&H147 -> 146DEPOSIT | C147: {=IFERROR(INDEX(Table1[Category],MATCH(B147,Table1[Unique ID Matches],0)),INDEX(Table2[Category],MATCH(TRUE,ISNUMBER(SEARCH(Table2[Unique ID Contains],B147)),0)))} -> Invoiced AR + New Revenue | D147: =INDEX('13 weeks CF'!$C$9:$C$59,MATCH(C147,'13 weeks CF'!$C$9:$C$59,0)) -> Invoiced AR + New Revenue | E147: 146 | F147: 45233 | G147: CREDIT | H147: DEPOSIT | I147: 46240 | J147: 495910
A148: =F148+7-WEEKDAY(F148+7-7) -> 45234 | B148: =E148&H148 -> 147ELECTRONIC WITHDRAWAL DYNACORP | C148: {=IFERROR(INDEX(Table1[Category],MATCH(B148,Table1[Unique ID Matches],0)),INDEX(Table2[Category],MATCH(TRUE,ISNUMBER(SEARCH(Table2[Unique ID Contains],B148)),0)))} -> Other Operating Outflows | D148: =INDEX('13 weeks CF'!$C$9:$C$59,MATCH(C148,'13 weeks CF'!$C$9:$C$59,0)) -> Other Operating Outflows | E148: 147 | F148: 45233 | G148: DEBIT | H148: ELECTRONIC WITHDRAWAL DYNACORP | I148: -790 | J148: 495120
...

Sheet Transaction Mapping
A1: Unique ID Matches | B1: Category | C1: Category Check | E1: Unique ID Contains | F1: Category | G1: Category Check
A2: 5CHECK | B2: Accounts Payable | C2: =INDEX('13 weeks CF'!$C$9:$C$59,MATCH(Table1[[#This Row],[Category]],'13 weeks CF'!$C$9:$C$59,0)) -> Accounts Payable | E2: BLITZIX | F2: Other Operating Outflows | G2: =INDEX('13 weeks CF'!$C$9:$C$59,MATCH(Table2[[#This Row],[Category]],'13 weeks CF'!$C$9:$C$59,0)) -> Other Operating Outflows
A3: 15CHECK | B3: Accounts Payable | C3: =INDEX('13 weeks CF'!$C$9:$C$59,MATCH(Table1[[#This Row],[Category]],'13 weeks CF'!$C$9:$C$59,0)) -> Accounts Payable | E3: CAPITALONE | F3: Credit Cards | G3: =INDEX('13 weeks CF'!$C$9:$C$59,MATCH(Table2[[#This Row],[Category]],'13 weeks CF'!$C$9:$C$59,0)) -> Credit Cards
A4: 18CHECK | B4: Accounts Payable | C4: =INDEX('13 weeks CF'!$C$9:$C$59,MATCH(Table1[[#This Row],[Category]],'13 weeks CF'!$C$9:$C$59,0)) -> Accounts Payable | E4: CHECK | F4: Payroll | G4: =INDEX('13 weeks CF'!$C$9:$C$59,MATCH(Table2[[#This Row],[Category]],'13 weeks CF'!$C$9:$C$59,0)) -> Payroll
A5: 69CHECK | B5: Accounts Payable | C5: =INDEX('13 weeks CF'!$C$9:$C$59,MATCH(Table1[[#This Row],[Category]],'13 weeks CF'!$C$9:$C$59,0)) -> Accounts Payable | E5: CRYONIX | F5: Other Operating Outflows | G5: =INDEX('13 weeks CF'!$C$9:$C$59,MATCH(Table2[[#This Row],[Category]],'13 weeks CF'!$C$9:$C$59,0)) -> Other Operating Outflows
A6: 72CHECK | B6: Accounts Payable | C6: =INDEX('13 weeks CF'!$C$9:$C$59,MATCH(Table1[[#This Row],[Category]],'13 weeks CF'!$C$9:$C$59,0)) -> Accounts Payable | E6: DEPOSIT | F6: Invoiced AR + New Revenue | G6: =INDEX('13 weeks CF'!$C$9:$C$59,MATCH(Table2[[#This Row],[Category]],'13 weeks CF'!$C$9:$C$59,0)) -> Invoiced AR + New Revenue
A7: 73CHECK | B7: Accounts Payable | C7: =INDEX('13 weeks CF'!$C$9:$C$59,MATCH(Table1[[#This Row],[Category]],'13 weeks CF'!$C$9:$C$59,0)) -> Accounts Payable | E7: DYNACORP | F7: Other Operating Outflows | G7: =INDEX('13 weeks CF'!$C$9:$C$59,MATCH(Table2[[#This Row],[Category]],'13 weeks CF'!$C$9:$C$59,0)) -> Other Operating Outflows
A8: 136CHECK | B8: Accounts Payable | C8: =INDEX('13 weeks CF'!$C$9:$C$59,MATCH(Table1[[#This Row],[Category]],'13 weeks CF'!$C$9:$C$59,0)) -> Accounts Payable | E8: ETERNIX | F8: Professional Fees | G8: =INDEX('13 weeks CF'!$C$9:$C$59,MATCH(Table2[[#This Row],[Category]],'13 weeks CF'!$C$9:$C$59,0)) -> Professional Fees
A9: 150CHECK | B9: Accounts Payable | C9: =INDEX('13 weeks CF'!$C$9:$C$59,MATCH(Table1[[#This Row],[Category]],'13 weeks CF'!$C$9:$C$59,0)) -> Accounts Payable | E9: IRS | F9: Tax Distributions | G9: =INDEX('13 weeks CF'!$C$9:$C$59,MATCH(Table2[[#This Row],[Category]],'13 weeks CF'!$C$9:$C$59,0)) -> Tax Distributions
A10: 151CHECK | B10: Accounts Payable | C10: =INDEX('13 weeks CF'!$C$9:$C$59,MATCH(Table1[[#This Row],[Category]],'13 weeks CF'!$C$9:$C$59,0)) -> Accounts Payable | E10: KRYPTONIX | F10: Dues & Subscriptions | G10: =INDEX('13 weeks CF'!$C$9:$C$59,MATCH(Table2[[#This Row],[Category]],'13 weeks CF'!$C$9:$C$59,0)) -> Dues & Subscriptions
A11: 193CHECK | B11: Accounts Payable | C11: =INDEX('13 weeks CF'!$C$9:$C$59,MATCH(Table1[[#This Row],[Category]],'13 weeks CF'!$C$9:$C$59,0)) -> Accounts Payable | E11: DISCOVER | F11: Credit Cards | G11: =INDEX('13 weeks CF'!$C$9:$C$59,MATCH(Table2[[#This Row],[Category]],'13 weeks CF'!$C$9:$C$59,0)) -> Credit Cards
A12: 198CHECK | B12: Accounts Payable | C12: =INDEX('13 weeks CF'!$C$9:$C$59,MATCH(Table1[[#This Row],[Category]],'13 weeks CF'!$C$9:$C$59,0)) -> Accounts Payable | E12: FRACTALIX | F12: Lease Payments | G12: =INDEX('13 weeks CF'!$C$9:$C$59,MATCH(Table2[[#This Row],[Category]],'13 weeks CF'!$C$9:$C$59,0)) -> Lease Payments
A13: 199CHECK | B13: Accounts Payable | C13: =INDEX('13 weeks CF'!$C$9:$C$59,MATCH(Table1[[#This Row],[Category]],'13 weeks CF'!$C$9:$C$59,0)) -> Accounts Payable | E13: GLOWTECH | F13: Technology | G13: =INDEX('13 weeks CF'!$C$9:$C$59,MATCH(Table2[[#This Row],[Category]],'13 weeks CF'!$C$9:$C$59,0)) -> Technology
... A23: 431CHECK | B23: Accounts Payable | C23: =INDEX('13 weeks CF'!$C$9:$C$59,MATCH(Table1[[#This Row],[Category]],'13 weeks CF'!$C$9:$C$59,0)) -> Accounts Payable | E23: JUNCTIX | F23: Other Non-operating Outflows | G23: =INDEX('13 weeks CF'!$C$9:$C$59,MATCH(Table2[[#This Row],[Category]],'13 weeks CF'!$C$9:$C$59,0)) -> Other Non-operating Outflows

Sheet Formula Helpers
B2: Formula helpers for 13 Week Cash Flow Modeling
B4: Week end date | D4: =[date]+7-WEEKDAY([date]+7-7)
B6: Exact match for Unique ID | D6: =INDEX(ID_Matches[CATEGORY],MATCH([unique id],ID_Matches[UNIQUE IDENTIFIER],0))
B8: Text contains for Unique ID | D8: =INDEX([table 2 category],MATCH(TRUE,ISNUMBER(SEARCH([unique id contains],[unique id from actuals])),0)))
B10: Complete formula | D10: =IFERROR(INDEX(Table1[CATEGORY],MATCH([unique ID from actuals],Table1[UNIQUE IDENTIFIER],0)),INDEX(Table2[CATEGORY],MATCH(TRUE,ISNUMBER(SEARCH(Table2[UNIQUE IDENTIFIER CONTAINS],[unique Id from actuals])),0)))
B12: SUMPRODUCT for Variance Report | D12: =SUMPRODUCT([result range]*([date range]=[date])*([category range]=[category]))
